Workbook
Name IQ_CH: 110000
Name IQ_CQ: 5000
Name IQ_CY: 10000
Name IQ_DAILY: 500000
Name IQ_FH: 100000
Name IQ_FQ: 500
Name IQ_FY: 1000
Name IQ_LTM: 2000
Name IQ_MONTH: 15000
Name IQ_NTM: 6000
Name IQ_WEEK: 50000
Name IQ_YTD: 3000
Name UPDATE: #REF!
Name UPDATE: 'Data Sheet'!$E$1

Sheet one page
B2: ='Data Sheet'!B1&" - One Page Report" -> HINDUSTAN UNILEVER LTD - One Page Report
C4: ='input sheet'!I1 -> Hindustan Unilever Limited (HUL) is an Indian fast-moving consumer goods company, headquartered in Mumbai.[3] It is a subsidiary of the Anglo-Dutch company Unilever. Its products include foods, beverages, cleaning agents, personal care products and other consumer staples. However, the integration of GSK's 3,800 employees remained uncertain as HUL stated there was no clause for retention of employees in the deal.
B5: INR (Crs)
B6: Key Financial Metrics | C6: ='Data Sheet'!G16 -> 44286 | D6: ='Data Sheet'!H16 -> 44651 | E6: ='Data Sheet'!I16 -> 45016 | F6: ='Data Sheet'!J16 -> 45382 | G6: ='Data Sheet'!K16 -> 45747 | I6: Share Price - 5Y
B8: Total sales | C8: ='Data Sheet'!G17 -> 47028 | D8: ='Data Sheet'!H17 -> 52446 | E8: ='Data Sheet'!I17 -> 60580 | F8: ='Data Sheet'!J17 -> 61896 | G8: ='Data Sheet'!K17 -> 63121
B9: Sales Growth (Y-O-Y) | C9: ='Profit & Loss'!G28 -> 0.18211296 | D9: ='Profit & Loss'!H28 -> 0.11520796 | E9: ='Profit & Loss'!I28 -> 0.15509286 | F9: ='Profit & Loss'!J28 -> 0.021723341 | G9: ='Profit & Loss'!K28 -> 0.019791263
B10: Gross Prifit Margin (%) | C10: ='Profit & Loss'!G30 -> 0.49491792 | D10: ='Profit & Loss'!H30 -> 0.49347901 | E10: ='Profit & Loss'!I30 -> 0.46059756 | F10: ='Profit & Loss'!J30 -> 0.50458834 | G10: ='Profit & Loss'!K30 -> 0.49687109
B11: EBITDA Margin (%) | C11: ='Profit & Loss'!G31 -> 0.24721443 | D11: ='Profit & Loss'!H31 -> 0.24514739 | E11: ='Profit & Loss'!I31 -> 0.23352592 | F11: ='Profit & Loss'!J31 -> 0.23683275 | G11: ='Profit & Loss'!K31 -> 0.23515153
B12: EBIT Margin (%) | C12: ='Profit & Loss'!G33 -> 0.22799183 | D12: ='Profit & Loss'!H33 -> 0.22852076 | E12: ='Profit & Loss'!I33 -> 0.22215253 | F12: ='Profit & Loss'!J33 -> 0.23038645 | G12: ='Profit & Loss'!K33 -> 0.23462873
B13: Net profit Margin (%) | C13: ='Profit & Loss'!G35 -> 0.1700051 | D13: ='Profit & Loss'!H35 -> 0.16929794 | E13: ='Profit & Loss'!I35 -> 0.16705183 | F13: ='Profit & Loss'!J35 -> 0.16603658 | G13: ='Profit & Loss'!K35 -> 0.16870772
B14: Earnings Per Share (In Rs) | C14: ='Profit & Loss'!G13 -> 34.027068 | D14: ='Profit & Loss'!H13 -> 37.789411 | E14: ='Profit & Loss'!I13 -> 43.071161 | F14: ='Profit & Loss'!J13 -> 43.73936 | G14: ='Profit & Loss'!K13 -> 45.322608
B15: EPS Growth (Y-O-Y) | C15: ='Profit & Loss'!G37 -> 0.091609332 | D15: ='Profit & Loss'!H37 -> 0.11056911 | E15: ='Profit & Loss'!I37 -> 0.13976799 | F15: ='Profit & Loss'!J37 -> 0.015513834 | G15: ='Profit & Loss'!K37 -> 0.036197334
B16: Dividend Per Share (In Rs) | C16: ='Profit & Loss'!G39 -> 40.506895 | D16: ='Profit & Loss'!H39 -> 34.005788 | E16: ='Profit & Loss'!I39 -> 39.006639 | F16: ='Profit & Loss'!J39 -> 42.00715 | G16: ='Profit & Loss'!K39 -> 53.009023
B17: DPS Growth (Y-O-Y) | C17: ='Profit & Loss'!G40 -> 0.6238764 | D17: ='Profit & Loss'!H40 -> -0.16049383 | E17: ='Profit & Loss'!I40 -> 0.14705882 | F17: ='Profit & Loss'!J40 -> 0.076923077 | G17: ='Profit & Loss'!K40 -> 0.26190476
B20: Key Financial Ratios | C20: =C6 -> 44286 | D20: =D6 -> 44651 | E20: =E6 -> 45016 | F20: =F6 -> 45382 | G20: =G6 -> 45747 | I20: VOLUME- 5Y
B22: Price To Earnings | C22: ='Profit & Loss'!G14 -> 71.457816 | D22: ='Profit & Loss'!H14 -> 54.212277 | E22: ='Profit & Loss'!I14 -> 59.444648 | F22: ='Profit & Loss'!J14 -> 51.769162 | G22: ='Profit & Loss'!K14 -> 49.839365
B23: Ev / EBITDA | C23: ='Profit & Loss'!G47 -> 48.755741 | D23: ='Profit & Loss'!H47 -> 37.220798 | E23: ='Profit & Loss'!I47 -> 42.278987 | F23: ='Profit & Loss'!J47 -> 35.879438 | G23: ='Profit & Loss'!K47 -> 35.358984
B24: EV / Sales | C24: ='Profit & Loss'!G48 -> 12.053122 | D24: ='Profit & Loss'!H48 -> 9.1245816 | E24: ='Profit & Loss'!I48 -> 9.8732393 | F24: ='Profit & Loss'!J48 -> 8.4974259 | G24: ='Profit & Loss'!K48 -> 8.3147193
B25: Price To Book Value | C25: ='Profit & Loss'!G50 -> 11.983581 | D25: ='Profit & Loss'!H50 -> 9.8112718 | E25: ='Profit & Loss'!I50 -> 11.958887 | F25: ='Profit & Loss'!J50 -> 10.387592 | G25: ='Profit & Loss'!K50 -> 10.743278
B26: Return on Equity (%) | C26: ='Balance Sheet'!G23 -> 0.16770147 | D26: ='Balance Sheet'!H23 -> 0.18097878 | E26: ='Balance Sheet'!I23 -> 0.20117684 | F26: ='Balance Sheet'!J23 -> 0.20065211 | G26: ='Balance Sheet'!K23 -> 0.21555807
B27: Return On Capital Employed (%) | C27: ='Balance Sheet'!G24 -> 0.38359301 | D27: ='Balance Sheet'!H24 -> 0.24514717 | E27: ='Balance Sheet'!I24 -> 0.26485088 | F27: ='Balance Sheet'!J24 -> 0.27363876 | G27: ='Balance Sheet'!K24 -> 0.28548847
B29: Top 10 Shareholders | C29: ='itc share price'!J46 -> No Of Shares | E29: ='itc share price'!K46 -> % Holding | F29: ='itc share price'!L46 -> Market value (In Crs) | I29: Shareholder Pattern
B31: ='input sheet'!C35 -> UNILEVER PLC | C31: ='input sheet'!D35 -> 111.43701 | E31: ='input sheet'!E35 -> 0.4743 | F31: ='input sheet'!G35 -> 281813.07
B32: ='input sheet'!C36 -> LICI INDEX PLUS FLEXI SMART GROWTH FUND | C32: ='input sheet'!D36 -> 15.131235 | E32: ='input sheet'!E36 -> 0.0644 | F32: ='input sheet'!G36 -> 38265.381
B33: ='input sheet'!C37 -> UNILEVER GROUP LIMITED | C33: ='input sheet'!D37 -> 10.673946 | E33: ='input sheet'!E37 -> 0.0454 | F33: ='input sheet'!G37 -> 26993.342
B34: ='input sheet'!C38 -> UNILEVER OVERSEAS HOLDINGS AG | C34: ='input sheet'!D38 -> 6.878432 | E34: ='input sheet'!E38 -> 0.0293 | F34: ='input sheet'!G38 -> 17394.867
B35: ='input sheet'!C39 -> UNILEVER UK&CN HOLDINGS LIMITED | C35: ='input sheet'!D39 -> 6.008625 | E35: ='input sheet'!E39 -> 0.0256 | F35: ='input sheet'!G39 -> 15195.212
B36: ='input sheet'!C40 -> UNILEVER SOUTH INDIA ESTATES LIMITED | C36: ='input sheet'!D40 -> 5.27472 | E36: ='input sheet'!E40 -> 0.0224 | F36: ='input sheet'!G40 -> 13339.239
B37: ='input sheet'!C41 -> SBI NIFTY 200 QUALITY 30 ETF | C37: ='input sheet'!D41 -> 3.9300417 | E37: ='input sheet'!E41 -> 0.0167 | F37: ='input sheet'!G41 -> 9938.6825
B38: ='input sheet'!C42 -> ICICI PRUDENTIAL MUTUAL FUND | C38: ='input sheet'!D42 -> 3.4360582 | E38: ='input sheet'!E42 -> 0.0146 | F38: ='input sheet'!G42 -> 8689.4476
B39: ='input sheet'!C43 -> UNILEVER ASSAM ESTATES LIMITED | C39: ='input sheet'!D43 -> 3.282048 | E39: ='input sheet'!E43 -> 0.014 | F39: ='input sheet'!G43 -> 8299.9712
B40: ='input sheet'!C44 -> UNILEVER OVERSEAS HOLDINGS B V | C40: ='input sheet'!D44 -> 1.8865 | E40: ='input sheet'!E44 -> 0.008 | F40: ='input sheet'!G44 -> 4770.7699
B42: Managerial Remuneration | C42: Designation | D42: Remuneration | F42: X of Median Salaray | I42: Capital Structure
B44: Rohit Jawa | C44: CEO & MD | E44: 22.392321 | G44: 146 | I44: Share Price on xxx | K44: ='Data Sheet'!B8 -> 2528.9
B45: Ritesh Tiwari | C45: Executive Director & CFO | E45: 8.5560788 | G45: 59 | I45: Number Of shares o/s | K45: ='Data Sheet'!B6 -> 244.7425
B46: BP Biddappa | C46: Executive Director & SO | E46: 7.9375613 | G46: 66 | I46: Market Capitalization | K46: =K45*K44 -> 618929.3
B47: Dev Bajpai | C47: Executive Director & CS | E47: 10.379239 | G47: 83 | I47: Less: Cash & Equivalents | K47: ='Data Sheet'!K69*-1 -> -7554
I48: Add: Total Debt | K48: ='Data Sheet'!K59 -> 1648 | P48: 10000000
I49: Add: Minority Interest | K49: 367.89
I50: Enerprise Value | K50: =SUM(K46:K49) -> 613391.19
B52: Resent Update
B54: Hindustan Unilever Cuts Prices on Dove, Horlicks, Lifebuoy, Lux, Clinic Plus, Kissan Jam, BRU Coffee & More
B55: GST 2.0 Impact: Dove shampoo, Kissan jam, Horlicks among HUL products to get cheaper
B56: India’s Biggest Consumer Goods Giant Hindustan Unilever Slashes Prices Of Popular Products After GST Rate Cut
B57: Hindustan Unilever Board Meeting Intimation for Consideration Of Unaudited Standalone
B58: riya Nair was appointed as the new Managing Director & Chief Executive Officer of HUL, effective 1 August 2025, succeeding Rohit Jawa
B59: HUL is pushing its portfolio revamp (e.g., extended premium variants, new categories under existing brands) to drive growth.
B60: Board meeting scheduled for 23 October 2025 to consider unaudited financial results for quarter/half year ending 30 September 2025.
B61: Competitive pressure from nimble & newer/ direct-to-consumer (D2C) brands in premium / beauty / skincare segments.
B62: Investors expect execution under the new CEO to deliver: premiumization, innovation, cost control. If not, the high valuation might become a burden.
B65: Source: Screener.in, EquityMaster, Wikipedia, Yahoo Finance, Annual Report 2025

Sheet HistoricalFS
B3: ='Data Sheet'!B1 -> HINDUSTAN UNILEVER LTD
B4: =CONCATENATE("(",B3," |"," BSE Code :",'Data Sheet'!B4,")") -> (HINDUSTAN UNILEVER LTD | BSE Code :500696)
B5: =CONCATENATE(,"INR ",'Data Sheet'!B8) -> INR 2528.9
B6: 52 week (High - INR 3,022.9 & Low - 2,136.0)
B10: ="Historical Financial Statement - "&'Data Sheet'!B1 -> Historical Financial Statement - HINDUSTAN UNILEVER LTD
B11: Years | C11: ='[1]Data Sheet'!B16 -> 42460 | D11: ='[1]Data Sheet'!C16 -> 42825 | E11: ='[1]Data Sheet'!D16 -> 43190 | F11: ='[1]Data Sheet'!E16 -> 43555 | G11: ='[1]Data Sheet'!F16 -> 43921 | H11: ='[1]Data Sheet'!G16 -> 44286 | I11: ='[1]Data Sheet'!H16 -> 44651 | J11: ='[1]Data Sheet'!I16 -> 45016 | ... L11: ='[1]Data Sheet'!K16 -> 45747 | M11: LTM
A13: # | B13: Income Statement
B14: Sales | C14: ='Data Sheet'!B17 -> 32186 | D14: ='Data Sheet'!C17 -> 33162 | E14: ='Data Sheet'!D17 -> 35545 | F14: ='Data Sheet'!E17 -> 39310 | G14: ='Data Sheet'!F17 -> 39783 | H14: ='Data Sheet'!G17 -> 47028 | I14: ='Data Sheet'!H17 -> 52446 | J14: ='Data Sheet'!I17 -> 60580 | ... L14: ='Data Sheet'!K17 -> 63121 | M14: =IFERROR(SUM('Data Sheet'!H42:K42),0) -> 63928
B15: Sales Growth | C15: - | D15: =D14/C14-1 -> 0.030323743 | E15: =E14/D14-1 -> 0.071859357 | F15: =F14/E14-1 -> 0.10592207 | G15: =G14/F14-1 -> 0.012032562 | H15: =H14/G14-1 -> 0.18211296 | I15: =I14/H14-1 -> 0.11520796 | J15: =J14/I14-1 -> 0.15509286 | K15: =K14/J14-1 -> 0.021723341 | ... M15: =M14/L14-1 -> 0.012784969
B17: COGS | C17: =IFERROR(SUM('Data Sheet'!B18,'Data Sheet'!B20:B22)-'Data Sheet'!B19,0) -> 18222 | D17: =IFERROR(SUM('Data Sheet'!C18,'Data Sheet'!C20:C22)-'Data Sheet'!C19,0) -> 18675 | E17: =IFERROR(SUM('Data Sheet'!D18,'Data Sheet'!D20:D22)-'Data Sheet'!D19,0) -> 19314 | F17: =IFERROR(SUM('Data Sheet'!E18,'Data Sheet'!E20:E22)-'Data Sheet'!E19,0) -> 21081 | G17: =IFERROR(SUM('Data Sheet'!F18,'Data Sheet'!F20:F22)-'Data Sheet'!F19,0) -> 20614 | H17: =IFERROR(SUM('Data Sheet'!G18,'Data Sheet'!G20:G22)-'Data Sheet'!G19,0) -> 25301 | I17: =IFERROR(SUM('Data Sheet'!H18,'Data Sheet'!H20:H22)-'Data Sheet'!H19,0) -> 29066 | J17: =IFERROR(SUM('Data Sheet'!I18,'Data Sheet'!I20:I22)-'Data Sheet'!I19,0) -> 35381 | ... L17: =IFERROR(SUM('Data Sheet'!K18,'Data Sheet'!K20:K22)-'Data Sheet'!K19,0) -> 34529 | M17: =IFERROR(SUM('Data Sheet'!H43:K43),0) -> 49111
B18: COGS % Sales | C18: =C17/C14 -> 0.56614677 | D18: =D17/D14 -> 0.56314456 | E18: =E17/E14 -> 0.54336756 | F18: =F17/F14 -> 0.53627576 | G18: =G17/G14 -> 0.51816102 | H18: =H17/H14 -> 0.53799864 | I18: =I17/I14 -> 0.55420814 | J18: =J17/J14 -> 0.58403764 | ... M18: =M17/M14 -> 0.76822363
B20: Gross Profit | C20: =C14-C17 -> 13964 | D20: =D14-D17 -> 14487 | E20: =E14-E17 -> 16231 | F20: =F14-F17 -> 18229 | G20: =G14-G17 -> 19169 | H20: =H14-H17 -> 21727 | I20: =I14-I17 -> 23380 | J20: =J14-J17 -> 25199 | ... M20: =M14-M17 -> 14817
B21: Gross Margins | C21: =C20/C14 -> 0.43385323 | D21: =D20/D14 -> 0.43685544 | E21: =E20/E14 -> 0.45663244 | F21: =F20/F14 -> 0.46372424 | G21: =G20/G14 -> 0.48183898 | H21: =H20/H14 -> 0.46200136 | I21: =I20/I14 -> 0.44579186 | J21: =J20/J14 -> 0.41596236 | ... M21: =M20/M14 -> 0.23177637
B23: Selling & General Expenses | C23: =IFERROR(SUM('Data Sheet'!B23:B24),0) -> 8054 | D23: =IFERROR(SUM('Data Sheet'!C23:C24),0) -> 8159 | E23: =IFERROR(SUM('Data Sheet'!D23:D24),0) -> 8732 | F23: =IFERROR(SUM('Data Sheet'!E23:E24),0) -> 9349 | G23: =IFERROR(SUM('Data Sheet'!F23:F24),0) -> 9308 | H23: =IFERROR(SUM('Data Sheet'!G23:G24),0) -> 10101 | I23: =IFERROR(SUM('Data Sheet'!H23:H24),0) -> 10523 | J23: =IFERROR(SUM('Data Sheet'!I23:I24),0) -> 11052 | ... L23: =IFERROR(SUM('Data Sheet'!K23:K24),0) -> 13749
B24: S&G Exp % Sales | C24: =C23/C14 -> 0.25023302 | D24: =D23/D14 -> 0.24603462 | E24: =E23/E14 -> 0.24566043 | F24: =F23/F14 -> 0.23782752 | G24: =G23/G14 -> 0.23396928 | H24: =H23/H14 -> 0.21478694 | I24: =I23/I14 -> 0.20064447 | J24: =J23/J14 -> 0.18243645 | ... M24: =M23/M14 -> 0
B26: EBITDA | C26: =C20-C23 -> 5910 | D26: =D20-D23 -> 6328 | E26: =E20-E23 -> 7499 | F26: =F20-F23 -> 8880 | G26: =G20-G23 -> 9861 | H26: =H20-H23 -> 11626 | I26: =I20-I23 -> 12857 | J26: =J20-J23 -> 14147 | ... L26: =L20-L23 -> 14843 | M26: =IFERROR(SUM('Data Sheet'!H52:K52),0) -> 15973
B27: EBITDA Margins | C27: =C26/C14 -> 0.18362021 | D27: =D26/D14 -> 0.19082082 | E27: =E26/E14 -> 0.21097201 | F27: =F26/F14 -> 0.22589672 | G27: =G26/G14 -> 0.24786969 | H27: =H26/H14 -> 0.24721443 | I27: =I26/I14 -> 0.24514739 | J27: =J26/J14 -> 0.23352592 | ... M27: =M26/M14 -> 0.24985922
B29: Interest | C29: ='Data Sheet'!B27 -> 17 | D29: ='Data Sheet'!C27 -> 35 | E29: ='Data Sheet'!D27 -> 26 | F29: ='Data Sheet'!E27 -> 33 | G29: ='Data Sheet'!F27 -> 118 | H29: ='Data Sheet'!G27 -> 117 | I29: ='Data Sheet'!H27 -> 106 | J29: ='Data Sheet'!I27 -> 114 | ... L29: ='Data Sheet'!K27 -> 395 | M29: =IFERROR(SUM('Data Sheet'!H46:K46),0) -> 429
B30: Interest % Sales | C30: =C29/C14 -> 0.00052817995 | D30: =D29/D14 -> 0.0010554249 | E30: =E29/E14 -> 0.00073146715 | F30: =F29/F14 -> 0.00083948105 | G30: =G29/G14 -> 0.002966091 | H30: =H29/H14 -> 0.0024878796 | I30: =I29/I14 -> 0.0020211265 | J30: =J29/J14 -> 0.0018818092 | ... M30: =M29/M14 -> 0.0067106745
B32: Depreciation | C32: ='Data Sheet'!B26 -> 353 | D32: ='Data Sheet'!C26 -> 432 | E32: ='Data Sheet'!D26 -> 520 | F32: ='Data Sheet'!E26 -> 565 | G32: ='Data Sheet'!F26 -> 1002 | H32: ='Data Sheet'!G26 -> 1074 | I32: ='Data Sheet'!H26 -> 1091 | J32: ='Data Sheet'!I26 -> 1137 | ... L32: ='Data Sheet'!K26 -> 1355 | M32: =IFERROR(SUM('Data Sheet'!H45:K45),0) -> 1387
B33: Depreciation%Sales | C33: =C32/C14 -> 0.010967501 | D33: =D32/D14 -> 0.013026959 | E33: =E32/E14 -> 0.014629343 | F33: =F32/F14 -> 0.014372933 | G33: =G32/G14 -> 0.025186638 | H33: =H32/H14 -> 0.022837459 | I33: =I32/I14 -> 0.020802349 | J33: =J32/J14 -> 0.01876857 | ... M33: =M32/M14 -> 0.021696283
B35: EBIT | C35: =C26-C32 -> 5557 | D35: =D26-D32 -> 5896 | E35: =E26-E32 -> 6979 | F35: =F26-F32 -> 8315 | G35: =G26-G32 -> 8859 | H35: =H26-H32 -> 10552 | I35: =I26-I32 -> 11766 | J35: =J26-J32 -> 13010 | ... M35: =M26-M32 -> 14586
B36: EBIT % Sales | C36: =C35/C14 -> 0.17265271 | D36: =D35/D14 -> 0.17779386 | E36: =E35/E14 -> 0.19634266 | F36: =F35/F14 -> 0.21152379 | G36: =G35/G14 -> 0.22268306 | H36: =H35/H14 -> 0.22437697 | I36: =I35/I14 -> 0.22434504 | J36: =J35/J14 -> 0.21475735 | ... M36: =M35/M14 -> 0.22816293
B38: Earnings Before Tax | C38: =IFERROR(C26-SUM(C32,C29),0) -> 5540 | D38: =IFERROR(D26-SUM(D32,D29),0) -> 5861 | E38: =IFERROR(E26-SUM(E32,E29),0) -> 6953 | F38: =IFERROR(F26-SUM(F32,F29),0) -> 8282 | G38: =IFERROR(G26-SUM(G32,G29),0) -> 8741 | H38: =IFERROR(H26-SUM(H32,H29),0) -> 10435 | I38: =IFERROR(I26-SUM(I32,I29),0) -> 11660 | J38: =IFERROR(J26-SUM(J32,J29),0) -> 12896 | ... M38: =IFERROR(M26-SUM(M32,M29),0) -> 14157
B39: EBT % Sales | C39: =C38/C14 -> 0.17212453 | D39: =D38/D14 -> 0.17673844 | E39: =E38/E14 -> 0.1956112 | F39: =F38/F14 -> 0.2106843 | G39: =G38/G14 -> 0.21971696 | H39: =H38/H14 -> 0.22188909 | I39: =I38/I14 -> 0.22232391 | J39: =J38/J14 -> 0.21287554 | ... M39: =M38/M14 -> 0.22145226
B41: Tax | C41: =IFERROR('Data Sheet'!B29,0) -> 1875 | D41: =IFERROR('Data Sheet'!C29,0) -> 1977 | E41: =IFERROR('Data Sheet'!D29,0) -> 2079 | F41: =IFERROR('Data Sheet'!E29,0) -> 2544 | G41: =IFERROR('Data Sheet'!F29,0) -> 2409 | H41: =IFERROR('Data Sheet'!G29,0) -> 2606 | I41: =IFERROR('Data Sheet'!H29,0) -> 2987 | J41: =IFERROR('Data Sheet'!I29,0) -> 3201 | ... L41: =IFERROR('Data Sheet'!K29,0) -> 3744 | M41: =IFERROR(SUM('Data Sheet'!H48:K48),0) -> 3362
B42: Effective Tax Rate | C42: =C41/C38 -> 0.33844765 | D42: =D41/D38 -> 0.33731445 | E42: =E41/E38 -> 0.29900762 | F42: =F41/F38 -> 0.30717218 | G42: =G41/G38 -> 0.27559776 | H42: =H41/H38 -> 0.24973646 | I42: =I41/I38 -> 0.25617496 | J42: =J41/J38 -> 0.2482165 | ... M42: =M41/M38 -> 0.23747969
B44: Net Profit | C44: =IFERROR(C38-C41,0) -> 3665 | D44: =IFERROR(D38-D41,0) -> 3884 | E44: =IFERROR(E38-E41,0) -> 4874 | F44: =IFERROR(F38-F41,0) -> 5738 | G44: =IFERROR(G38-G41,0) -> 6332 | H44: =IFERROR(H38-H41,0) -> 7829 | I44: =IFERROR(I38-I41,0) -> 8673 | J44: =IFERROR(J38-J41,0) -> 9695 | ... M44: =IFERROR(M38-M41,0) -> 10795
B45: Net Margins | C45: =C44/C14 -> 0.11386938 | D45: =D44/D14 -> 0.11712201 | E45: =E44/E14 -> 0.13712196 | F45: =F44/F14 -> 0.14596795 | G45: =G44/G14 -> 0.15916346 | H45: =H44/H14 -> 0.16647529 | I45: =I44/I14 -> 0.16537009 | J45: =J44/J14 -> 0.16003632 | ... M45: =M44/M14 -> 0.16886184
B47: No of Equity Shares | C47: =IFERROR('Data Sheet'!B93,0) -> 216.39 | D47: =IFERROR('Data Sheet'!C93,0) -> 216.43 | E47: =IFERROR('Data Sheet'!D93,0) -> 216.45 | F47: =IFERROR('Data Sheet'!E93,0) -> 216.47 | G47: =IFERROR('Data Sheet'!F93,0) -> 216.48 | H47: =IFERROR('Data Sheet'!G93,0) -> 234.96 | I47: =IFERROR('Data Sheet'!H93,0) -> 234.96 | J47: =IFERROR('Data Sheet'!I93,0) -> 234.96 | ... L47: =IFERROR('Data Sheet'!K93,0) -> 234.96 | M47: =L47 -> 234.96
B49: Earnings per Share | C49: =IFERROR(C44/C47,0) -> 16.937012 | D49: =IFERROR(D44/D47,0) -> 17.945756 | E49: =IFERROR(E44/E47,0) -> 22.517903 | F49: =IFERROR(F44/F47,0) -> 26.507137 | G49: =IFERROR(G44/G47,0) -> 29.249815 | H49: =IFERROR(H44/H47,0) -> 33.320565 | I49: =IFERROR(I44/I47,0) -> 36.912666 | J49: =IFERROR(J44/J47,0) -> 41.262343 | ... M49: =IFERROR(M44/M47,0) -> 45.94399
B50: EPS Growth % | D50: =IFERROR(D49/C49-1,0) -> 0.059558573 | E50: =IFERROR(E49/D49-1,0) -> 0.25477591 | F50: =IFERROR(F49/E49-1,0) -> 0.17715836 | G50: =IFERROR(G49/F49-1,0) -> 0.10346941 | H50: =IFERROR(H49/G49-1,0) -> 0.13917182 | I50: =IFERROR(I49/H49-1,0) -> 0.10780432 | J50: =IFERROR(J49/I49-1,0) -> 0.11783697 | K50: =IFERROR(K49/J49-1,0) -> -0.023723569 | ... M50: =IFERROR(M49/L49-1,0) -> 0.15466895
B52: Dividend per Share | C52: =IFERROR('Data Sheet'!B31/HistoricalFS!C47,0) -> 15.971163 | D52: =IFERROR('Data Sheet'!C31/HistoricalFS!D47,0) -> 16.966225 | E52: =IFERROR('Data Sheet'!D31/HistoricalFS!E47,0) -> 19.95842 | F52: =IFERROR('Data Sheet'!E31/HistoricalFS!F47,0) -> 21.952234 | G52: =IFERROR('Data Sheet'!F31/HistoricalFS!G47,0) -> 24.944568 | H52: =IFERROR('Data Sheet'!G31/HistoricalFS!H47,0) -> 40.506895 | I52: =IFERROR('Data Sheet'!H31/HistoricalFS!I47,0) -> 34.005788 | J52: =IFERROR('Data Sheet'!I31/HistoricalFS!J47,0) -> 39.006639 | ... M52: =IFERROR('Data Sheet'!L31/HistoricalFS!M47,0) -> 0
B53: Dividend payout ratio | C53: =IFERROR(C52/C49,0) -> 0.94297408 | D53: =IFERROR(D52/D49,0) -> 0.9454171 | E53: =IFERROR(E52/E49,0) -> 0.88633566 | F53: =IFERROR(F52/F49,0) -> 0.82816312 | G53: =IFERROR(G52/G49,0) -> 0.85281112 | H53: =IFERROR(H52/H49,0) -> 1.2156725 | I53: =IFERROR(I52/I49,0) -> 0.92124986 | J53: =IFERROR(J52/J49,0) -> 0.94533265 | ... M53: =IFERROR(M52/M49,0) -> 0
B55: Retained Earnings | C55: =IFERROR(IF(C49>C52,1-C53,0),0) -> 0.057025921 | D55: =IFERROR(IF(D49>D52,1-D53,0),0) -> 0.054582904 | E55: =IFERROR(IF(E49>E52,1-E53,0),0) -> 0.11366434 | F55: =IFERROR(IF(F49>F52,1-F53,0),0) -> 0.17183688 | G55: =IFERROR(IF(G49>G52,1-G53,0),0) -> 0.14718888 | H55: =IFERROR(IF(H49>H52,1-H53,0),0) -> 0 | I55: =IFERROR(IF(I49>I52,1-I53,0),0) -> 0.078750144 | J55: =IFERROR(IF(J49>J52,1-J53,0),0) -> 0.054667354 | ... M55: =IFERROR(IF(M49>M52,1-M53,0),0) -> 1
B62: ='Data Sheet'!B1 -> HINDUSTAN UNILEVER LTD
B63: =CONCATENATE("(",B62," |"," BSE Code :","500696",")") -> (HINDUSTAN UNILEVER LTD | BSE Code :500696)
B64: =CONCATENATE(,"INR ",'Data Sheet'!B8) -> INR 2528.9
B65: 52 week (High - INR 3,022.9 & Low - 2,136.0)
A70: # | B70: Balance Sheet
B71: Equity Share Capital | C71: =IFERROR('Data Sheet'!B57,0) -> 216 | D71: =IFERROR('Data Sheet'!C57,0) -> 216 | E71: =IFERROR('Data Sheet'!D57,0) -> 216 | F71: =IFERROR('Data Sheet'!E57,0) -> 216 | G71: =IFERROR('Data Sheet'!F57,0) -> 216 | H71: =IFERROR('Data Sheet'!G57,0) -> 235 | I71: =IFERROR('Data Sheet'!H57,0) -> 235 | J71: =IFERROR('Data Sheet'!I57,0) -> 235 | ... L71: =IFERROR('Data Sheet'!K57,0) -> 235
B72: Reserves | C72: =IFERROR('Data Sheet'!B58,0) -> 6357 | D72: =IFERROR('Data Sheet'!C58,0) -> 6528 | E72: =IFERROR('Data Sheet'!D58,0) -> 7065 | F72: =IFERROR('Data Sheet'!E58,0) -> 7651 | G72: =IFERROR('Data Sheet'!F58,0) -> 8013 | H72: =IFERROR('Data Sheet'!G58,0) -> 47439 | I72: =IFERROR('Data Sheet'!H58,0) -> 48826 | J72: =IFERROR('Data Sheet'!I58,0) -> 50069 | ... L72: =IFERROR('Data Sheet'!K58,0) -> 49167
B73: Borrowings | C73: =IFERROR('Data Sheet'!B59,0) -> 177 | D73: =IFERROR('Data Sheet'!C59,0) -> 277 | E73: =IFERROR('Data Sheet'!D59,0) -> 0 | F73: =IFERROR('Data Sheet'!E59,0) -> 99 | G73: =IFERROR('Data Sheet'!F59,0) -> 0 | H73: =IFERROR('Data Sheet'!G59,0) -> 0 | I73: =IFERROR('Data Sheet'!H59,0) -> 1043 | J73: =IFERROR('Data Sheet'!I59,0) -> 1219 | ... L73: =IFERROR('Data Sheet'!K59,0) -> 1648
B74: Other Liabilities | C74: =IFERROR('Data Sheet'!B60,0) -> 8043 | D74: =IFERROR('Data Sheet'!C60,0) -> 8685 | E74: =IFERROR('Data Sheet'!D60,0) -> 10581 | F74: =IFERROR('Data Sheet'!E60,0) -> 10663 | G74: =IFERROR('Data Sheet'!F60,0) -> 11924 | H74: =IFERROR('Data Sheet'!G60,0) -> 21066 | I74: =IFERROR('Data Sheet'!H60,0) -> 20402 | J74: =IFERROR('Data Sheet'!I60,0) -> 21554 | ... L74: =IFERROR('Data Sheet'!K60,0) -> 28813
B75: Total Liabilities | C75: =IFERROR('Data Sheet'!B61,0) -> 14793 | D75: =IFERROR('Data Sheet'!C61,0) -> 15706 | E75: =IFERROR('Data Sheet'!D61,0) -> 17862 | F75: =IFERROR('Data Sheet'!E61,0) -> 18629 | G75: =IFERROR('Data Sheet'!F61,0) -> 20153 | H75: =IFERROR('Data Sheet'!G61,0) -> 68740 | I75: =IFERROR('Data Sheet'!H61,0) -> 70506 | J75: =IFERROR('Data Sheet'!I61,0) -> 73077 | ... L75: =IFERROR('Data Sheet'!K61,0) -> 79863
B77: Fixed Assets Net Block | C77: =IFERROR('Data Sheet'!B62,0) -> 3258 | D77: =IFERROR('Data Sheet'!C62,0) -> 4419 | E77: =IFERROR('Data Sheet'!D62,0) -> 4528 | F77: =IFERROR('Data Sheet'!E62,0) -> 4715 | G77: =IFERROR('Data Sheet'!F62,0) -> 5479 | H77: =IFERROR('Data Sheet'!G62,0) -> 51443 | I77: =IFERROR('Data Sheet'!H62,0) -> 51473 | J77: =IFERROR('Data Sheet'!I62,0) -> 52678 | ... L77: =IFERROR('Data Sheet'!K62,0) -> 54335
B78: Capital Work in Progress | C78: =IFERROR('Data Sheet'!B63,0) -> 408 | D78: =IFERROR('Data Sheet'!C63,0) -> 229 | E78: =IFERROR('Data Sheet'!D63,0) -> 461 | F78: =IFERROR('Data Sheet'!E63,0) -> 406 | G78: =IFERROR('Data Sheet'!F63,0) -> 597 | H78: =IFERROR('Data Sheet'!G63,0) -> 745 | I78: =IFERROR('Data Sheet'!H63,0) -> 1313 | J78: =IFERROR('Data Sheet'!I63,0) -> 1132 | ... L78: =IFERROR('Data Sheet'!K63,0) -> 1009
B79: Investments | C79: =IFERROR('Data Sheet'!B64,0) -> 2592 | D79: =IFERROR('Data Sheet'!C64,0) -> 3794 | E79: =IFERROR('Data Sheet'!D64,0) -> 2873 | F79: =IFERROR('Data Sheet'!E64,0) -> 2716 | G79: =IFERROR('Data Sheet'!F64,0) -> 1255 | H79: =IFERROR('Data Sheet'!G64,0) -> 2709 | I79: =IFERROR('Data Sheet'!H64,0) -> 3521 | J79: =IFERROR('Data Sheet'!I64,0) -> 2882 | ... L79: =IFERROR('Data Sheet'!K64,0) -> 3810
B80: Other Assets | C80: =IFERROR('Data Sheet'!B65-SUM('Data Sheet'!B67:B69),0) -> 1536 | D80: =IFERROR('Data Sheet'!C65-SUM('Data Sheet'!C67:C69),0) -> 1810 | E80: =IFERROR('Data Sheet'!D65-SUM('Data Sheet'!D67:D69),0) -> 2692 | F80: =IFERROR('Data Sheet'!E65-SUM('Data Sheet'!E67:E69),0) -> 2645 | G80: =IFERROR('Data Sheet'!F65-SUM('Data Sheet'!F67:F69),0) -> 3793 | H80: =IFERROR('Data Sheet'!G65-SUM('Data Sheet'!G67:G69),0) -> 4035 | I80: =IFERROR('Data Sheet'!H65-SUM('Data Sheet'!H67:H69),0) -> 4021 | J80: =IFERROR('Data Sheet'!I65-SUM('Data Sheet'!I67:I69),0) -> 4377 | ... L80: =IFERROR('Data Sheet'!K65-SUM('Data Sheet'!K67:K69),0) -> 4921
B81: Total Non Current Assets | C81: =SUM(C77:C80) -> 7794 | D81: =SUM(D77:D80) -> 10252 | E81: =SUM(E77:E80) -> 10554 | F81: =SUM(F77:F80) -> 10482 | G81: =SUM(G77:G80) -> 11124 | H81: =SUM(H77:H80) -> 58932 | I81: =SUM(I77:I80) -> 60328 | J81: =SUM(J77:J80) -> 61069 | ... L81: =SUM(L77:L80) -> 64075
B83: Receivables | C83: =IFERROR('Data Sheet'!B67,0) -> 1264 | D83: =IFERROR('Data Sheet'!C67,0) -> 1085 | E83: =IFERROR('Data Sheet'!D67,0) -> 1310 | F83: =IFERROR('Data Sheet'!E67,0) -> 1816 | G83: =IFERROR('Data Sheet'!F67,0) -> 1149 | H83: =IFERROR('Data Sheet'!G67,0) -> 1758 | I83: =IFERROR('Data Sheet'!H67,0) -> 2236 | J83: =IFERROR('Data Sheet'!I67,0) -> 3079 | ... L83: =IFERROR('Data Sheet'!K67,0) -> 3819
B84: Inventory | C84: =IFERROR('Data Sheet'!B68,0) -> 2726 | D84: =IFERROR('Data Sheet'!C68,0) -> 2541 | E84: =IFERROR('Data Sheet'!D68,0) -> 2513 | F84: =IFERROR('Data Sheet'!E68,0) -> 2574 | G84: =IFERROR('Data Sheet'!F68,0) -> 2767 | H84: =IFERROR('Data Sheet'!G68,0) -> 3579 | I84: =IFERROR('Data Sheet'!H68,0) -> 4096 | J84: =IFERROR('Data Sheet'!I68,0) -> 4251 | ... L84: =IFERROR('Data Sheet'!K68,0) -> 4415
B85: Cash & Bank | C85: =IFERROR('Data Sheet'!B69,0) -> 3009 | D85: =IFERROR('Data Sheet'!C69,0) -> 1828 | E85: =IFERROR('Data Sheet'!D69,0) -> 3485 | F85: =IFERROR('Data Sheet'!E69,0) -> 3757 | G85: =IFERROR('Data Sheet'!F69,0) -> 5113 | H85: =IFERROR('Data Sheet'!G69,0) -> 4471 | I85: =IFERROR('Data Sheet'!H69,0) -> 3846 | J85: =IFERROR('Data Sheet'!I69,0) -> 4678 | ... L85: =IFERROR('Data Sheet'!K69,0) -> 7554
B86: Total Current Assets | C86: =IFERROR(SUM(C83:C85),0) -> 6999 | D86: =IFERROR(SUM(D83:D85),0) -> 5454 | E86: =IFERROR(SUM(E83:E85),0) -> 7308 | F86: =IFERROR(SUM(F83:F85),0) -> 8147 | G86: =IFERROR(SUM(G83:G85),0) -> 9029 | H86: =IFERROR(SUM(H83:H85),0) -> 9808 | I86: =IFERROR(SUM(I83:I85),0) -> 10178 | J86: =IFERROR(SUM(J83:J85),0) -> 12008 | ... L86: =IFERROR(SUM(L83:L85),0) -> 15788
B88: Total Assets | C88: =IFERROR(C86+C81,0) -> 14793 | D88: =IFERROR(D86+D81,0) -> 15706 | E88: =IFERROR(E86+E81,0) -> 17862 | F88: =IFERROR(F86+F81,0) -> 18629 | G88: =IFERROR(G86+G81,0) -> 20153 | H88: =IFERROR(H86+H81,0) -> 68740 | I88: =IFERROR(I86+I81,0) -> 70506 | J88: =IFERROR(J86+J81,0) -> 73077 | ... L88: =IFERROR(L86+L81,0) -> 79863
B90: Check | C90: =C88=C75 -> TRUE | D90: =D88=D75 -> TRUE | E90: =E88=E75 -> TRUE | F90: =F88=F75 -> TRUE | G90: =G88=G75 -> TRUE | H90: =H88=H75 -> TRUE | I90: =I88=I75 -> TRUE | J90: =J88=J75 -> TRUE | ... L90: =L88=L75 -> TRUE
A92: # | B92: Cash Flow Statements
B94: Cash from Operating Activities | C94: ='Data Sheet'!B82 -> 4171 | D94: ='Data Sheet'!C82 -> 5185 | E94: ='Data Sheet'!D82 -> 6059 | F94: ='Data Sheet'!E82 -> 5800 | G94: ='Data Sheet'!F82 -> 7623 | H94: ='Data Sheet'!G82 -> 9163 | I94: ='Data Sheet'!H82 -> 9048 | J94: ='Data Sheet'!I82 -> 9991 | ... L94: ='Data Sheet'!K82 -> 11886
B96: Cash from Investing Activities | C96: ='Data Sheet'!B83 -> -282 | D96: ='Data Sheet'!C83 -> -1173 | E96: ='Data Sheet'!D83 -> -1063 | F96: ='Data Sheet'!E83 -> -438 | G96: ='Data Sheet'!F83 -> 1791 | H96: ='Data Sheet'!G83 -> -1228 | I96: ='Data Sheet'!H83 -> -1728 | J96: ='Data Sheet'!I83 -> -1484 | ... L96: ='Data Sheet'!K83 -> 6473
B98: Cash from Financing Activities | C98: ='Data Sheet'!B84 -> -3864 | D98: ='Data Sheet'!C84 -> -4214 | E98: ='Data Sheet'!D84 -> -4975 | F98: ='Data Sheet'!E84 -> -5390 | G98: ='Data Sheet'!F84 -> -6819 | H98: ='Data Sheet'!G84 -> -9309 | I98: ='Data Sheet'!H84 -> -8015 | J98: ='Data Sheet'!I84 -> -8953 | ... L98: ='Data Sheet'!K84 -> -13101
B100: Net Cash Flow | C100: =IFERROR(C94+C96+C98,0) -> 25 | D100: =IFERROR(D94+D96+D98,0) -> -202 | E100: =IFERROR(E94+E96+E98,0) -> 21 | F100: =IFERROR(F94+F96+F98,0) -> -28 | G100: =IFERROR(G94+G96+G98,0) -> 2595 | H100: =IFERROR(H94+H96+H98,0) -> -1374 | I100: =IFERROR(I94+I96+I98,0) -> -695 | J100: =IFERROR(J94+J96+J98,0) -> -446 | ... L100: =IFERROR(L94+L96+L98,0) -> 5258

Sheet common size
B3: ='Data Sheet'!B1 -> HINDUSTAN UNILEVER LTD
B4: =CONCATENATE("(",B3," |"," BSE Code :",'Data Sheet'!B4,")") -> (HINDUSTAN UNILEVER LTD | BSE Code :500696)
B5: =CONCATENATE(,"INR ",'Data Sheet'!B8) -> INR 2528.9
B6: 52 week (High - INR 3,022.9 & Low - 2,136.0)
A8: # | B8: ="Common Size Statemment"&" "&" - "&'Data Sheet'!B1 -> Common Size Statemment - HINDUSTAN UNILEVER LTD
B10: Particular | C10: ='Data Sheet'!B16 -> 42460 | D10: ='Data Sheet'!C16 -> 42825 | E10: ='Data Sheet'!D16 -> 43190 | F10: ='Data Sheet'!E16 -> 43555 | G10: ='Data Sheet'!F16 -> 43921 | H10: ='Data Sheet'!G16 -> 44286 | I10: ='Data Sheet'!H16 -> 44651 | J10: ='Data Sheet'!I16 -> 45016 | ... L10: ='Data Sheet'!K16 -> 45747
B12: ='[2]Data Sheet'!A17 -> Sales | C12: ='Data Sheet'!B17/'Data Sheet'!B$17 -> 1 | D12: ='Data Sheet'!C17/'Data Sheet'!C$17 -> 1 | E12: ='Data Sheet'!D17/'Data Sheet'!D$17 -> 1 | F12: ='Data Sheet'!E17/'Data Sheet'!E$17 -> 1 | G12: ='Data Sheet'!F17/'Data Sheet'!F$17 -> 1 | H12: ='Data Sheet'!G17/'Data Sheet'!G$17 -> 1 | I12: ='Data Sheet'!H17/'Data Sheet'!H$17 -> 1 | J12: ='Data Sheet'!I17/'Data Sheet'!I$17 -> 1 | ... L12: ='Data Sheet'!K17/'Data Sheet'!K$17 -> 1
B13: ='[2]Data Sheet'!A18 -> Raw Material Cost | C13: ='Data Sheet'!B18/'Data Sheet'!B$17 -> 0.40961909 | D13: ='Data Sheet'!C18/'Data Sheet'!C$17 -> 0.41028888 | E13: ='Data Sheet'!D18/'Data Sheet'!D$17 -> 0.400422 | F13: ='Data Sheet'!E18/'Data Sheet'!E$17 -> 0.4030781 | G13: ='Data Sheet'!F18/'Data Sheet'!F$17 -> 0.39456552 | H13: ='Data Sheet'!G18/'Data Sheet'!G$17 -> 0.42827677 | I13: ='Data Sheet'!H18/'Data Sheet'!H$17 -> 0.43608664 | J13: ='Data Sheet'!I18/'Data Sheet'!I$17 -> 0.46924728 | ... L13: ='Data Sheet'!K18/'Data Sheet'!K$17 -> 0.43319973
B14: ='[2]Data Sheet'!A19 -> Change in Inventory | C14: ='Data Sheet'!B19/'Data Sheet'!B$17 -> -0.002578761 | D14: ='Data Sheet'!C19/'Data Sheet'!C$17 -> -0.0043423195 | E14: ='Data Sheet'!D19/'Data Sheet'!D$17 -> 0.0020256014 | F14: ='Data Sheet'!E19/'Data Sheet'!E$17 -> -0.00030526584 | G14: ='Data Sheet'!F19/'Data Sheet'!F$17 -> 0.0027147274 | H14: ='Data Sheet'!G19/'Data Sheet'!G$17 -> 0.0086118908 | I14: ='Data Sheet'!H19/'Data Sheet'!H$17 -> 0.00041947908 | J14: ='Data Sheet'!I19/'Data Sheet'!I$17 -> 0.0012380324 | ... L14: ='Data Sheet'!K19/'Data Sheet'!K$17 -> 0.002423916
B15: ='[2]Data Sheet'!A20 -> Power and Fuel | C15: ='Data Sheet'!B20/'Data Sheet'!B$17 -> 0.0096004474 | D15: ='Data Sheet'!C20/'Data Sheet'!C$17 -> 0.008895724 | E15: ='Data Sheet'!D20/'Data Sheet'!D$17 -> 0.0082993389 | F15: ='Data Sheet'!E20/'Data Sheet'!E$17 -> 0.0078351564 | G15: ='Data Sheet'!F20/'Data Sheet'!F$17 -> 0.0075157731 | H15: ='Data Sheet'!G20/'Data Sheet'!G$17 -> 0.0072084715 | I15: ='Data Sheet'!H20/'Data Sheet'!H$17 -> 0.0060633795 | J15: ='Data Sheet'!I20/'Data Sheet'!I$17 -> 0.0063387257 | ... L15: ='Data Sheet'!K20/'Data Sheet'!K$17 -> 0.0067647851
B16: ='[2]Data Sheet'!A21 -> Other Mfr. Exp | C16: ='Data Sheet'!B21/'Data Sheet'!B$17 -> 0.092151867 | D16: ='Data Sheet'!C21/'Data Sheet'!C$17 -> 0.087057475 | E16: ='Data Sheet'!D21/'Data Sheet'!D$17 -> 0.08434379 | F16: ='Data Sheet'!E21/'Data Sheet'!E$17 -> 0.077359451 | G16: ='Data Sheet'!F21/'Data Sheet'!F$17 -> 0.073046276 | H16: ='Data Sheet'!G21/'Data Sheet'!G$17 -> 0.060984945 | I16: ='Data Sheet'!H21/'Data Sheet'!H$17 -> 0.063951493 | J16: ='Data Sheet'!I21/'Data Sheet'!I$17 -> 0.062578409 | ... L16: ='Data Sheet'!K21/'Data Sheet'!K$17 -> 0.060740483
B17: ='[2]Data Sheet'!A22 -> Employee Cost | C17: ='Data Sheet'!B22/'Data Sheet'!B$17 -> 0.052196607 | D17: ='Data Sheet'!C22/'Data Sheet'!C$17 -> 0.052560159 | E17: ='Data Sheet'!D22/'Data Sheet'!D$17 -> 0.052328035 | F17: ='Data Sheet'!E22/'Data Sheet'!E$17 -> 0.047697787 | G17: ='Data Sheet'!F22/'Data Sheet'!F$17 -> 0.045748184 | H17: ='Data Sheet'!G22/'Data Sheet'!G$17 -> 0.050140342 | I17: ='Data Sheet'!H22/'Data Sheet'!H$17 -> 0.048526103 | J17: ='Data Sheet'!I22/'Data Sheet'!I$17 -> 0.047111258 | ... L17: ='Data Sheet'!K22/'Data Sheet'!K$17 -> 0.048747643
B18: ='[2]Data Sheet'!A23 -> Selling and admin | C18: ='Data Sheet'!B23/'Data Sheet'!B$17 -> 0.20943889 | D18: ='Data Sheet'!C23/'Data Sheet'!C$17 -> 0.20170677 | E18: ='Data Sheet'!D23/'Data Sheet'!D$17 -> 0.20402307 | F18: ='Data Sheet'!E23/'Data Sheet'!E$17 -> 0.19832104 | G18: ='Data Sheet'!F23/'Data Sheet'!F$17 -> 0.1915391 | H18: ='Data Sheet'!G23/'Data Sheet'!G$17 -> 0.16811261 | I18: ='Data Sheet'!H23/'Data Sheet'!H$17 -> 0.15566487 | J18: ='Data Sheet'!I23/'Data Sheet'!I$17 -> 0.14501486 | ... L18: ='Data Sheet'!K23/'Data Sheet'!K$17 -> 0.16940479
B19: ='[2]Data Sheet'!A24 -> Other Expenses | C19: ='Data Sheet'!B24/'Data Sheet'!B$17 -> 0.040794134 | D19: ='Data Sheet'!C24/'Data Sheet'!C$17 -> 0.044327845 | E19: ='Data Sheet'!D24/'Data Sheet'!D$17 -> 0.041637361 | F19: ='Data Sheet'!E24/'Data Sheet'!E$17 -> 0.039506487 | G19: ='Data Sheet'!F24/'Data Sheet'!F$17 -> 0.042430184 | H19: ='Data Sheet'!G24/'Data Sheet'!G$17 -> 0.046674322 | I19: ='Data Sheet'!H24/'Data Sheet'!H$17 -> 0.044979598 | J19: ='Data Sheet'!I24/'Data Sheet'!I$17 -> 0.037421591 | ... L19: ='Data Sheet'!K24/'Data Sheet'!K$17 -> 0.048414949
B20: ='[2]Data Sheet'!A25 -> Other Income | C20: ='Data Sheet'!B25/'Data Sheet'!B$17 -> 0.015099733 | D20: ='Data Sheet'!C25/'Data Sheet'!C$17 -> 0.018273928 | E20: ='Data Sheet'!D25/'Data Sheet'!D$17 -> 0.0099310733 | F20: ='Data Sheet'!E25/'Data Sheet'!E$17 -> 0.0081912999 | G20: ='Data Sheet'!F25/'Data Sheet'!F$17 -> 0.010657819 | H20: ='Data Sheet'!G25/'Data Sheet'!G$17 -> 0.0036148677 | I20: ='Data Sheet'!H25/'Data Sheet'!H$17 -> 0.0041757236 | J20: ='Data Sheet'!I25/'Data Sheet'!I$17 -> 0.0073951799 | ... L20: ='Data Sheet'!K25/'Data Sheet'!K$17 -> 0.020943901
B21: ='[2]Data Sheet'!A26 -> Depreciation | C21: ='Data Sheet'!B26/'Data Sheet'!B$17 -> 0.010967501 | D21: ='Data Sheet'!C26/'Data Sheet'!C$17 -> 0.013026959 | E21: ='Data Sheet'!D26/'Data Sheet'!D$17 -> 0.014629343 | F21: ='Data Sheet'!E26/'Data Sheet'!E$17 -> 0.014372933 | G21: ='Data Sheet'!F26/'Data Sheet'!F$17 -> 0.025186638 | H21: ='Data Sheet'!G26/'Data Sheet'!G$17 -> 0.022837459 | I21: ='Data Sheet'!H26/'Data Sheet'!H$17 -> 0.020802349 | J21: ='Data Sheet'!I26/'Data Sheet'!I$17 -> 0.01876857 | ... L21: ='Data Sheet'!K26/'Data Sheet'!K$17 -> 0.021466707
B22: ='[2]Data Sheet'!A27 -> Interest | C22: ='Data Sheet'!B27/'Data Sheet'!B$17 -> 0.00052817995 | D22: ='Data Sheet'!C27/'Data Sheet'!C$17 -> 0.0010554249 | E22: ='Data Sheet'!D27/'Data Sheet'!D$17 -> 0.00073146715 | F22: ='Data Sheet'!E27/'Data Sheet'!E$17 -> 0.00083948105 | G22: ='Data Sheet'!F27/'Data Sheet'!F$17 -> 0.002966091 | H22: ='Data Sheet'!G27/'Data Sheet'!G$17 -> 0.0024878796 | I22: ='Data Sheet'!H27/'Data Sheet'!H$17 -> 0.0020211265 | J22: ='Data Sheet'!I27/'Data Sheet'!I$17 -> 0.0018818092 | ... L22: ='Data Sheet'!K27/'Data Sheet'!K$17 -> 0.0062578223
B23: ='[2]Data Sheet'!A28 -> Profit before tax | C23: ='Data Sheet'!B28/'Data Sheet'!B$17 -> 0.18722426 | D23: ='Data Sheet'!C28/'Data Sheet'!C$17 -> 0.19501236 | E23: ='Data Sheet'!D28/'Data Sheet'!D$17 -> 0.20554227 | F23: ='Data Sheet'!E28/'Data Sheet'!E$17 -> 0.2188756 | G23: ='Data Sheet'!F28/'Data Sheet'!F$17 -> 0.23037478 | H23: ='Data Sheet'!G28/'Data Sheet'!G$17 -> 0.22550396 | I23: ='Data Sheet'!H28/'Data Sheet'!H$17 -> 0.22649964 | J23: ='Data Sheet'!I28/'Data Sheet'!I$17 -> 0.22027072 | ... L23: ='Data Sheet'!K28/'Data Sheet'!K$17 -> 0.22837091
... B26: ='[2]Data Sheet'!A31 -> Dividend Amount | C26: ='Data Sheet'!B31/'Data Sheet'!B$17 -> 0.10737588 | D26: ='Data Sheet'!C31/'Data Sheet'!C$17 -> 0.11072915 | E26: ='Data Sheet'!D31/'Data Sheet'!D$17 -> 0.12153608 | F26: ='Data Sheet'!E31/'Data Sheet'!E$17 -> 0.12088527 | G26: ='Data Sheet'!F31/'Data Sheet'!F$17 -> 0.13573637 | H26: ='Data Sheet'!G31/'Data Sheet'!G$17 -> 0.20237943 | I26: ='Data Sheet'!H31/'Data Sheet'!H$17 -> 0.15234718 | J26: ='Data Sheet'!I31/'Data Sheet'!I$17 -> 0.15128755 | ... L26: ='Data Sheet'!K31/'Data Sheet'!K$17 -> 0.19731943
B27: ='[2]Data Sheet'!A34 -> EBITDA | C27: ='Data Sheet'!B33/'Data Sheet'!B$17 -> 0.19871994 | D27: ='Data Sheet'!C33/'Data Sheet'!C$17 -> 0.20867258 | E27: ='Data Sheet'!D33/'Data Sheet'!D$17 -> 0.22053735 | F27: ='Data Sheet'!E33/'Data Sheet'!E$17 -> 0.23393539 | G27: ='Data Sheet'!F33/'Data Sheet'!F$17 -> 0.25832642 | H27: ='Data Sheet'!G33/'Data Sheet'!G$17 -> 0.25074424 | I27: ='Data Sheet'!H33/'Data Sheet'!H$17 -> 0.24907524 | J27: ='Data Sheet'!I33/'Data Sheet'!I$17 -> 0.24054143 | ... L27: ='Data Sheet'!K33/'Data Sheet'!K$17 -> 0.2557469
A30: # | B30: ="Common Size Balance Sheet"&" "&" - "&'Data Sheet'!B1 -> Common Size Balance Sheet - HINDUSTAN UNILEVER LTD
B32: Particular | C32: ='Data Sheet'!B81 -> 42460 | D32: ='Data Sheet'!C81 -> 42825 | E32: ='Data Sheet'!D81 -> 43190 | F32: ='Data Sheet'!E81 -> 43555 | G32: ='Data Sheet'!F81 -> 43921 | H32: ='Data Sheet'!G81 -> 44286 | I32: ='Data Sheet'!H81 -> 44651 | J32: ='Data Sheet'!I81 -> 45016 | ... L32: ='Data Sheet'!K81 -> 45747
B34: Total Liability | C34: ='Data Sheet'!B61/'Data Sheet'!B$61 -> 1 | D34: ='Data Sheet'!C61/'Data Sheet'!C$61 -> 1 | E34: ='Data Sheet'!D61/'Data Sheet'!D$61 -> 1 | F34: ='Data Sheet'!E61/'Data Sheet'!E$61 -> 1 | G34: ='Data Sheet'!F61/'Data Sheet'!F$61 -> 1 | H34: ='Data Sheet'!G61/'Data Sheet'!G$61 -> 1 | I34: ='Data Sheet'!H61/'Data Sheet'!H$61 -> 1 | J34: ='Data Sheet'!I61/'Data Sheet'!I$61 -> 1 | ... L34: ='Data Sheet'!K61/'Data Sheet'!K$61 -> 1
B35: ='[2]Data Sheet'!A57 -> Equity Share Capital | C35: ='Data Sheet'!B57/'Data Sheet'!B$61 -> 0.014601501 | D35: ='Data Sheet'!C57/'Data Sheet'!C$61 -> 0.013752706 | E35: ='Data Sheet'!D57/'Data Sheet'!D$61 -> 0.012092711 | F35: ='Data Sheet'!E57/'Data Sheet'!E$61 -> 0.011594825 | G35: ='Data Sheet'!F57/'Data Sheet'!F$61 -> 0.010718007 | H35: ='Data Sheet'!G57/'Data Sheet'!G$61 -> 0.0034186791 | I35: ='Data Sheet'!H57/'Data Sheet'!H$61 -> 0.0033330497 | J35: ='Data Sheet'!I57/'Data Sheet'!I$61 -> 0.0032157861 | ... L35: ='Data Sheet'!K57/'Data Sheet'!K$61 -> 0.0029425391
B36: ='[2]Data Sheet'!A58 -> Reserves | C36: ='Data Sheet'!B58/'Data Sheet'!B$61 -> 0.42973028 | D36: ='Data Sheet'!C58/'Data Sheet'!C$61 -> 0.41563734 | E36: ='Data Sheet'!D58/'Data Sheet'!D$61 -> 0.39553242 | F36: ='Data Sheet'!E58/'Data Sheet'!E$61 -> 0.41070374 | G36: ='Data Sheet'!F58/'Data Sheet'!F$61 -> 0.3976083 | H36: ='Data Sheet'!G58/'Data Sheet'!G$61 -> 0.6901222 | I36: ='Data Sheet'!H58/'Data Sheet'!H$61 -> 0.69250844 | J36: ='Data Sheet'!I58/'Data Sheet'!I$61 -> 0.68515402 | ... L36: ='Data Sheet'!K58/'Data Sheet'!K$61 -> 0.61564179
B37: ='[2]Data Sheet'!A59 -> Borrowings | C37: ='Data Sheet'!B59/'Data Sheet'!B$61 -> 0.011965119 | D37: ='Data Sheet'!C59/'Data Sheet'!C$61 -> 0.017636572 | E37: ='Data Sheet'!D59/'Data Sheet'!D$61 -> 0 | F37: ='Data Sheet'!E59/'Data Sheet'!E$61 -> 0.0053142949 | G37: ='Data Sheet'!F59/'Data Sheet'!F$61 -> 0 | H37: ='Data Sheet'!G59/'Data Sheet'!G$61 -> 0 | I37: ='Data Sheet'!H59/'Data Sheet'!H$61 -> 0.014793067 | J37: ='Data Sheet'!I59/'Data Sheet'!I$61 -> 0.016681035 | ... L37: ='Data Sheet'!K59/'Data Sheet'!K$61 -> 0.020635338
B38: ='[2]Data Sheet'!A60 -> Other Liabilities | C38: ='Data Sheet'!B60/'Data Sheet'!B$61 -> 0.5437031 | D38: ='Data Sheet'!C60/'Data Sheet'!C$61 -> 0.55297339 | E38: ='Data Sheet'!D60/'Data Sheet'!D$61 -> 0.59237487 | F38: ='Data Sheet'!E60/'Data Sheet'!E$61 -> 0.57238714 | G38: ='Data Sheet'!F60/'Data Sheet'!F$61 -> 0.5916737 | H38: ='Data Sheet'!G60/'Data Sheet'!G$61 -> 0.30645912 | I38: ='Data Sheet'!H60/'Data Sheet'!H$61 -> 0.28936544 | J38: ='Data Sheet'!I60/'Data Sheet'!I$61 -> 0.29494916 | ... L38: ='Data Sheet'!K60/'Data Sheet'!K$61 -> 0.36078034
B40: Total Assets | C40: ='Data Sheet'!B66/'Data Sheet'!B$66 -> 1 | D40: ='Data Sheet'!C66/'Data Sheet'!C$66 -> 1 | E40: ='Data Sheet'!D66/'Data Sheet'!D$66 -> 1 | F40: ='Data Sheet'!E66/'Data Sheet'!E$66 -> 1 | G40: ='Data Sheet'!F66/'Data Sheet'!F$66 -> 1 | H40: ='Data Sheet'!G66/'Data Sheet'!G$66 -> 1 | I40: ='Data Sheet'!H66/'Data Sheet'!H$66 -> 1 | J40: ='Data Sheet'!I66/'Data Sheet'!I$66 -> 1 | ... L40: ='Data Sheet'!K66/'Data Sheet'!K$66 -> 1
B41: ='[2]Data Sheet'!A62 -> Net Block | C41: ='Data Sheet'!B62/'Data Sheet'!B$66 -> 0.2202393 | D41: ='Data Sheet'!C62/'Data Sheet'!C$66 -> 0.28135744 | E41: ='Data Sheet'!D62/'Data Sheet'!D$66 -> 0.25349905 | F41: ='Data Sheet'!E62/'Data Sheet'!E$66 -> 0.25310001 | G41: ='Data Sheet'!F62/'Data Sheet'!F$66 -> 0.27187019 | H41: ='Data Sheet'!G62/'Data Sheet'!G$66 -> 0.74837067 | I41: ='Data Sheet'!H62/'Data Sheet'!H$66 -> 0.73005134 | J41: ='Data Sheet'!I62/'Data Sheet'!I$66 -> 0.72085608 | ... L41: ='Data Sheet'!K62/'Data Sheet'!K$66 -> 0.6803526
B42: ='[2]Data Sheet'!A63 -> Capital Work in Progress | C42: ='Data Sheet'!B63/'Data Sheet'!B$66 -> 0.027580612 | D42: ='Data Sheet'!C63/'Data Sheet'!C$66 -> 0.014580415 | E42: ='Data Sheet'!D63/'Data Sheet'!D$66 -> 0.02580898 | F42: ='Data Sheet'!E63/'Data Sheet'!E$66 -> 0.021793977 | G42: ='Data Sheet'!F63/'Data Sheet'!F$66 -> 0.029623381 | H42: ='Data Sheet'!G63/'Data Sheet'!G$66 -> 0.01083794 | I42: ='Data Sheet'!H63/'Data Sheet'!H$66 -> 0.018622529 | J42: ='Data Sheet'!I63/'Data Sheet'!I$66 -> 0.01549051 | ... L42: ='Data Sheet'!K63/'Data Sheet'!K$66 -> 0.012634136
B43: ='[2]Data Sheet'!A64 -> Investments | C43: ='Data Sheet'!B64/'Data Sheet'!B$66 -> 0.17521801 | D43: ='Data Sheet'!C64/'Data Sheet'!C$66 -> 0.24156373 | E43: ='Data Sheet'!D64/'Data Sheet'!D$66 -> 0.16084425 | F43: ='Data Sheet'!E64/'Data Sheet'!E$66 -> 0.14579419 | G43: ='Data Sheet'!F64/'Data Sheet'!F$66 -> 0.062273607 | H43: ='Data Sheet'!G64/'Data Sheet'!G$66 -> 0.039409369 | I43: ='Data Sheet'!H64/'Data Sheet'!H$66 -> 0.049939012 | J43: ='Data Sheet'!I64/'Data Sheet'!I$66 -> 0.039437853 | ... L43: ='Data Sheet'!K64/'Data Sheet'!K$66 -> 0.047706698
B44: ='[2]Data Sheet'!A65 -> Other Assets | C44: ='Data Sheet'!B75/'Data Sheet'!B$66 -> 0.10383289 | D44: ='Data Sheet'!C75/'Data Sheet'!C$66 -> 0.11524258 | E44: ='Data Sheet'!D75/'Data Sheet'!D$66 -> 0.15071101 | F44: ='Data Sheet'!E75/'Data Sheet'!E$66 -> 0.14198293 | G44: ='Data Sheet'!F75/'Data Sheet'!F$66 -> 0.18821019 | H44: ='Data Sheet'!G75/'Data Sheet'!G$66 -> 0.058699447 | I44: ='Data Sheet'!H75/'Data Sheet'!H$66 -> 0.057030607 | J44: ='Data Sheet'!I75/'Data Sheet'!I$66 -> 0.059895726 | ... L44: ='Data Sheet'!K75/'Data Sheet'!K$66 -> 0.061618021
B45: ='[2]Data Sheet'!A67 -> Receivables | C45: ='Data Sheet'!B67/'Data Sheet'!B$66 -> 0.085445819 | D45: ='Data Sheet'!C67/'Data Sheet'!C$66 -> 0.06908188 | E45: ='Data Sheet'!D67/'Data Sheet'!D$66 -> 0.073340052 | F45: ='Data Sheet'!E67/'Data Sheet'!E$66 -> 0.09748242 | G45: ='Data Sheet'!F67/'Data Sheet'!F$66 -> 0.057013844 | H45: ='Data Sheet'!G67/'Data Sheet'!G$66 -> 0.025574629 | I45: ='Data Sheet'!H67/'Data Sheet'!H$66 -> 0.031713613 | J45: ='Data Sheet'!I67/'Data Sheet'!I$66 -> 0.04213364 | ... L45: ='Data Sheet'!K67/'Data Sheet'!K$66 -> 0.047819391
B46: ='[2]Data Sheet'!A68 -> Inventory | C46: ='Data Sheet'!B68/'Data Sheet'!B$66 -> 0.18427635 | D46: ='Data Sheet'!C68/'Data Sheet'!C$66 -> 0.1617853 | E46: ='Data Sheet'!D68/'Data Sheet'!D$66 -> 0.14068973 | F46: ='Data Sheet'!E68/'Data Sheet'!E$66 -> 0.13817167 | G46: ='Data Sheet'!F68/'Data Sheet'!F$66 -> 0.13729966 | H46: ='Data Sheet'!G68/'Data Sheet'!G$66 -> 0.052065755 | I46: ='Data Sheet'!H68/'Data Sheet'!H$66 -> 0.058094347 | J46: ='Data Sheet'!I68/'Data Sheet'!I$66 -> 0.058171518 | ... L46: ='Data Sheet'!K68/'Data Sheet'!K$66 -> 0.055282171
B47: ='[2]Data Sheet'!A69 -> Cash & Bank | C47: ='Data Sheet'!B69/'Data Sheet'!B$66 -> 0.20340702 | D47: ='Data Sheet'!C69/'Data Sheet'!C$66 -> 0.11638864 | E47: ='Data Sheet'!D69/'Data Sheet'!D$66 -> 0.19510693 | F47: ='Data Sheet'!E69/'Data Sheet'!E$66 -> 0.20167481 | G47: ='Data Sheet'!F69/'Data Sheet'!F$66 -> 0.25370913 | H47: ='Data Sheet'!G69/'Data Sheet'!G$66 -> 0.065042188 | I47: ='Data Sheet'!H69/'Data Sheet'!H$66 -> 0.054548549 | J47: ='Data Sheet'!I69/'Data Sheet'!I$66 -> 0.064014669 | ... L47: ='Data Sheet'!K69/'Data Sheet'!K$66 -> 0.09458698

Sheet Ratio Analysis
B4: ='Data Sheet'!B1 -> HINDUSTAN UNILEVER LTD
B5: =CONCATENATE("(",B4," |"," BSE Code :",'Data Sheet'!B4,")") -> (HINDUSTAN UNILEVER LTD | BSE Code :500696)
B6: =CONCATENATE(,"INR ",'Data Sheet'!B8) -> INR 2528.9
B7: 52 week (High - INR 3,022.9 & Low - 2,136.0)
B10: ="Ratio Analysis of - "&'Data Sheet'!B1 -> Ratio Analysis of - HINDUSTAN UNILEVER LTD
B11: Years | C11: ='Data Sheet'!B16 -> 42460 | D11: ='Data Sheet'!C16 -> 42825 | E11: ='Data Sheet'!D16 -> 43190 | F11: ='Data Sheet'!E16 -> 43555 | G11: ='Data Sheet'!F16 -> 43921 | H11: ='Data Sheet'!G16 -> 44286 | I11: ='Data Sheet'!H16 -> 44651 | J11: ='Data Sheet'!I16 -> 45016 | ... L11: ='Data Sheet'!K16 -> 45747 | N11: Mean | O11: Median
B13: SalesGrowth | D13: =IFERROR(HistoricalFS!D14/HistoricalFS!C14-1,0) -> 0.030323743 | E13: =IFERROR(HistoricalFS!E14/HistoricalFS!D14-1,0) -> 0.071859357 | F13: =IFERROR(HistoricalFS!F14/HistoricalFS!E14-1,0) -> 0.10592207 | G13: =IFERROR(HistoricalFS!G14/HistoricalFS!F14-1,0) -> 0.012032562 | H13: =IFERROR(HistoricalFS!H14/HistoricalFS!G14-1,0) -> 0.18211296 | I13: =IFERROR(HistoricalFS!I14/HistoricalFS!H14-1,0) -> 0.11520796 | J13: =IFERROR(HistoricalFS!J14/HistoricalFS!I14-1,0) -> 0.15509286 | K13: =IFERROR(HistoricalFS!K14/HistoricalFS!J14-1,0) -> 0.021723341 | L13: =IFERROR(HistoricalFS!L14/HistoricalFS!K14-1,0) -> 0.019791263 | N13: =IFERROR(AVERAGE(D13:L13),0) -> 0.07934068 | O13: =IFERROR(MEDIAN(C13:L13),0) -> 0.071859357
B14: EBITDA Growth | D14: =IFERROR(HistoricalFS!D26/HistoricalFS!C26-1,0) -> 0.07072758 | E14: =IFERROR(HistoricalFS!E26/HistoricalFS!D26-1,0) -> 0.18505057 | F14: =IFERROR(HistoricalFS!F26/HistoricalFS!E26-1,0) -> 0.18415789 | G14: =IFERROR(HistoricalFS!G26/HistoricalFS!F26-1,0) -> 0.11047297 | H14: =IFERROR(HistoricalFS!H26/HistoricalFS!G26-1,0) -> 0.17898793 | I14: =IFERROR(HistoricalFS!I26/HistoricalFS!H26-1,0) -> 0.10588336 | J14: =IFERROR(HistoricalFS!J26/HistoricalFS!I26-1,0) -> 0.10033445 | K14: =IFERROR(HistoricalFS!K26/HistoricalFS!J26-1,0) -> 0.036191419 | L14: =IFERROR(HistoricalFS!L26/HistoricalFS!K26-1,0) -> 0.012552016 | N14: =IFERROR(AVERAGE(D14:L14),0) -> 0.10937313 | O14: =IFERROR(MEDIAN(C14:L14),0) -> 0.10588336
B15: EBIT Growth | D15: =IFERROR(HistoricalFS!D35/HistoricalFS!C35-1,0) -> 0.061004139 | E15: =IFERROR(HistoricalFS!E35/HistoricalFS!D35-1,0) -> 0.18368385 | F15: =IFERROR(HistoricalFS!F35/HistoricalFS!E35-1,0) -> 0.19143144 | G15: =IFERROR(HistoricalFS!G35/HistoricalFS!F35-1,0) -> 0.065423933 | H15: =IFERROR(HistoricalFS!H35/HistoricalFS!G35-1,0) -> 0.19110509 | I15: =IFERROR(HistoricalFS!I35/HistoricalFS!H35-1,0) -> 0.11504928 | J15: =IFERROR(HistoricalFS!J35/HistoricalFS!I35-1,0) -> 0.10572837 | K15: =IFERROR(HistoricalFS!K35/HistoricalFS!J35-1,0) -> 0.033282091 | L15: =IFERROR(HistoricalFS!L35/HistoricalFS!K35-1,0) -> 0.0033474671 | N15: =IFERROR(AVERAGE(D15:L15),0) -> 0.10556174 | O15: =IFERROR(MEDIAN(C15:L15),0) -> 0.10572837
B16: Net Profit Growth | D16: =IFERROR(HistoricalFS!D41/HistoricalFS!C41-1,0) -> 0.0544 | E16: =IFERROR(HistoricalFS!E41/HistoricalFS!D41-1,0) -> 0.051593323 | F16: =IFERROR(HistoricalFS!F41/HistoricalFS!E41-1,0) -> 0.22366522 | G16: =IFERROR(HistoricalFS!G41/HistoricalFS!F41-1,0) -> -0.053066038 | H16: =IFERROR(HistoricalFS!H41/HistoricalFS!G41-1,0) -> 0.081776671 | I16: =IFERROR(HistoricalFS!I41/HistoricalFS!H41-1,0) -> 0.14620107 | J16: =IFERROR(HistoricalFS!J41/HistoricalFS!I41-1,0) -> 0.07164379 | K16: =IFERROR(HistoricalFS!K41/HistoricalFS!J41-1,0) -> 0.13839425 | L16: =IFERROR(HistoricalFS!L41/HistoricalFS!K41-1,0) -> 0.027442371 | N16: =IFERROR(AVERAGE(D16:L16),0) -> 0.082450074 | O16: =IFERROR(MEDIAN(C16:L16),0) -> 0.07164379
B17: Dividend Growth | D17: =IFERROR(HistoricalFS!D49/HistoricalFS!C49-1,0) -> 0.059558573 | E17: =IFERROR(HistoricalFS!E49/HistoricalFS!D49-1,0) -> 0.25477591 | F17: =IFERROR(HistoricalFS!F49/HistoricalFS!E49-1,0) -> 0.17715836 | G17: =IFERROR(HistoricalFS!G49/HistoricalFS!F49-1,0) -> 0.10346941 | H17: =IFERROR(HistoricalFS!H49/HistoricalFS!G49-1,0) -> 0.13917182 | I17: =IFERROR(HistoricalFS!I49/HistoricalFS!H49-1,0) -> 0.10780432 | J17: =IFERROR(HistoricalFS!J49/HistoricalFS!I49-1,0) -> 0.11783697 | K17: =IFERROR(HistoricalFS!K49/HistoricalFS!J49-1,0) -> -0.023723569 | L17: =IFERROR(HistoricalFS!L49/HistoricalFS!K49-1,0) -> -0.012255679 | N17: =IFERROR(AVERAGE(D17:L17),0) -> 0.10264401 | O17: =IFERROR(MEDIAN(C17:L17),0) -> 0.10780432
B19: Gross Margin | C19: =IFERROR(HistoricalFS!C21,0) -> 0.43385323 | D19: =IFERROR(HistoricalFS!D21,0) -> 0.43685544 | E19: =IFERROR(HistoricalFS!E21,0) -> 0.45663244 | F19: =IFERROR(HistoricalFS!F21,0) -> 0.46372424 | G19: =IFERROR(HistoricalFS!G21,0) -> 0.48183898 | H19: =IFERROR(HistoricalFS!H21,0) -> 0.46200136 | I19: =IFERROR(HistoricalFS!I21,0) -> 0.44579186 | J19: =IFERROR(HistoricalFS!J21,0) -> 0.41596236 | ... L19: =IFERROR(HistoricalFS!L21,0) -> 0.45297128 | N19: =IFERROR(AVERAGE(C19:L19),0) -> 0.45059612 | O19: =IFERROR(MEDIAN(C19:L19),0) -> 0.45465063
B20: EBITDA Margin | C20: =IFERROR(HistoricalFS!C27,0) -> 0.18362021 | D20: =IFERROR(HistoricalFS!D27,0) -> 0.19082082 | E20: =IFERROR(HistoricalFS!E27,0) -> 0.21097201 | F20: =IFERROR(HistoricalFS!F27,0) -> 0.22589672 | G20: =IFERROR(HistoricalFS!G27,0) -> 0.24786969 | H20: =IFERROR(HistoricalFS!H27,0) -> 0.24721443 | I20: =IFERROR(HistoricalFS!I27,0) -> 0.24514739 | J20: =IFERROR(HistoricalFS!J27,0) -> 0.23352592 | ... L20: =IFERROR(HistoricalFS!L27,0) -> 0.23515153 | N20: =IFERROR(AVERAGE(C20:L20),0) -> 0.22570515 | O20: =IFERROR(MEDIAN(C20:L20),0) -> 0.23433873
B21: EBIT Margin | C21: =IFERROR(HistoricalFS!C35/HistoricalFS!C14,0) -> 0.17265271 | D21: =IFERROR(HistoricalFS!D35/HistoricalFS!D14,0) -> 0.17779386 | E21: =IFERROR(HistoricalFS!E35/HistoricalFS!E14,0) -> 0.19634266 | F21: =IFERROR(HistoricalFS!F35/HistoricalFS!F14,0) -> 0.21152379 | G21: =IFERROR(HistoricalFS!G35/HistoricalFS!G14,0) -> 0.22268306 | H21: =IFERROR(HistoricalFS!H35/HistoricalFS!H14,0) -> 0.22437697 | I21: =IFERROR(HistoricalFS!I35/HistoricalFS!I14,0) -> 0.22434504 | J21: =IFERROR(HistoricalFS!J35/HistoricalFS!J14,0) -> 0.21475735 | ... L21: =IFERROR(HistoricalFS!L35/HistoricalFS!L14,0) -> 0.21368483 | N21: =IFERROR(AVERAGE(C21:L21),0) -> 0.20753471 | O21: =IFERROR(MEDIAN(C21:L21),0) -> 0.21422109
B22: EBT Margin | C22: =IFERROR(HistoricalFS!C39,0) -> 0.17212453 | D22: =IFERROR(HistoricalFS!D39,0) -> 0.17673844 | E22: =IFERROR(HistoricalFS!E39,0) -> 0.1956112 | F22: =IFERROR(HistoricalFS!F39,0) -> 0.2106843 | G22: =IFERROR(HistoricalFS!G39,0) -> 0.21971696 | H22: =IFERROR(HistoricalFS!H39,0) -> 0.22188909 | I22: =IFERROR(HistoricalFS!I39,0) -> 0.22232391 | J22: =IFERROR(HistoricalFS!J39,0) -> 0.21287554 | ... L22: =IFERROR(HistoricalFS!L39,0) -> 0.20742701 | N22: =IFERROR(AVERAGE(C22:L22),0) -> 0.20511817 | O22: =IFERROR(MEDIAN(C22:L22),0) -> 0.21123753
B23: Net Profit Margin | C23: =IFERROR(HistoricalFS!C42,0) -> 0.33844765 | D23: =IFERROR(HistoricalFS!D42,0) -> 0.33731445 | E23: =IFERROR(HistoricalFS!E42,0) -> 0.29900762 | F23: =IFERROR(HistoricalFS!F42,0) -> 0.30717218 | G23: =IFERROR(HistoricalFS!G42,0) -> 0.27559776 | H23: =IFERROR(HistoricalFS!H42,0) -> 0.24973646 | I23: =IFERROR(HistoricalFS!I42,0) -> 0.25617496 | J23: =IFERROR(HistoricalFS!J42,0) -> 0.2482165 | ... L23: =IFERROR(HistoricalFS!L42,0) -> 0.28595433 | N23: =IFERROR(AVERAGE(C23:L23),0) -> 0.28755989 | O23: =IFERROR(MEDIAN(C23:L23),0) -> 0.28196564
B25: SalesExpenses%Sales | C25: =IFERROR(HistoricalFS!C24,0) -> 0.25023302 | D25: =IFERROR(HistoricalFS!D24,0) -> 0.24603462 | E25: =IFERROR(HistoricalFS!E24,0) -> 0.24566043 | F25: =IFERROR(HistoricalFS!F24,0) -> 0.23782752 | G25: =IFERROR(HistoricalFS!G24,0) -> 0.23396928 | H25: =IFERROR(HistoricalFS!H24,0) -> 0.21478694 | I25: =IFERROR(HistoricalFS!I24,0) -> 0.20064447 | J25: =IFERROR(HistoricalFS!J24,0) -> 0.18243645 | ... L25: =IFERROR(HistoricalFS!L24,0) -> 0.21781974 | N25: =IFERROR(AVERAGE(C25:L25),0) -> 0.22489097 | O25: =IFERROR(MEDIAN(C25:L25),0) -> 0.22673325
B26: Depreciation%Sales | C26: =IFERROR(HistoricalFS!C33,0) -> 0.010967501 | D26: =IFERROR(HistoricalFS!D33,0) -> 0.013026959 | E26: =IFERROR(HistoricalFS!E33,0) -> 0.014629343 | F26: =IFERROR(HistoricalFS!F33,0) -> 0.014372933 | G26: =IFERROR(HistoricalFS!G33,0) -> 0.025186638 | H26: =IFERROR(HistoricalFS!H33,0) -> 0.022837459 | I26: =IFERROR(HistoricalFS!I33,0) -> 0.020802349 | J26: =IFERROR(HistoricalFS!J33,0) -> 0.01876857 | ... L26: =IFERROR(HistoricalFS!L33,0) -> 0.021466707 | N26: =IFERROR(AVERAGE(C26:L26),0) -> 0.018170432 | O26: =IFERROR(MEDIAN(C26:L26),0) -> 0.019207214
B27: OperatingIncome%Sales | C27: =IFERROR('Ratio Analysis'!C21,0) -> 0.17265271 | D27: =IFERROR('Ratio Analysis'!D21,0) -> 0.17779386 | E27: =IFERROR('Ratio Analysis'!E21,0) -> 0.19634266 | F27: =IFERROR('Ratio Analysis'!F21,0) -> 0.21152379 | G27: =IFERROR('Ratio Analysis'!G21,0) -> 0.22268306 | H27: =IFERROR('Ratio Analysis'!H21,0) -> 0.22437697 | I27: =IFERROR('Ratio Analysis'!I21,0) -> 0.22434504 | J27: =IFERROR('Ratio Analysis'!J21,0) -> 0.21475735 | ... L27: =IFERROR('Ratio Analysis'!L21,0) -> 0.21368483 | N27: =IFERROR(AVERAGE(C27:L27),0) -> 0.20753471 | O27: =IFERROR(MEDIAN(C27:L27),0) -> 0.21422109
B29: Return on Capital Employed | C29: =IFERROR((HistoricalFS!C35)/(SUM(HistoricalFS!C71:C73)),0) -> 0.82325926 | D29: =IFERROR((HistoricalFS!D35)/(SUM(HistoricalFS!D71:D73)),0) -> 0.83976642 | E29: =IFERROR((HistoricalFS!E35)/(SUM(HistoricalFS!E71:E73)),0) -> 0.95852218 | F29: =IFERROR((HistoricalFS!F35)/(SUM(HistoricalFS!F71:F73)),0) -> 1.0438112 | G29: =IFERROR((HistoricalFS!G35)/(SUM(HistoricalFS!G71:G73)),0) -> 1.0765585 | H29: =IFERROR((HistoricalFS!H35)/(SUM(HistoricalFS!H71:H73)),0) -> 0.22133658 | I29: =IFERROR((HistoricalFS!I35)/(SUM(HistoricalFS!I71:I73)),0) -> 0.23483155 | J29: =IFERROR((HistoricalFS!J35)/(SUM(HistoricalFS!J71:J73)),0) -> 0.25250859 | ... L29: =IFERROR((HistoricalFS!L35)/(SUM(HistoricalFS!L71:L73)),0) -> 0.26421156 | N29: =IFERROR(AVERAGE(C29:L29),0) -> 0.59698815 | O29: =IFERROR(MEDIAN(C29:L29),0) -> 0.54373541
B30: Retained Earnings% | C30: =IFERROR(HistoricalFS!C55,0) -> 0.057025921 | D30: =IFERROR(HistoricalFS!D55,0) -> 0.054582904 | E30: =IFERROR(HistoricalFS!E55,0) -> 0.11366434 | F30: =IFERROR(HistoricalFS!F55,0) -> 0.17183688 | G30: =IFERROR(HistoricalFS!G55,0) -> 0.14718888 | H30: =IFERROR(HistoricalFS!H55,0) -> 0 | I30: =IFERROR(HistoricalFS!I55,0) -> 0.078750144 | J30: =IFERROR(HistoricalFS!J55,0) -> 0.054667354 | ... L30: =IFERROR(HistoricalFS!L55,0) -> 0 | N30: =IFERROR(AVERAGE(C30:L30),0) -> 0.067771642 | O30: =IFERROR(MEDIAN(C30:L30),0) -> 0.055846638
B31: Return on Equity% | C31: =IFERROR(HistoricalFS!C44/SUM(HistoricalFS!C71:C72),0) -> 0.55758406 | D31: =IFERROR(HistoricalFS!D44/SUM(HistoricalFS!D71:D72),0) -> 0.57591934 | E31: =IFERROR(HistoricalFS!E44/SUM(HistoricalFS!E71:E72),0) -> 0.66941354 | F31: =IFERROR(HistoricalFS!F44/SUM(HistoricalFS!F71:F72),0) -> 0.72937587 | G31: =IFERROR(HistoricalFS!G44/SUM(HistoricalFS!G71:G72),0) -> 0.76947381 | H31: =IFERROR(HistoricalFS!H44/SUM(HistoricalFS!H71:H72),0) -> 0.16421949 | I31: =IFERROR(HistoricalFS!I44/SUM(HistoricalFS!I71:I72),0) -> 0.17677993 | J31: =IFERROR(HistoricalFS!J44/SUM(HistoricalFS!J71:J72),0) -> 0.19272821 | ... L31: =IFERROR(HistoricalFS!L44/SUM(HistoricalFS!L71:L72),0) -> 0.18924335 | N31: =IFERROR(AVERAGE(C31:L31),0) -> 0.42095359 | O31: =IFERROR(MEDIAN(C31:L31),0) -> 0.37515613
B32: Self Sustained Growth Rate | C32: =IFERROR(C30*C31,0) -> 0.031796744 | D32: =IFERROR(D30*D31,0) -> 0.03143535 | E32: =IFERROR(E30*E31,0) -> 0.076088449 | F32: =IFERROR(F30*F31,0) -> 0.12533367 | G32: =IFERROR(G30*G31,0) -> 0.11325799 | H32: =IFERROR(H30*H31,0) -> 0 | I32: =IFERROR(I30*I31,0) -> 0.013921445 | J32: =IFERROR(J30*J31,0) -> 0.010535941 | ... L32: =IFERROR(L30*L31,0) -> 0 | N32: =IFERROR(AVERAGE(C32:L32),0) -> 0.040236959 | O32: =IFERROR(MEDIAN(C32:L32),0) -> 0.022678397
B33: Interest Coverage Ratio | C33: =IFERROR(HistoricalFS!C35/HistoricalFS!C29,0) -> 326.88235 | D33: =IFERROR(HistoricalFS!D35/HistoricalFS!D29,0) -> 168.45714 | E33: =IFERROR(HistoricalFS!E35/HistoricalFS!E29,0) -> 268.42308 | F33: =IFERROR(HistoricalFS!F35/HistoricalFS!F29,0) -> 251.9697 | G33: =IFERROR(HistoricalFS!G35/HistoricalFS!G29,0) -> 75.076271 | H33: =IFERROR(HistoricalFS!H35/HistoricalFS!H29,0) -> 90.188034 | I33: =IFERROR(HistoricalFS!I35/HistoricalFS!I29,0) -> 111 | J33: =IFERROR(HistoricalFS!J35/HistoricalFS!J29,0) -> 114.12281 | ... L33: =IFERROR(HistoricalFS!L35/HistoricalFS!L29,0) -> 34.146835 | N33: =IFERROR(AVERAGE(C33:L33),0) -> 148.05147 | O33: =IFERROR(MEDIAN(C33:L33),0) -> 112.5614
B35: Debtor Turnover Ratio | C35: =IFERROR(HistoricalFS!C14/HistoricalFS!C83,0) -> 25.463608 | D35: =IFERROR(HistoricalFS!D14/HistoricalFS!D83,0) -> 30.564055 | E35: =IFERROR(HistoricalFS!E14/HistoricalFS!E83,0) -> 27.133588 | F35: =IFERROR(HistoricalFS!F14/HistoricalFS!F83,0) -> 21.646476 | G35: =IFERROR(HistoricalFS!G14/HistoricalFS!G83,0) -> 34.624021 | H35: =IFERROR(HistoricalFS!H14/HistoricalFS!H83,0) -> 26.750853 | I35: =IFERROR(HistoricalFS!I14/HistoricalFS!I83,0) -> 23.455277 | J35: =IFERROR(HistoricalFS!J14/HistoricalFS!J83,0) -> 19.675219 | ... L35: =IFERROR(HistoricalFS!L14/HistoricalFS!L83,0) -> 16.528149 | N35: =IFERROR(AVERAGE(C35:L35),0) -> 24.64939 | O35: =IFERROR(MEDIAN(C35:L35),0) -> 24.459442
B36: Creditor Turnover Ratio | C36: =IFERROR(HistoricalFS!C14/HistoricalFS!C74,0) -> 4.0017406 | D36: =IFERROR(HistoricalFS!D14/HistoricalFS!D74,0) -> 3.8183074 | E36: =IFERROR(HistoricalFS!E14/HistoricalFS!E74,0) -> 3.3593233 | F36: =IFERROR(HistoricalFS!F14/HistoricalFS!F74,0) -> 3.6865798 | G36: =IFERROR(HistoricalFS!G14/HistoricalFS!G74,0) -> 3.3363804 | H36: =IFERROR(HistoricalFS!H14/HistoricalFS!H74,0) -> 2.2324124 | I36: =IFERROR(HistoricalFS!I14/HistoricalFS!I74,0) -> 2.5706303 | J36: =IFERROR(HistoricalFS!J14/HistoricalFS!J74,0) -> 2.8106152 | ... L36: =IFERROR(HistoricalFS!L14/HistoricalFS!L74,0) -> 2.1907125 | N36: =IFERROR(AVERAGE(C36:L36),0) -> 3.0406981 | O36: =IFERROR(MEDIAN(C36:L36),0) -> 3.0734978
B37: Inventory Turnover | C37: =IFERROR(HistoricalFS!C14/HistoricalFS!C84,0) -> 11.807043 | D37: =IFERROR(HistoricalFS!D14/HistoricalFS!D84,0) -> 13.050767 | E37: =IFERROR(HistoricalFS!E14/HistoricalFS!E84,0) -> 14.144449 | F37: =IFERROR(HistoricalFS!F14/HistoricalFS!F84,0) -> 15.27195 | G37: =IFERROR(HistoricalFS!G14/HistoricalFS!G84,0) -> 14.377665 | H37: =IFERROR(HistoricalFS!H14/HistoricalFS!H84,0) -> 13.139983 | I37: =IFERROR(HistoricalFS!I14/HistoricalFS!I84,0) -> 12.804199 | J37: =IFERROR(HistoricalFS!J14/HistoricalFS!J84,0) -> 14.250765 | ... L37: =IFERROR(HistoricalFS!L14/HistoricalFS!L84,0) -> 14.296942 | N37: =IFERROR(AVERAGE(C37:L37),0) -> 13.853312 | O37: =IFERROR(MEDIAN(C37:L37),0) -> 14.197607
B38: Fixed Asset Turnover | C38: =IFERROR(HistoricalFS!C14/HistoricalFS!C77,0) -> 9.8790669 | D38: =IFERROR(HistoricalFS!D14/HistoricalFS!D77,0) -> 7.5044128 | E38: =IFERROR(HistoricalFS!E14/HistoricalFS!E77,0) -> 7.8500442 | F38: =IFERROR(HistoricalFS!F14/HistoricalFS!F77,0) -> 8.3372216 | G38: =IFERROR(HistoricalFS!G14/HistoricalFS!G77,0) -> 7.2609965 | H38: =IFERROR(HistoricalFS!H14/HistoricalFS!H77,0) -> 0.91417686 | I38: =IFERROR(HistoricalFS!I14/HistoricalFS!I77,0) -> 1.0189031 | J38: =IFERROR(HistoricalFS!J14/HistoricalFS!J77,0) -> 1.1500057 | ... L38: =IFERROR(HistoricalFS!L14/HistoricalFS!L77,0) -> 1.1617006 | N38: =IFERROR(AVERAGE(C38:L38),0) -> 4.622821 | O38: =IFERROR(MEDIAN(C38:L38),0) -> 4.2113485
B39: Capital Turnover Ratio | C39: =IFERROR(HistoricalFS!C14/SUM(HistoricalFS!C71:C72),0) -> 4.8966986 | D39: =IFERROR(HistoricalFS!D14/SUM(HistoricalFS!D71:D72),0) -> 4.9172598 | E39: =IFERROR(HistoricalFS!E14/SUM(HistoricalFS!E71:E72),0) -> 4.8818844 | F39: =IFERROR(HistoricalFS!F14/SUM(HistoricalFS!F71:F72),0) -> 4.9968222 | G39: =IFERROR(HistoricalFS!G14/SUM(HistoricalFS!G71:G72),0) -> 4.8344878 | H39: =IFERROR(HistoricalFS!H14/SUM(HistoricalFS!H71:H72),0) -> 0.98644964 | I39: =IFERROR(HistoricalFS!I14/SUM(HistoricalFS!I71:I72),0) -> 1.0689957 | J39: =IFERROR(HistoricalFS!J14/SUM(HistoricalFS!J71:J72),0) -> 1.204278 | ... L39: =IFERROR(HistoricalFS!L14/SUM(HistoricalFS!L71:L72),0) -> 1.2777013 | N39: =IFERROR(AVERAGE(C39:L39),0) -> 3.0273059 | O39: =IFERROR(MEDIAN(C39:L39),0) -> 3.0560945
B41: ( in days)
B42: Debtor Days | C42: =IFERROR(365/C35,0) -> 14.334183 | D42: =IFERROR(365/D35,0) -> 11.942133 | E42: =IFERROR(365/E35,0) -> 13.451962 | F42: =IFERROR(365/F35,0) -> 16.861867 | G42: =IFERROR(365/G35,0) -> 10.541814 | H42: =IFERROR(365/H35,0) -> 13.644425 | I42: =IFERROR(365/I35,0) -> 15.56153 | J42: =IFERROR(365/J35,0) -> 18.551255 | ... L42: =IFERROR(365/L35,0) -> 22.083538 | N42: =IFERROR(AVERAGE(C42:L42),0) -> 15.464598 | O42: =IFERROR(MEDIAN(C42:L42),0) -> 14.947856
B43: Payable Days | C43: =IFERROR(365/C36,0) -> 91.210309 | D43: =IFERROR(365/D36,0) -> 95.592093 | E43: =IFERROR(365/E36,0) -> 108.65283 | F43: =IFERROR(365/F36,0) -> 99.007759 | G43: =IFERROR(365/G36,0) -> 109.39999 | H43: =IFERROR(365/H36,0) -> 163.50026 | I43: =IFERROR(365/I36,0) -> 141.98852 | J43: =IFERROR(365/J36,0) -> 129.86481 | ... L43: =IFERROR(365/L36,0) -> 166.61246 | N43: =IFERROR(AVERAGE(C43:L43),0) -> 125.78947 | O43: =IFERROR(MEDIAN(C43:L43),0) -> 119.6324
B44: Inventory Days | C44: =IFERROR(365/C37,0) -> 30.913751 | D44: =IFERROR(365/D37,0) -> 27.967704 | E44: =IFERROR(365/E37,0) -> 25.805177 | F44: =IFERROR(365/F37,0) -> 23.900025 | G44: =IFERROR(365/G37,0) -> 25.386597 | H44: =IFERROR(365/H37,0) -> 27.777813 | I44: =IFERROR(365/I37,0) -> 28.506273 | J44: =IFERROR(365/J37,0) -> 25.612661 | ... L44: =IFERROR(365/L37,0) -> 25.529935 | N44: =IFERROR(AVERAGE(C44:L44),0) -> 26.511762 | O44: =IFERROR(MEDIAN(C44:L44),0) -> 25.708919
B45: Cash Conversion Cycle | C45: =SUM(C42,C44)-C43 -> -45.962375 | D45: =SUM(D42,D44)-D43 -> -55.682257 | E45: =SUM(E42,E44)-E43 -> -69.395696 | F45: =SUM(F42,F44)-F43 -> -58.245866 | G45: =SUM(G42,G44)-G43 -> -73.471583 | H45: =SUM(H42,H44)-H43 -> -122.07802 | I45: =SUM(I42,I44)-I43 -> -97.920718 | J45: =SUM(J42,J44)-J43 -> -85.700891 | ... L45: =SUM(L42,L44)-L43 -> -118.99899 | N45: =IFERROR(AVERAGE(C45:L45),0) -> -83.813107 | O45: =IFERROR(MEDIAN(C45:L45),0) -> -79.586237
B47: CFO/Sales | C47: =IFERROR(HistoricalFS!C94/HistoricalFS!C14,0) -> 0.12959051 | D47: =IFERROR(HistoricalFS!D94/HistoricalFS!D14,0) -> 0.15635366 | E47: =IFERROR(HistoricalFS!E94/HistoricalFS!E14,0) -> 0.17045998 | F47: =IFERROR(HistoricalFS!F94/HistoricalFS!F14,0) -> 0.14754515 | G47: =IFERROR(HistoricalFS!G94/HistoricalFS!G14,0) -> 0.19161451 | H47: =IFERROR(HistoricalFS!H94/HistoricalFS!H14,0) -> 0.19484137 | I47: =IFERROR(HistoricalFS!I94/HistoricalFS!I14,0) -> 0.17252031 | J47: =IFERROR(HistoricalFS!J94/HistoricalFS!J14,0) -> 0.16492242 | ... L47: =IFERROR(HistoricalFS!L94/HistoricalFS!L14,0) -> 0.188305 | N47: =IFERROR(AVERAGE(C47:L47),0) -> 0.17660721 | O47: =IFERROR(MEDIAN(C47:L47),0) -> 0.17149014
B48: CFO/Total Assets | C48: =IFERROR(HistoricalFS!C94/HistoricalFS!C88,0) -> 0.28195768 | D48: =IFERROR(HistoricalFS!D94/HistoricalFS!D88,0) -> 0.33012861 | E48: =IFERROR(HistoricalFS!E94/HistoricalFS!E88,0) -> 0.33921173 | F48: =IFERROR(HistoricalFS!F94/HistoricalFS!F88,0) -> 0.31134253 | G48: =IFERROR(HistoricalFS!G94/HistoricalFS!G88,0) -> 0.37825634 | H48: =IFERROR(HistoricalFS!H94/HistoricalFS!H88,0) -> 0.13329939 | I48: =IFERROR(HistoricalFS!I94/HistoricalFS!I88,0) -> 0.1283295 | J48: =IFERROR(HistoricalFS!J94/HistoricalFS!J88,0) -> 0.1367188 | ... L48: =IFERROR(HistoricalFS!L94/HistoricalFS!L88,0) -> 0.14882987 | N48: =IFERROR(AVERAGE(C48:L48),0) -> 0.23851594 | O48: =IFERROR(MEDIAN(C48:L48),0) -> 0.23952131
B49: CFO/Total Debt | C49: =IFERROR(HistoricalFS!C94/HistoricalFS!C73,0) -> 23.564972 | D49: =IFERROR(HistoricalFS!D94/HistoricalFS!D73,0) -> 18.718412 | E49: =IFERROR(HistoricalFS!E94/HistoricalFS!E73,0) -> 0 | F49: =IFERROR(HistoricalFS!F94/HistoricalFS!F73,0) -> 58.585859 | G49: =IFERROR(HistoricalFS!G94/HistoricalFS!G73,0) -> 0 | H49: =IFERROR(HistoricalFS!H94/HistoricalFS!H73,0) -> 0 | I49: =IFERROR(HistoricalFS!I94/HistoricalFS!I73,0) -> 8.674976 | J49: =IFERROR(HistoricalFS!J94/HistoricalFS!J73,0) -> 8.1960623 | ... L49: =IFERROR(HistoricalFS!L94/HistoricalFS!L73,0) -> 7.2123786 | N49: =IFERROR(AVERAGE(C49:L49),0) -> 13.537651 | O49: =IFERROR(MEDIAN(C49:L49),0) -> 8.4355192

Sheet forcasting
B3: ='Data Sheet'!B1 -> HINDUSTAN UNILEVER LTD
B4: =CONCATENATE("(",B3," |"," BSE Code :",'Data Sheet'!B4,")") -> (HINDUSTAN UNILEVER LTD | BSE Code :500696)
B5: =CONCATENATE(,"INR ",'Data Sheet'!B8) -> INR 2528.9
B6: 52 week (High - INR 3,022.9 & Low - 2,136.0)
B9: ='Data Sheet'!$B$1&" - "&"EBITDA"&" Forecasting" -> HINDUSTAN UNILEVER LTD - EBITDA Forecasting | G9: ='Data Sheet'!$B$1&" - "&"EBITDA"&" Forecasting" -> HINDUSTAN UNILEVER LTD - EBITDA Forecasting | L9: ='Data Sheet'!$B$1&" - "&"Earnings Per Share"&" Forecasting" -> HINDUSTAN UNILEVER LTD - Earnings Per Share Forecasting
B10: Year Weight | C10: Year | D10: Sales | E10: Sales Growth | G10: Year Weight | H10: Year | I10: EBITDA | J10: EBITDAGrowth | L10: Year Weight | M10: Year | N10: EPS | O10: Sales Growth
B11: 1 | C11: ='Data Sheet'!$B$16 -> 42460 | D11: {=TRANSPOSE('Data Sheet'!B17:K17)} -> 32186 | G11: 1 | H11: ='Data Sheet'!$B$16 -> 42460 | I11: {=TRANSPOSE('Data Sheet'!B33:K33)} -> 6396 | L11: 1 | M11: ='Data Sheet'!$B$16 -> 42460 | N11: {=TRANSPOSE(HistoricalFS!C49:L49)} -> 16.937012
B12: =B11+1 -> 2 | C12: =C11+365 -> 42825 | D12: 33162 | E12: =D12/D11-1 -> 0.030323743 | G12: =G11+1 -> 2 | H12: =H11+365 -> 42825 | I12: 6920 | J12: =I12/I11-1 -> 0.081926204 | L12: =L11+1 -> 2 | M12: =M11+365 -> 42825 | N12: 17.945756 | O12: =N12/N11-1 -> 0.059558573
B13: =B12+1 -> 3 | C13: =C12+365 -> 43190 | D13: 35545 | E13: =D13/D12-1 -> 0.071859357 | G13: =G12+1 -> 3 | H13: =H12+365 -> 43190 | I13: 7839 | J13: =I13/I12-1 -> 0.13280347 | L13: =L12+1 -> 3 | M13: =M12+365 -> 43190 | N13: 22.517903 | O13: =N13/N12-1 -> 0.25477591
B14: =B13+1 -> 4 | C14: =C13+365 -> 43555 | D14: 39310 | E14: =D14/D13-1 -> 0.10592207 | G14: =G13+1 -> 4 | H14: =H13+365 -> 43555 | I14: 9196 | J14: =I14/I13-1 -> 0.17310881 | L14: =L13+1 -> 4 | M14: =M13+365 -> 43555 | N14: 26.507137 | O14: =N14/N13-1 -> 0.17715836
B15: =B14+1 -> 5 | C15: =C14+365 -> 43920 | D15: 39783 | E15: =D15/D14-1 -> 0.012032562 | G15: =G14+1 -> 5 | H15: =H14+365 -> 43920 | I15: 10277 | J15: =I15/I14-1 -> 0.11755111 | L15: =L14+1 -> 5 | M15: =M14+365 -> 43920 | N15: 29.249815 | O15: =N15/N14-1 -> 0.10346941
B16: =B15+1 -> 6 | C16: =C15+365 -> 44285 | D16: 47028 | E16: =D16/D15-1 -> 0.18211296 | G16: =G15+1 -> 6 | H16: =H15+365 -> 44285 | I16: 11792 | J16: =I16/I15-1 -> 0.14741656 | L16: =L15+1 -> 6 | M16: =M15+365 -> 44285 | N16: 33.320565 | O16: =N16/N15-1 -> 0.13917182
B17: =B16+1 -> 7 | C17: =C16+365 -> 44650 | D17: 52446 | E17: =D17/D16-1 -> 0.11520796 | G17: =G16+1 -> 7 | H17: =H16+365 -> 44650 | I17: 13063 | J17: =I17/I16-1 -> 0.10778494 | L17: =L16+1 -> 7 | M17: =M16+365 -> 44650 | N17: 36.912666 | O17: =N17/N16-1 -> 0.10780432
B18: =B17+1 -> 8 | C18: =C17+365 -> 45015 | D18: 60580 | E18: =D18/D17-1 -> 0.15509286 | G18: =G17+1 -> 8 | H18: =H17+365 -> 45015 | I18: 14572 | J18: =I18/I17-1 -> 0.11551711 | L18: =L17+1 -> 8 | M18: =M17+365 -> 45015 | N18: 41.262343 | O18: =N18/N17-1 -> 0.11783697
B19: =B18+1 -> 9 | C19: =C18+365 -> 45380 | D19: 61896 | E19: =D19/D18-1 -> 0.021723341 | G19: =G18+1 -> 9 | H19: =H18+365 -> 45380 | I19: 15471 | J19: =I19/I18-1 -> 0.061693659 | L19: =L18+1 -> 9 | M19: =M18+365 -> 45380 | N19: 40.283453 | O19: =N19/N18-1 -> -0.023723569
B20: =B19+1 -> 10 | C20: =C19+365 -> 45745 | D20: 63121 | E20: =D20/D19-1 -> 0.019791263 | G20: =G19+1 -> 10 | H20: =H19+365 -> 45745 | I20: 16143 | J20: =I20/I19-1 -> 0.043436106 | L20: =L19+1 -> 10 | M20: =M19+365 -> 45745 | N20: 39.789751 | O20: =N20/N19-1 -> -0.012255679
B21: =B20+1 -> 11 | C21: =C20+365 -> 46110 | D21: =FORECAST(B21,$D$11:$D$20,$B$11:$B$20) -> 68218.4 | E21: =D21/D20-1 -> 0.080756008 | G21: =G20+1 -> 11 | H21: =H20+365 -> 46110 | I21: =FORECAST(G21,$I$11:$I$20,$G$11:$G$20) -> 17645.6 | J21: =I21/I20-1 -> 0.093080592 | L21: =L20+1 -> 11 | M21: =M20+365 -> 46110 | N21: =FORECAST(L21,$N$11:$N$20,$L$11:$L$20) -> 46.840909 | O21: =N21/N20-1 -> 0.17721039
B22: =B21+1 -> 12 | C22: =C21+365 -> 46475 | D22: =FORECAST(B22,$D$11:$D$20,$B$11:$B$20) -> 72166.164 | E22: =D22/D21-1 -> 0.057869484 | G22: =G21+1 -> 12 | H22: =H21+365 -> 46475 | I22: =FORECAST(G22,$I$11:$I$20,$G$11:$G$20) -> 18823.545 | J22: =I22/I21-1 -> 0.066755761 | L22: =L21+1 -> 12 | M22: =M21+365 -> 46475 | N22: =FORECAST(L22,$N$11:$N$20,$L$11:$L$20) -> 49.816958 | O22: =N22/N21-1 -> 0.063535251
B23: =B22+1 -> 13 | C23: =C22+365 -> 46840 | D23: =FORECAST(B23,$D$11:$D$20,$B$11:$B$20) -> 76113.927 | E23: =D23/D22-1 -> 0.054703804 | G23: =G22+1 -> 13 | H23: =H22+365 -> 46840 | I23: =FORECAST(G23,$I$11:$I$20,$G$11:$G$20) -> 20001.491 | J23: =I23/I22-1 -> 0.062578299 | L23: =L22+1 -> 13 | M23: =M22+365 -> 46840 | N23: =FORECAST(L23,$N$11:$N$20,$L$11:$L$20) -> 52.793007 | O23: =N23/N22-1 -> 0.059739675
B24: =B23+1 -> 14 | C24: =C23+365 -> 47205 | D24: =FORECAST(B24,$D$11:$D$20,$B$11:$B$20) -> 80061.691 | E24: =D24/D23-1 -> 0.051866508 | G24: =G23+1 -> 14 | H24: =H23+365 -> 47205 | I24: =FORECAST(G24,$I$11:$I$20,$G$11:$G$20) -> 21179.436 | J24: =I24/I23-1 -> 0.058892883 | L24: =L23+1 -> 14 | M24: =M23+365 -> 47205 | N24: =FORECAST(L24,$N$11:$N$20,$L$11:$L$20) -> 55.769056 | O24: =N24/N23-1 -> 0.056372029
B25: =B24+1 -> 15 | C25: =C24+365 -> 47570 | D25: =FORECAST(B25,$D$11:$D$20,$B$11:$B$20) -> 84009.455 | E25: =D25/D24-1 -> 0.049309021 | G25: =G24+1 -> 15 | H25: =H24+365 -> 47570 | I25: =FORECAST(G25,$I$11:$I$20,$G$11:$G$20) -> 22357.382 | J25: =I25/I24-1 -> 0.055617413 | L25: =L24+1 -> 15 | M25: =M24+365 -> 47570 | N25: =FORECAST(L25,$N$11:$N$20,$L$11:$L$20) -> 58.745105 | O25: =N25/N24-1 -> 0.053363803

Sheet real wacc
B3: ='Data Sheet'!B1 -> HINDUSTAN UNILEVER LTD
B4: =CONCATENATE("(",B3," |"," BSE Code :",'Data Sheet'!B4,")") -> (HINDUSTAN UNILEVER LTD | BSE Code :500696)
B5: =CONCATENATE(,"INR ",'Data Sheet'!B8) -> INR 2528.9
B6: 52 week (High - INR 3,022.9 & Low - 2,136.0)
B8: Weighted average cost of capital
B10: All figures are in INR unless stated otherwise
B12: Peer company's
G13: Debt/ | H13: Debt/ | I13: Levered | J13: Unlevered
B14: Name of the Company | C14: country | D14: Total debt | E14: Total equity | F14: Tax rate 1 | G14: Equity | H14: Capital | I14: Beta 2 | J14: Beta 3
B16: =Peer!B4 -> Hindustan Unilever Ltd | C16: India | D16: =Peer!J4 -> 1648 | E16: =Peer!H4 -> 49609 | F16: 0.3 | G16: =D16/E16 -> 0.033219779 | H16: =D16/(E16+D16) -> 0.032151706 | I16: =Peer!G4 -> 0.74 | J16: =I16/(1+(1-F16)*G16) -> 0.72318321
B17: =Peer!B5 -> ITC Ltd | C17: India | D17: =Peer!J5 -> 284.54 | E17: =Peer!H5 -> 70397.94 | F17: 0.3 | G17: =D17/E17 -> 0.0040418796 | H17: =D17/(E17+D17) -> 0.0040256086 | I17: =Peer!G5 -> 0.83 | J17: =I17/(1+(1-F17)*G17) -> 0.82765829
B18: =Peer!B6 -> Nestle India Ltd | C18: India | D18: =Peer!J6 -> 1166.85 | E18: =Peer!H6 -> 4010.21 | F18: 0.3 | G18: =D18/E18 -> 0.2909698 | H18: =D18/(E18+D18) -> 0.22538854 | I18: =Peer!G6 -> 0.84 | J18: =I18/(1+(1-F18)*G18) -> 0.69786056
B19: =Peer!B7 -> Britannia Industries Ltd | C19: India | D19: =Peer!J7 -> 1246.51 | E19: =Peer!H7 -> 4381.32 | F19: 0.3 | G19: =D19/E19 -> 0.28450558 | H19: =D19/(E19+D19) -> 0.22149034 | I19: =Peer!G7 -> 0.76 | J19: =I19/(1+(1-F19)*G19) -> 0.6337802
B20: =Peer!B8 -> Godrej Consumer Products Ltd | C20: India | D20: =Peer!J8 -> 4004.49 | E20: =Peer!H8 -> 12003.92 | F20: 0.3 | G20: =D20/E20 -> 0.33359852 | H20: =D20/(E20+D20) -> 0.25014914 | I20: =Peer!G8 -> 0.84 | J20: =I20/(1+(1-F20)*G20) -> 0.68097858
B21: =Peer!B9 -> Dabur India Ltd | C21: India | D21: =Peer!J9 -> 950.37 | E21: =Peer!H9 -> 11210.26 | F21: 0.3 | G21: =D21/E21 -> 0.084776803 | H21: =D21/(E21+D21) -> 0.078151379 | I21: =Peer!G9 -> 0.54 | J21: =I21/(1+(1-F21)*G21) -> 0.50974954
B22: =Peer!B10 -> Marico Ltd | C22: India | D22: =Peer!J10 -> 554 | E22: =Peer!H10 -> 4266 | F22: 0.3 | G22: =D22/E22 -> 0.12986404 | H22: =D22/(E22+D22) -> 0.11493776 | I22: =Peer!G10 -> 0.51 | J22: =I22/(1+(1-F22)*G22) -> 0.46750183
E23: Average | F23: =AVERAGE(F16:F22) -> 0.3 | G23: =AVERAGE(G16:G22) -> 0.16585377 | H23: =AVERAGE(H16:H22) -> 0.13232778 | I23: =AVERAGE(I16:I22) -> 0.72285714 | J23: =AVERAGE(J16:J22) -> 0.64867317
E24: median | F24: =MEDIAN(F16:F22) -> 0.3 | G24: =MEDIAN(G16:G22) -> 0.12986404 | H24: =MEDIAN(H16:H22) -> 0.11493776 | I24: =MEDIAN(I16:I22) -> 0.76 | J24: =MEDIAN(J16:J22) -> 0.68097858
B27: cost of Debt | G27: cost of Equity
B29: Pre-tax cost of debt | E29: ='Data Sheet'!K27/'real wacc'!D16 -> 0.23968447 | G29: Risk free rate | J29: 0.0736
B30: tax rate | E30: =F16 -> 0.3 | G30: Equity Risk Premium | J30: ='nifty 50 data'!N10-'real wacc'!J29 -> 0.07956
B31: post tax cost of debt | E31: =E29*(1-E30) -> 0.16777913 | G31: Levered Beta 4 | J31: ='Regression beta'!M13 -> 0.14896049
G32: cost of equity | J32: =J29+(J31*(J30-J29)) -> 0.074487805
B34: capital structure | G34: Levered Beta
D36: current | E36: target | G36: company median Unlevered Beta | J36: =J24 -> 0.68097858
B37: Total Debt | C37: =D16 -> 1648 | D37: =C37/($C$39) -> 0.032151706 | E37: =H23 -> 0.13232778 | G37: Target debt/ Equity | J37: =E41 -> 0.15250895
B38: Market Capitalization | C38: =E16 -> 49609 | D38: =C38/($C$39) -> 0.96784829 | E38: =E39-E37 -> 0.86767222 | G38: Tax Rate | J38: =E30 -> 0.3
B39: Total capital | C39: =C38+C37 -> 51257 | D39: =C39/($C$39) -> 1 | E39: =D39 -> 1 | G39: Levered Beta | J39: =J36*(1+(1-J38)*J37) -> 0.75367732
B41: debt / equity | D41: =D37/D38 -> 0.033219779 | E41: =E37/E38 -> 0.15250895
B43: Note: | G43: Weighted Average Cost of Capital
B44: 1. Tax Rate Considered as Marginal Tax Rate For The Country
B45: 2. Levered Beta is based on 5 year monthly data | I45: total Cost | J45: Total Weight
B46: 3. Levered Beta = Unlevered Beta * (1+(1- Tax Rate)* Debt/Equity) | G46: Debt | I46: =E31 -> 0.16777913 | J46: =E37 -> 0.13232778
B47: 4. Unlevered Beta = Levered Beta / (1+(1- Tax Rate)* Debt/Equity) | G47: Equity | I47: =J32 -> 0.074487805 | J47: =E38 -> 0.86767222
G48: WACC | J48: =SUMPRODUCT(I46:I47,J46:J47) -> 0.086832838

Sheet Data Sheet
A1: COMPANY NAME | B1: HINDUSTAN UNILEVER LTD | E1: =IF(B2<>B3, "A NEW VERSION OF THE WORKSHEET IS AVAILABLE", "")
A2: LATEST VERSION | B2: 2.1 | E2: PLEASE DO NOT MAKE ANY CHANGES TO THIS SHEET
A3: CURRENT VERSION | B3: 2.1
B4: 500696
A5: META
A6: Number of shares | B6: =IF(B9>0, B9/B8, 0) -> 244.7425
A7: Face Value | B7: 1
A8: Current Price | B8: 2528.9
A9: Market Capitalization | B9: 618929.3
A15: PROFIT & LOSS
A16: Report Date | B16: 42460 | C16: 42825 | D16: 43190 | E16: 43555 | F16: 43921 | G16: 44286 | H16: 44651 | I16: 45016 | J16: 45382 | K16: 45747
A17: Sales | B17: 32186 | C17: 33162 | D17: 35545 | E17: 39310 | F17: 39783 | G17: 47028 | H17: 52446 | I17: 60580 | J17: 61896 | K17: 63121
A18: Raw Material Cost | B18: 13184 | C18: 13606 | D18: 14233 | E18: 15845 | F18: 15697 | G18: 20141 | H18: 22871 | I18: 28427 | J18: 26822 | K18: 27344
A19: Change in Inventory | B19: -83 | C19: -144 | D19: 72 | E19: -12 | F19: 108 | G19: 405 | H19: 22 | I19: 75 | J19: 11 | K19: 153
A20: Power and Fuel | B20: 309 | C20: 295 | D20: 295 | E20: 308 | F20: 299 | G20: 339 | H20: 318 | I20: 384 | J20: 446 | K20: 427
A21: Other Mfr. Exp | B21: 2966 | C21: 2887 | D21: 2998 | E21: 3041 | F21: 2906 | G21: 2868 | H21: 3354 | I21: 3791 | J21: 3385 | K21: 3834
A22: Employee Cost | B22: 1680 | C22: 1743 | D22: 1860 | E22: 1875 | F22: 1820 | G22: 2358 | H22: 2545 | I22: 2854 | J22: 3009 | K22: 3077
A23: Selling and admin | B23: 6741 | C23: 6689 | D23: 7252 | E23: 7796 | F23: 7620 | G23: 7906 | H23: 8164 | I23: 8785 | J23: 10780 | K23: 10693
A24: Other Expenses | B24: 1313 | C24: 1470 | D24: 1480 | E24: 1553 | F24: 1688 | G24: 2195 | H24: 2359 | I24: 2267 | J24: 2806 | K24: 3056
A25: Other Income | B25: 486 | C25: 606 | D25: 353 | E25: 322 | F25: 424 | G25: 170 | H25: 219 | I25: 448 | J25: 817 | K25: 1322
A26: Depreciation | B26: 353 | C26: 432 | D26: 520 | E26: 565 | F26: 1002 | G26: 1074 | H26: 1091 | I26: 1137 | J26: 1216 | K26: 1355
A27: Interest | B27: 17 | C27: 35 | D27: 26 | E27: 33 | F27: 118 | G27: 117 | H27: 106 | I27: 114 | J27: 334 | K27: 395
... A31: Dividend Amount | B31: 3456 | C31: 3672 | D31: 4320 | E31: 4752 | F31: 5400 | G31: 9517.5 | H31: 7990 | I31: 9165 | J31: 9870 | K31: 12455
A33: EBITDA | B33: =B30+B27+B29+B26 -> 6396 | C33: =C30+C27+C29+C26 -> 6920 | D33: =D30+D27+D29+D26 -> 7839 | E33: =E30+E27+E29+E26 -> 9196 | F33: =F30+F27+F29+F26 -> 10277 | G33: =G30+G27+G29+G26 -> 11792 | H33: =H30+H27+H29+H26 -> 13063 | I33: =I30+I27+I29+I26 -> 14572 | ... K33: =K30+K27+K29+K26 -> 16143
A40: Quarters
A41: Report Date | B41: 45016 | C41: 45107 | D41: 45199 | E41: 45291 | F41: 45382 | G41: 45473 | H41: 45565 | I41: 45657 | J41: 45747 | K41: 45838
A42: Sales | B42: 15215 | C42: 15496 | D42: 15623 | E42: 15567 | F42: 15210 | G42: 15707 | H42: 15926 | I42: 15818 | J42: 15670 | K42: 16514
A43: Expenses | B43: 11643 | C43: 11832 | D43: 11828 | E43: 11902 | F43: 11675 | G43: 11965 | H43: 12139 | I43: 12123 | J43: 12052 | K43: 12797
A44: Other Income | B44: 240 | C44: 146 | D44: 178 | E44: 184 | F44: 309 | G44: 209 | H44: 203 | I44: 740 | J44: 171 | K44: 74
A45: Depreciation | B45: 291 | C45: 286 | D45: 297 | E45: 313 | F45: 320 | G45: 329 | H45: 338 | I45: 341 | J45: 347 | K45: 361
A46: Interest | B46: 29 | C46: 50 | D46: 88 | E46: 91 | F46: 105 | G46: 93 | H46: 110 | I46: 112 | J46: 80 | K46: 127
A47: Profit before tax | B47: 3492 | C47: 3474 | D47: 3588 | E47: 3445 | F47: 3419 | G47: 3529 | H47: 3542 | I47: 3982 | J47: 3362 | K47: 3303
A48: Tax | B48: 891 | C48: 918 | D48: 931 | E48: 937 | F48: 858 | G48: 917 | H48: 947 | I48: 993 | J48: 887 | K48: 535
A49: Net profit | B49: 2600 | C49: 2554 | D49: 2656 | E49: 2509 | F49: 2558 | G49: 2610 | H49: 2591 | I49: 2984 | J49: 2464 | K49: 2756
A50: Operating Profit | B50: 3572 | C50: 3664 | D50: 3795 | E50: 3665 | F50: 3535 | G50: 3742 | H50: 3787 | I50: 3695 | J50: 3618 | K50: 3717
A52: EBITDA | B52: =B48+B49+B46+B45 -> 3811 | C52: =C48+C49+C46+C45 -> 3808 | D52: =D48+D49+D46+D45 -> 3972 | E52: =E48+E49+E46+E45 -> 3850 | F52: =F48+F49+F46+F45 -> 3841 | G52: =G48+G49+G46+G45 -> 3949 | H52: =H48+H49+H46+H45 -> 3986 | I52: =I48+I49+I46+I45 -> 4430 | ... K52: =K48+K49+K46+K45 -> 3779
B53: =B47+B46+B45 -> 3812
A55: BALANCE SHEET
A56: Report Date | B56: 42460 | C56: 42825 | D56: 43190 | E56: 43555 | F56: 43921 | G56: 44286 | H56: 44651 | I56: 45016 | J56: 45382 | K56: 45747
A57: Equity Share Capital | B57: 216 | C57: 216 | D57: 216 | E57: 216 | F57: 216 | G57: 235 | H57: 235 | I57: 235 | J57: 235 | K57: 235
A58: Reserves | B58: 6357 | C58: 6528 | D58: 7065 | E58: 7651 | F58: 8013 | G58: 47439 | H58: 48826 | I58: 50069 | J58: 50983 | K58: 49167
A59: Borrowings | B59: 177 | C59: 277 | E59: 99 | H59: 1043 | I59: 1219 | J59: 1484 | K59: 1648
A60: Other Liabilities | B60: 8043 | C60: 8685 | D60: 10581 | E60: 10663 | F60: 11924 | G60: 21066 | H60: 20402 | I60: 21554 | J60: 25787 | K60: 28813
A61: Total | B61: 14793 | C61: 15706 | D61: 17862 | E61: 18629 | F61: 20153 | G61: 68740 | H61: 70506 | I61: 73077 | J61: 78489 | K61: 79863
A62: Net Block | B62: 3258 | C62: 4419 | D62: 4528 | E62: 4715 | F62: 5479 | G62: 51443 | H62: 51473 | I62: 52678 | J62: 53744 | K62: 54335
A63: Capital Work in Progress | B63: 408 | C63: 229 | D63: 461 | E63: 406 | F63: 597 | G63: 745 | H63: 1313 | I63: 1132 | J63: 1025 | K63: 1009
A64: Investments | B64: 2592 | C64: 3794 | D64: 2873 | E64: 2716 | F64: 1255 | G64: 2709 | H64: 3521 | I64: 2882 | J64: 4625 | K64: 3810
A65: Other Assets | B65: 8535 | C65: 7264 | D65: 10000 | E65: 10792 | F65: 12822 | G65: 13843 | H65: 14199 | I65: 16385 | J65: 19095 | K65: 20709
A66: Total | B66: 14793 | C66: 15706 | D66: 17862 | E66: 18629 | F66: 20153 | G66: 68740 | H66: 70506 | I66: 73077 | J66: 78489 | K66: 79863
A67: Receivables | B67: 1264 | C67: 1085 | D67: 1310 | E67: 1816 | F67: 1149 | G67: 1758 | H67: 2236 | I67: 3079 | J67: 2997 | K67: 3819
A68: Inventory | B68: 2726 | C68: 2541 | D68: 2513 | E68: 2574 | F68: 2767 | G68: 3579 | H68: 4096 | I68: 4251 | J68: 4022 | K68: 4415
A69: Cash & Bank | B69: 3009 | C69: 1828 | D69: 3485 | E69: 3757 | F69: 5113 | G69: 4471 | H69: 3846 | I69: 4678 | J69: 7559 | K69: 7554
A70: No. of Equity Shares | B70: 2163936971 | C70: 2164349639 | D70: 2164528777 | E70: 2164704405 | F70: 2164704405 | G70: 2349567819 | H70: 2349591262 | I70: 2349591262 | J70: 2349591262 | K70: 2349591262
A71: New Bonus Shares
A72: Face value | B72: 1 | C72: 1 | D72: 1 | E72: 1 | F72: 1 | G72: 1 | H72: 1 | I72: 1 | J72: 1 | K72: 1
B73: =B65-SUM(B67:B69) -> 1536 | C73: =B69+B68+B67+B64+B63+B62 -> 13257
A75: Other Assets | B75: =B65-SUM(B67:B69) -> 1536 | C75: =C65-SUM(C67:C69) -> 1810 | D75: =D65-SUM(D67:D69) -> 2692 | E75: =E65-SUM(E67:E69) -> 2645 | F75: =F65-SUM(F67:F69) -> 3793 | G75: =G65-SUM(G67:G69) -> 4035 | H75: =H65-SUM(H67:H69) -> 4021 | I75: =I65-SUM(I67:I69) -> 4377 | ... K75: =K65-SUM(K67:K69) -> 4921
A80: CASH FLOW:
A81: Report Date | B81: 42460 | C81: 42825 | D81: 43190 | E81: 43555 | F81: 43921 | G81: 44286 | H81: 44651 | I81: 45016 | J81: 45382 | K81: 45747
A82: Cash from Operating Activity | B82: 4171 | C82: 5185 | D82: 6059 | E82: 5800 | F82: 7623 | G82: 9163 | H82: 9048 | I82: 9991 | J82: 15469 | K82: 11886
A83: Cash from Investing Activity | B83: -282 | C83: -1173 | D83: -1063 | E83: -438 | F83: 1791 | G83: -1228 | H83: -1728 | I83: -1484 | J83: -5324 | K83: 6473
A84: Cash from Financing Activity | B84: -3864 | C84: -4214 | D84: -4975 | E84: -5390 | F84: -6819 | G84: -9309 | H84: -8015 | I84: -8953 | J84: -10034 | K84: -13101
A85: Net Cash Flow | B85: 25 | C85: -202 | D85: 21 | E85: -28 | F85: 2595 | G85: -1374 | H85: -695 | I85: -446 | J85: 111 | K85: 5258
A90: PRICE: | B90: 869.5 | C90: 911.75 | D90: 1333.35 | E90: 1706.8 | F90: 2298.5 | G90: 2431.5 | H90: 2048.65 | I90: 2560.35 | J90: 2264.35 | K90: 2258.85
A92: DERIVED:
A93: Adjusted Equity Shares in Cr | B93: 216.39 | C93: 216.43 | D93: 216.45 | E93: 216.47 | F93: 216.48 | G93: 234.96 | H93: 234.96 | I93: 234.96 | J93: 234.96 | K93: 234.96
A96: Book value | B96: =B57+B58 -> 6573 | C96: =C57+C58 -> 6744 | D96: =D57+D58 -> 7281 | E96: =E57+E58 -> 7867 | F96: =F57+F58 -> 8229 | G96: =G57+G58 -> 47674 | H96: =H57+H58 -> 49061 | I96: =I57+I58 -> 50304 | ... K96: =K57+K58 -> 49402

Sheet Regression beta
B3: ='Data Sheet'!B1 -> HINDUSTAN UNILEVER LTD
B4: =CONCATENATE("(",B3," |"," BSE Code :",'Data Sheet'!B4,")") -> (HINDUSTAN UNILEVER LTD | BSE Code :500696)
B5: =CONCATENATE(,"INR ",'Data Sheet'!B8) -> INR 2528.9
B6: 52 week (High - INR 3,022.9 & Low - 2,136.0)
A9: # | B9: regression beta - 2 year weekly
B11: ='Data Sheet'!B1&" -"&" weekly return" -> HINDUSTAN UNILEVER LTD - weekly return | F11: Nifty 50 weekly return | I11: Market Return | L11: Leavered Beta | O11: beta 1 | P11: =SLOPE(D15:D114,G15:G114) -> 0.14896049
O12: beta 2 | P12: =_xlfn.COVARIANCE.S(D14:D114,G14:G114)/_xlfn.VAR.S(G15:G114) -> 0.14896049
B13: Date | C13: Close | D13: return | F13: Close | G13: return | I13: Year | J13: Return (%) | L13: levered Raw Beta | M13: =P12 -> 0.14896049 | O13: beta 3 | P13: =#REF! -> #REF!
B14: 45184 | C14: 2469.7 | F14: 20192.35 | I14: 2000 | J14: -0.14 | L14: raw beta weight | M14: 0.75
B15: 45191 | C15: 2482.45 | D15: =C15/C14-1 -> 0.0051625704 | F15: 19674.25 | G15: =F15/F14-1 -> -0.025658232 | I15: 2001 | J15: -0.174
B16: 45198 | C16: 2465.6 | D16: =C16/C15-1 -> -0.0067876493 | F16: 19638.3 | G16: =F16/F15-1 -> -0.0018272615 | I16: 2002 | J16: 0.032 | L16: market Beta | M16: 1
B17: 45205 | C17: 2499.4 | D17: =C17/C16-1 -> 0.013708631 | F17: 19653.5 | G17: =F17/F16-1 -> 0.00077399775 | I17: 2003 | J17: 0.719 | L17: Market Beta weight | M17: 0.25
B18: 45212 | C18: 2569.45 | D18: =C18/C17-1 -> 0.028026726 | F18: 19751.05 | G18: =F18/F17-1 -> 0.0049634925 | I18: 2004 | J18: 0.106
B19: 45219 | C19: 2495.15 | D19: =C19/C18-1 -> -0.028916694 | F19: 19542.65 | G19: =F19/F18-1 -> -0.010551338 | I19: 2005 | J19: 0.363 | L19: Adjusted beta | M19: =(M13*M14)+(M16*M17) -> 0.36172037
B20: 45226 | C20: 2482.05 | D20: =C20/C19-1 -> -0.0052501854 | F20: 19047.25 | G20: =F20/F19-1 -> -0.025349684 | I20: 2006 | J20: 0.398
B21: 45233 | C21: 2509.25 | D21: =C21/C20-1 -> 0.010958683 | F21: 19230.6 | G21: =F21/F20-1 -> 0.0096260615 | I21: 2007 | J21: 0.547
B22: 45240 | C22: 2486.55 | D22: =C22/C21-1 -> -0.0090465278 | F22: 19425.35 | G22: =F22/F21-1 -> 0.010127089 | I22: 2008 | J22: -0.518 | L22: Market return
B23: 45247 | C23: 2528.8 | D23: =C23/C22-1 -> 0.016991414 | F23: 19731.8 | G23: =F23/F22-1 -> 0.015775778 | I23: 2009 | J23: 0.757 | L23: Average return | M23: ='nifty 50 data'!N8 -> 0.15316
B24: 45254 | C24: 2515.2 | D24: =C24/C23-1 -> -0.0053780449 | F24: 19794.7 | G24: =F24/F23-1 -> 0.0031877477 | I24: 2010 | J24: 0.179 | L24: Dividend Yeild | M24: ='nifty 50 data'!N9 -> 1.36% 1
B25: 45261 | C25: 2563.65 | D25: =C25/C24-1 -> 0.019262882 | F25: 20267.9 | G25: =F25/F24-1 -> 0.023905389 | I25: 2011 | J25: -0.247 | L25: Total Return | M25: ='nifty 50 data'!N10 -> 0.15316
B26: 45268 | C26: 2522.3 | D26: =C26/C25-1 -> -0.016129347 | F26: 20969.4 | G26: =F26/F25-1 -> 0.034611381 | I26: 2012 | J26: 0.276
B27: 45275 | C27: 2522.9 | D27: =C27/C26-1 -> 0.00023787813 | F27: 21456.65 | G27: =F27/F26-1 -> 0.023236239 | I27: 2013 | J27: 0.067
B28: 45282 | C28: 2575.6 | D28: =C28/C27-1 -> 0.02088866 | F28: 21349.4 | G28: =F28/F27-1 -> -0.0049984504 | I28: 2014 | J28: 0.313
B29: 45289 | C29: 2663.95 | D29: =C29/C28-1 -> 0.034302687 | F29: 21731.4 | G29: =F29/F28-1 -> 0.017892775 | I29: 2015 | J29: -0.041
B30: 45296 | C30: 2620.05 | D30: =C30/C29-1 -> -0.016479288 | F30: 21710.8 | G30: =F30/F29-1 -> -0.00094793709 | I30: 2016 | J30: 0.03
B31: 45303 | C31: 2544 | D31: =C31/C30-1 -> -0.029026164 | F31: 21894.55 | G31: =F31/F30-1 -> 0.0084635297 | I31: 2017 | J31: 0.286
B32: 45316 | C32: 2428.3 | D32: =C32/C31-1 -> -0.04547956 | F32: 21622.4 | G32: =F32/F31-1 -> -0.012430034 | I32: 2018 | J32: 0.031
B33: 45324 | C33: 2452.6 | D33: =C33/C32-1 -> 0.010007001 | F33: 21352.6 | G33: =F33/F32-1 -> -0.012477801 | I33: 2019 | J33: 0.12
B34: 45331 | C34: 2424.15 | D34: =C34/C33-1 -> -0.011599935 | F34: 21853.8 | G34: =F34/F33-1 -> 0.023472551 | I34: 2020 | J34: 0.149
B35: 45338 | C35: 2375.25 | D35: =C35/C34-1 -> -0.020172019 | F35: 21782.5 | G35: =F35/F34-1 -> -0.0032625905 | I35: 2021 | J35: 0.241
B36: 45345 | C36: 2394.1 | D36: =C36/C35-1 -> 0.0079360067 | F36: 22040.7 | G36: =F36/F35-1 -> 0.011853552 | I36: 2022 | J36: 0.043
B37: 45358 | C37: 2419.55 | D37: =C37/C36-1 -> 0.010630299 | F37: 22212.7 | G37: =F37/F36-1 -> 0.0078037449 | I37: 2023 | J37: 0.2
B38: 45366 | C38: 2327.7 | D38: =C38/C37-1 -> -0.037961604 | F38: 22493.55 | G38: =F38/F37-1 -> 0.012643668 | I38: 2024 | J38: 0.092
B39: 45373 | C39: 2256.55 | D39: =C39/C38-1 -> -0.030566654 | F39: 22023.35 | G39: =F39/F38-1 -> -0.02090377
B40: 45379 | C40: 2264.35 | D40: =C40/C39-1 -> 0.0034566041 | F40: 22096.75 | G40: =F40/F39-1 -> 0.0033328263
B41: 45387 | C41: 2266.95 | D41: =C41/C40-1 -> 0.0011482324 | F41: 22326.9 | G41: =F41/F40-1 -> 0.010415559
B42: 45394 | C42: 2232.3 | D42: =C42/C41-1 -> -0.015284854 | F42: 22513.7 | G42: =F42/F41-1 -> 0.0083665892
B43: 45401 | C43: 2231.6 | D43: =C43/C42-1 -> -0.00031357792 | F43: 22519.4 | G43: =F43/F42-1 -> 0.00025317918
B44: 45408 | C44: 2222.65 | D44: =C44/C43-1 -> -0.0040105754 | F44: 22147 | G44: =F44/F43-1 -> -0.016536853
B45: 45415 | C45: 2217.05 | D45: =C45/C44-1 -> -0.002519515 | F45: 22419.95 | G45: =F45/F44-1 -> 0.012324468
B46: 45422 | C46: 2362.55 | D46: =C46/C45-1 -> 0.065627749 | F46: 22475.85 | G46: =F46/F45-1 -> 0.0024933151
B47: 45436 | C47: 2369.05 | D47: =C47/C46-1 -> 0.0027512645 | F47: 22055.2 | G47: =F47/F46-1 -> -0.018715644
B48: 45443 | C48: 2329.05 | D48: =C48/C47-1 -> -0.016884405 | F48: 22957.1 | G48: =F48/F47-1 -> 0.040892851
B49: 45450 | C49: 2577.8 | D49: =C49/C48-1 -> 0.1068032 | F49: 22530.7 | G49: =F49/F48-1 -> -0.018573775
B50: 45457 | C50: 2479.75 | D50: =C50/C49-1 -> -0.03803631 | F50: 23290.15 | G50: =F50/F49-1 -> 0.033707342
... B114: 45653.646 | C114: 3408.3 | D114: =C114/C113-1 -> -0.066807217 | F114: 23587.5 | G114: =F114/F113-1 -> -0.046623014
C115: 3568.35

Sheet Intrinsic value 
B4: ='Data Sheet'!B1 -> HINDUSTAN UNILEVER LTD
B5: =CONCATENATE("(",B4," |"," BSE Code :",'Data Sheet'!B4,")") -> (HINDUSTAN UNILEVER LTD | BSE Code :500696)
B6: =CONCATENATE(,"INR ",'Data Sheet'!B8) -> INR 2528.9
B7: 52 week (High - INR 3,022.9 & Low - 2,136.0)
A10: # | B10: Calculation of ROIC | F10: ='[3]Data Sheet'!G$56 -> 44286 | G10: ='[3]Data Sheet'!H$56 -> 44651 | H10: ='[3]Data Sheet'!I$56 -> 45016 | I10: ='[3]Data Sheet'!J$56 -> 45382 | J10: ='[3]Data Sheet'!K$56 -> 45747
B12: Current Assets
B13: ='[3]balance sheet'!B32 -> Inventories | F13: ='BAlance sheet HUL'!H31 -> 3579 | G13: ='BAlance sheet HUL'!I31 -> 4096 | H13: ='BAlance sheet HUL'!J31 -> 4251 | I13: ='BAlance sheet HUL'!K31 -> 4022 | J13: ='BAlance sheet HUL'!L31 -> 4415
B14: ='[3]balance sheet'!B33 -> Trade receivables | F14: ='BAlance sheet HUL'!H32 -> 1758 | G14: ='BAlance sheet HUL'!I32 -> 2236 | H14: ='BAlance sheet HUL'!J32 -> 3079 | I14: ='BAlance sheet HUL'!K32 -> 2997 | J14: ='BAlance sheet HUL'!L32 -> 3819
B15: Cash Equivalents | F15: ='BAlance sheet HUL'!H33 -> 4471 | G15: ='BAlance sheet HUL'!I33 -> 3846 | H15: ='BAlance sheet HUL'!J33 -> 4678 | I15: ='BAlance sheet HUL'!K33 -> 7559 | J15: ='BAlance sheet HUL'!L33 -> 7554
B16: ='[3]balance sheet'!B35 -> Loans n Advances | F16: ='BAlance sheet HUL'!H34 -> 78 | G16: ='BAlance sheet HUL'!I34 -> 170 | H16: ='BAlance sheet HUL'!J34 -> 188 | I16: ='BAlance sheet HUL'!K34 -> 172 | J16: ='BAlance sheet HUL'!L34 -> 242
B17: ='[3]balance sheet'!B36 -> Other asset items | F17: ='BAlance sheet HUL'!H35 -> 3957 | G17: ='BAlance sheet HUL'!I35 -> 3851 | H17: ='BAlance sheet HUL'!J35 -> 4189 | I17: ='BAlance sheet HUL'!K35 -> 4345 | J17: ='BAlance sheet HUL'!L35 -> 4679
B18: Total Current Assets | F18: =SUM(F13:F17) -> 13843 | G18: =SUM(G13:G17) -> 14199 | H18: =SUM(H13:H17) -> 16385 | I18: =SUM(I13:I17) -> 19095 | J18: =SUM(J13:J17) -> 20709
B20: Current Liabilities
B21: ='[3]Raw FS'!B13 -> Trade Payables | F21: ='BAlance sheet HUL'!H12 -> 8802 | G21: ='BAlance sheet HUL'!I12 -> 9068 | H21: ='BAlance sheet HUL'!J12 -> 9574 | I21: ='BAlance sheet HUL'!K12 -> 10486 | J21: ='BAlance sheet HUL'!L12 -> 11315
B22: Advance from Customers | F22: ='BAlance sheet HUL'!H13 -> 96 | G22: ='BAlance sheet HUL'!I13 -> 119 | H22: ='BAlance sheet HUL'!J13 -> 98 | I22: ='BAlance sheet HUL'!K13 -> 91 | J22: ='BAlance sheet HUL'!L13 -> 105
B23: ='[3]Raw FS'!B14 -> Other liability items | F23: ='BAlance sheet HUL'!H14 -> 12148 | G23: ='BAlance sheet HUL'!I14 -> 11189 | H23: ='BAlance sheet HUL'!J14 -> 11664 | I23: ='BAlance sheet HUL'!K14 -> 15005 | J23: ='BAlance sheet HUL'!L14 -> 17186
B24: Total Current Liabilities | F24: =SUM(F21:F23) -> 21046 | G24: =SUM(G21:G23) -> 20376 | H24: =SUM(H21:H23) -> 21336 | I24: =SUM(I21:I23) -> 25582 | J24: =SUM(J21:J23) -> 28606
A26: # | B26: Net working Capital | F26: =F18-F24 -> -7203 | G26: =G18-G24 -> -6177 | H26: =H18-H24 -> -4951 | I26: =I18-I24 -> -6487 | J26: =J18-J24 -> -7897
B28: Non current Assets
B29: ='BAlance sheet HUL'!B17 -> Land | F29: ='BAlance sheet HUL'!H17 -> 477 | G29: ='BAlance sheet HUL'!I17 -> 477 | H29: ='BAlance sheet HUL'!J17 -> 609 | I29: ='BAlance sheet HUL'!K17 -> 633 | J29: ='BAlance sheet HUL'!L17 -> 628
B30: ='BAlance sheet HUL'!B18 -> Building | F30: ='BAlance sheet HUL'!H18 -> 2602 | G30: ='BAlance sheet HUL'!I18 -> 2788 | H30: ='BAlance sheet HUL'!J18 -> 3101 | I30: ='BAlance sheet HUL'!K18 -> 3590 | J30: ='BAlance sheet HUL'!L18 -> 3833
B31: ='BAlance sheet HUL'!B19 -> Plant Machinery | F31: ='BAlance sheet HUL'!H19 -> 6097 | G31: ='BAlance sheet HUL'!I19 -> 6566 | H31: ='BAlance sheet HUL'!J19 -> 7612 | I31: ='BAlance sheet HUL'!K19 -> 8946 | J31: ='BAlance sheet HUL'!L19 -> 9900
B32: ='BAlance sheet HUL'!B20 -> Equipments | F32: ='BAlance sheet HUL'!H20 -> 175 | G32: ='BAlance sheet HUL'!I20 -> 181 | H32: ='BAlance sheet HUL'!J20 -> 185 | I32: ='BAlance sheet HUL'!K20 -> 206 | J32: ='BAlance sheet HUL'!L20 -> 245
B33: ='BAlance sheet HUL'!B21 -> Furniture n fittings | F33: ='BAlance sheet HUL'!H21 -> 156 | G33: ='BAlance sheet HUL'!I21 -> 152 | H33: ='BAlance sheet HUL'!J21 -> 161 | I33: ='BAlance sheet HUL'!K21 -> 165 | J33: ='BAlance sheet HUL'!L21 -> 174
B34: ='BAlance sheet HUL'!B23 -> Vehicles | F34: ='BAlance sheet HUL'!H23 -> 0 | G34: ='BAlance sheet HUL'!I23 -> 0 | H34: ='BAlance sheet HUL'!J23 -> 33 | I34: ='BAlance sheet HUL'!K23 -> 39 | J34: ='BAlance sheet HUL'!L23 -> 102
B35: ='BAlance sheet HUL'!B24 -> Intangible Assets | F35: ='BAlance sheet HUL'!H24 -> 45262 | G35: ='BAlance sheet HUL'!I24 -> 45262 | H35: ='BAlance sheet HUL'!J24 -> 45692 | I35: ='BAlance sheet HUL'!K24 -> 45692 | J35: ='BAlance sheet HUL'!L24 -> 45692
B36: ='[3]Raw FS'!B26 -> Other fixed assets | F36: ='BAlance sheet HUL'!H25 -> 155 | G36: ='BAlance sheet HUL'!I25 -> 152 | H36: ='BAlance sheet HUL'!J25 -> 171 | I36: ='BAlance sheet HUL'!K25 -> 180 | J36: ='BAlance sheet HUL'!L25 -> 190
B37: Gross Block | F37: ='BAlance sheet HUL'!H26 -> 54924 | G37: ='BAlance sheet HUL'!I26 -> 55578 | H37: ='BAlance sheet HUL'!J26 -> 57564 | I37: ='BAlance sheet HUL'!K26 -> 59451 | J37: ='BAlance sheet HUL'!L26 -> 60764
B38: ='[3]Raw FS'!B28 -> Accumulated Depreciation | F38: ='BAlance sheet HUL'!H27 -> 3481 | G38: ='BAlance sheet HUL'!I27 -> 4105 | H38: ='BAlance sheet HUL'!J27 -> 4886 | I38: ='BAlance sheet HUL'!K27 -> 5707 | J38: ='BAlance sheet HUL'!L27 -> 6429
A39: # | B39: Net NON Current Assets | F39: =SUM(F37:F38) -> 58405 | G39: =SUM(G37:G38) -> 59683 | H39: =SUM(H37:H38) -> 62450 | I39: =SUM(I37:I38) -> 65158 | J39: =SUM(J37:J38) -> 67193
A41: # | B41: Invested Capital | F41: =F39+F26 -> 51202 | G41: =G39+G26 -> 53506 | H41: =H39+H26 -> 57499 | I41: =I39+I26 -> 58671 | J41: =J39+J26 -> 59296
B42: EBIT | F42: ='Profit & Loss'!G32 -> 10722 | G42: ='Profit & Loss'!H32 -> 11985 | H42: ='Profit & Loss'!I32 -> 13458 | I42: ='Profit & Loss'!J32 -> 14260 | J42: ='Profit & Loss'!K32 -> 14810
A44: # | B44: ROIC | F44: =F42/F41 -> 0.20940588 | G44: =G42/G41 -> 0.22399357 | H44: =H42/H41 -> 0.23405624 | I44: =I42/I41 -> 0.24305023 | J44: =J42/J41 -> 0.2497639
A46: # | B46: Calculation of Reinvestment Rate | F46: =F10 -> 44286 | G46: =G10 -> 44651 | H46: =H10 -> 45016 | I46: =I10 -> 45382 | J46: =J10 -> 45747
B48: Net Capital Expenditure | F48: =SUM('BAlance sheet HUL'!H54:H55) -> -4066 | G48: =SUM('BAlance sheet HUL'!I54:I55) -> -1053 | H48: =SUM('BAlance sheet HUL'!J54:J55) -> -1011 | I48: =SUM('BAlance sheet HUL'!K54:K55) -> -1457 | J48: =SUM('BAlance sheet HUL'!L54:L55) -> -1262
B49: Change In Working Capital | G49: =G26-F26 -> 1026 | H49: =H26-G26 -> 1226 | I49: =I26-H26 -> -1536 | J49: =J26-I26 -> -1410
B51: EBIT | F51: =F42 -> 10722 | G51: =G42 -> 11985 | H51: =H42 -> 13458 | I51: =I42 -> 14260 | J51: =J42 -> 14810
B52: Tax Rate | F52: 0.25 | G52: 0.25 | H52: 0.25 | I52: 0.25 | J52: 0.25
B53: EBIT(1-Tax) | F53: =F51*(1-F52) -> 8041.5 | G53: =G51*(1-G52) -> 8988.75 | H53: =H51*(1-H52) -> 10093.5 | I53: =I51*(1-I52) -> 10695 | J53: =J51*(1-J52) -> 11107.5
B55: Reinvestment | G55: =SUM(G48:G49) -> -27 | H55: =SUM(H48:H49) -> 215 | I55: =SUM(I48:I49) -> -2993 | J55: =SUM(J48:J49) -> -2672
B57: Reinvestment Rate | G57: =G55/G53 -> -0.0030037547 | H57: =H55/H53 -> 0.021300837 | I57: =I55/I53 -> -0.2798504 | J57: =J55/J53 -> -0.24055818
I59: 4 year Average | J59: =AVERAGE(G57:J57) -> -0.12552787
I60: 4 Year Median | J60: =MEDIAN(G57:J57) -> -0.12178097
A62: # | B62: Calculation of Reinvestment Rate | F62: =F46 -> 44286 | G62: =G46 -> 44651 | H62: =H46 -> 45016 | I62: =I46 -> 45382 | J62: =J46 -> 45747
B64: ROIC | G64: =G44 -> 0.22399357 | H64: =H44 -> 0.23405624 | I64: =I44 -> 0.24305023 | J64: =J44 -> 0.2497639
B65: Reinvestment Rate | G65: =G57 -> -0.0030037547 | H65: =H57 -> 0.021300837 | I65: =I57 -> -0.2798504 | J65: =J57 -> -0.24055818
B67: Intrinsic Growth rate | G67: =G65*G64 -> -0.00067282174 | H67: =H65*H64 -> 0.004985594 | I67: =I65*I64 -> -0.068017703 | J67: =J65*J64 -> -0.060082749
I69: 4 year Average | J69: =AVERAGE(G67:J67) -> -0.03094692
I70: 4 Year Median | J70: =MEDIAN(G67:J67) -> -0.030377785

Sheet DCF
B3: ='Data Sheet'!B1 -> HINDUSTAN UNILEVER LTD
B4: =CONCATENATE("(",B3," |"," BSE Code :",'Data Sheet'!B4,")") -> (HINDUSTAN UNILEVER LTD | BSE Code :500696)
B5: =CONCATENATE(,"INR ",'Data Sheet'!B8) -> INR 2528.9
B6: 52 week (High - INR 3,022.9 & Low - 2,136.0)
A8: # | B8: Calculation of PV of FCFF | G8: ='[3]Intrinsic value'!J39 -> 45747 | H8: =G8+365 -> 46112 | I8: =H8+365 -> 46477 | J8: =I8+365 -> 46842 | K8: =J8+365 -> 47207 | L8: =K8+365 -> 47572
B10: EBIT | G10: ='Profit & Loss'!K32 -> 14810 | H10: =G10*(1+$D$20) -> 17943.796 | I10: =H10*(1+$D$20) -> 21740.703 | J10: =I10*(1+$D$20) -> 26341.036 | K10: =J10*(1+$D$20) -> 31914.799 | L10: =K10*(1+$D$20) -> 38667.971
B11: tax rate | G11: 0.25 | H11: 0.25 | I11: 0.25 | J11: 0.25 | K11: 0.25 | L11: 0.25
B12: EBIT( 1- TAX ) | G12: =G10*(1-G11) -> 11107.5 | H12: =H10*(1-H11) -> 13457.847 | I12: =I10*(1-I11) -> 16305.527 | J12: =J10*(1-J11) -> 19755.777 | K12: =K10*(1-K11) -> 23936.099 | L12: =L10*(1-L11) -> 29000.978
B13: Less: Reinvestment rate | G13: ='Intrinsic value '!J57 -> -0.24055818 | H13: =G13+(($L$13-($G$13))/4) -> -0.092093636 | I13: =H13+(($L$13-($G$13))/4) -> 0.056370909 | J13: =I13+(($L$13-($G$13))/4) -> 0.20483545 | K13: =J13+(($L$13-($G$13))/4) -> 0.3533 | L13: 0.3533
B14: Free Cash Flow to Firm (FCFF) | G14: =G12*(1-(G13)) -> 13779.5 | H14: =H12*(1-(H13)) -> 14697.229 | I14: =I12*(1-(I13)) -> 15386.37 | J14: =J12*(1-(J13)) -> 15709.093 | K14: =K12*(1-(K13)) -> 15479.476 | L14: =L12*(1-(L13)) -> 18754.933
B15: Mid Year Convention | H15: 0.5 | I15: =+H15+1 -> 1.5 | J15: =+I15+1 -> 2.5 | K15: =+J15+1 -> 3.5 | L15: =+K15+1 -> 4.5
B16: Discounted Factor | H16: =1/(1+$D$22)^H15 -> 0.95922088 | I16: =1/(1+$D$22)^I15 -> 0.88258364 | J16: =1/(1+$D$22)^J15 -> 0.81206935 | K16: =1/(1+$D$22)^K15 -> 0.74718883 | L16: =1/(1+$D$22)^L15 -> 0.68749195
B18: PV of FCFF | H18: =H14*H16 -> 14097.889 | I18: =I14*I16 -> 13579.758 | J18: =J14*J16 -> 12756.873 | K18: =K14*K16 -> 11566.091 | L18: =L14*L16 -> 12893.865
B20: Expected Growth | D20: 0.2116
B21: Terminal Growth | D21: 0.058
B22: WACC | D22: ='real wacc'!J48 -> 0.086832838
A24: # | B24: Calculation of Terminal Value | G24: Sensitivity Analysis
B26: FCFF (n+1) | E26: =L14*(1+D21) -> 19842.719 | H26: Enterprice Value (in INR)
B27: WACC | E27: =D22 -> 0.086832838
B28: Terminal Growth Rate | E28: =D21 -> 0.058 | H28: WACC | R28: 2315.0047
G29: Terminal Growth Rate | H29: =E42 -> 543931.47 | I29: 0.05 | J29: 0.07 | K29: 0.0868 | L29: 0.105
B30: Terminal value | E30: =E26/(E27-E28) -> 688198.59 | H30: 0.04 | I30: 1434971.4 | J30: 525524.12 | K30: 362289.99 | L30: 280672.93
H31: 0.058 | I31: -1634413.2 | J31: 1207609.6 | K31: 544470.94 | L31: 361049.61 | R31: 543931.47
H32: 0.08 | I32: -383923.17 | J32: -1293370.5 | K32: 2076934.2 | L32: 616468.85
A33: # | B33: Calculation of Equity Value Per Share | H33: 0.1 | I33: -202033.71 | J33: -383923.17 | K33: -962662.35 | L33: 2799142.3 | R33: 0.086832838
B35: PV of FCFF | E35: =SUM(H18:L18) -> 64894.477
B36: PV of Terminal value | E36: =E30*L16 -> 473130.99
B37: Value of Operational Assets | E37: =SUM(E35:E36) -> 538025.47
B39: Add: Cash | E39: ='Data Sheet'!K69 -> 7554
B40: Less: Debt | E40: ='Data Sheet'!K59 -> 1648
B41: Net Debt | E41: =E40-E39 -> -5906
B42: value Of Equity | E42: =E37-E41 -> 543931.47
B43: NO of Shares | E43: ='Data Sheet'!B6 -> 244.7425
B45: Equity Value Per share | E45: =E42/E43 -> 2222.4643
B47: Share Price | E47: ='Data Sheet'!B8 -> 2528.9
B48: Discount/Premium | E48: =E47/E45 -> 1.137881

Sheet Comps_Val
B3: ='dupont analysis'!B3 -> HINDUSTAN UNILEVER LTD
B4: ='dupont analysis'!$B$4 -> (HINDUSTAN UNILEVER LTD | BSE Code :500696)
B5: ='dupont analysis'!$B$5 -> INR 2528.9
B6: ='dupont analysis'!$B$6 -> 52 week (High - INR 3,022.9 & Low - 2,136.0)
B9: Figures in INR(Cr.)
B10: comparable Company Valuation
D12: Market Data | K12: Financials | O12: Valuation
B13: Company | C13: Ticker | D13: Share Price | E13: Shares Outstanding | F13: Equity Value | G13: Net Debt | H13: Enterprise Value | K13: Revenue | L13: EBITDA | M13: Net Income | O13: EV/Revenue | P13: EV/EBITDA | Q13: P/E
B15: =Sheet2!C5 -> Hind. Unilever | D15: =Sheet2!D5 -> 2584 | E15: =Sheet2!G5 -> 234.96 | F15: =E15*D15 -> 607136.64 | G15: =Sheet2!O5 -> -5906 | H15: =Sheet2!F5 -> 601344.18 | K15: =Sheet2!I5 -> 63928 | L15: =Sheet2!P5 -> 15779 | M15: =Sheet2!L5 -> 10827 | O15: =$H15/K15 -> 9.4065852 | P15: =$H15/L15 -> 38.110411 | Q15: =F15/M15 -> 56.076165
B16: =Sheet2!C5 -> Hind. Unilever | D16: =Sheet2!D5 -> 2584 | E16: =Sheet2!G5 -> 234.96 | F16: =E16*D16 -> 607136.64 | G16: =Sheet2!O5 -> -5906 | H16: =Sheet2!F5 -> 601344.18 | K16: =Sheet2!I5 -> 63928 | L16: =Sheet2!P5 -> 15779 | M16: =Sheet2!L5 -> 10827 | O16: =$H16/K16 -> 9.4065852 | P16: =$H16/L16 -> 38.110411 | Q16: =F16/M16 -> 56.076165
B17: =Sheet2!C6 -> ITC | D17: =Sheet2!D6 -> 413.6 | E17: =Sheet2!G6 -> 1252.67 | F17: =E17*D17 -> 518104.31 | G17: =Sheet2!O6 -> -3727.82 | H17: =Sheet2!F6 -> 514437.38 | K17: =Sheet2!I6 -> 79040.32 | L17: =Sheet2!P6 -> 28954.46 | M17: =Sheet2!L6 -> 35218.9 | O17: =$H17/K17 -> 6.5085437 | P17: =$H17/L17 -> 17.767121 | Q17: =F17/M17 -> 14.710974
B18: =Sheet2!C7 -> Nestle India | D18: =Sheet2!D7 -> 1217.45 | E18: =Sheet2!G7 -> 192.83 | F18: =E18*D18 -> 234760.88 | G18: =Sheet2!O7 -> 1071.2 | H18: =Sheet2!F7 -> 235930.01 | K18: =Sheet2!I7 -> 20483.77 | L18: =Sheet2!P7 -> 4783.42 | M18: =Sheet2!L7 -> 3227.13 | O18: =$H18/K18 -> 11.5179 | P18: =$H18/L18 -> 49.322453 | Q18: =F18/M18 -> 72.746026
B19: =Sheet2!C8 -> Varun Beverages | D19: =Sheet2!D8 -> 469.9 | E19: =Sheet2!G8 -> 338.2 | F19: =E19*D19 -> 158920.18 | G19: =Sheet2!O8 -> -311.8 | H19: =Sheet2!F8 -> 158924.38 | K19: =Sheet2!I8 -> 21077.78 | L19: =Sheet2!P8 -> 5165.4 | M19: =Sheet2!L8 -> 2881.31 | O19: =$H19/K19 -> 7.5399013 | P19: =$H19/L19 -> 30.7671 | Q19: =F19/M19 -> 55.15553
B20: =Sheet2!C9 -> Britannia Inds. | D20: =Sheet2!D9 -> 6251 | E20: =Sheet2!G9 -> 24.09 | F20: =E20*D20 -> 150586.59 | G20: =Sheet2!O9 -> 934.03 | H20: =Sheet2!F9 -> 151486.47 | K20: =Sheet2!I9 -> 18314.59 | L20: =Sheet2!P9 -> 3404.08 | M20: =Sheet2!L9 -> 2193.11 | O20: =$H20/K20 -> 8.2713547 | P20: =$H20/L20 -> 44.501442 | Q20: =F20/M20 -> 68.663492
B21: =Sheet2!C10 -> Godrej Consumer | D21: =Sheet2!D10 -> 1253.8 | E21: =Sheet2!G10 -> 102.31 | F21: =E21*D21 -> 128276.28 | G21: =Sheet2!O10 -> 3526.13 | H21: =Sheet2!F10 -> 131531.36 | K21: =Sheet2!I10 -> 14694.57 | L21: =Sheet2!P10 -> 3296.63 | M21: =Sheet2!L10 -> 1853.97 | O21: =$H21/K21 -> 8.951018 | P21: =$H21/L21 -> 39.898733 | Q21: =F21/M21 -> 69.190051
B22: =Sheet2!C11 -> Tata Consumer | D22: =Sheet2!D11 -> 1102.5 | E22: =Sheet2!G11 -> 98.95 | F22: =E22*D22 -> 109092.38 | G22: =Sheet2!O11 -> -425.18 | H22: =Sheet2!F11 -> 108695.95 | K22: =Sheet2!I11 -> 18045.14 | L22: =Sheet2!P11 -> 2614.16 | M22: =Sheet2!L11 -> 1329.6 | O22: =$H22/K22 -> 6.0235581 | P22: =$H22/L22 -> 41.579685 | Q22: =F22/M22 -> 82.049019
B23: =Sheet2!C12 -> Dabur India | D23: =Sheet2!D12 -> 538.8 | E23: =Sheet2!G12 -> 177.37 | F23: =E23*D23 -> 95566.956 | G23: =Sheet2!O12 -> 372.36 | H23: =Sheet2!F12 -> 95938.78 | K23: =Sheet2!I12 -> 12618.56 | L23: =Sheet2!P12 -> 2894.15 | M23: =Sheet2!L12 -> 1754.36 | O23: =$H23/K23 -> 7.6029896 | P23: =$H23/L23 -> 33.149208 | Q23: =F23/M23 -> 54.473971
B24: =Sheet2!C13 -> Marico | D24: =Sheet2!D13 -> 736.1 | E24: =Sheet2!G13 -> 129.79 | F24: =E24*D24 -> 95538.419 | G24: =Sheet2!O13 -> -223 | H24: =Sheet2!F13 -> 95302.71 | K24: =Sheet2!I13 -> 11447 | L24: =Sheet2!P13 -> 2395 | M24: =Sheet2!L13 -> 1697 | O24: =$H24/K24 -> 8.3255622 | P24: =$H24/L24 -> 39.792363 | Q24: =F24/M24 -> 56.29842
B26: High | O26: =MAX(O15:O24) -> 11.5179 | P26: =MAX(P15:P24) -> 49.322453 | Q26: =MAX(Q15:Q24) -> 82.049019
B27: 75th Percentile | O27: =QUARTILE(O15:O24,3) -> 9.2926934 | P27: =QUARTILE(P15:P24,3) -> 41.159447 | Q27: =QUARTILE(Q15:Q24,3) -> 69.058411
B28: Average | O28: =AVERAGE(O15:O24) -> 8.3553998 | P28: =AVERAGE(P15:P24) -> 37.299893 | Q28: =AVERAGE(Q15:Q24) -> 58.543981
B29: Median | O29: =MEDIAN(O15:O24) -> 8.2984584 | P29: =MEDIAN(P15:P24) -> 38.951387 | Q29: =MEDIAN(Q15:Q24) -> 56.187293
B30: 25th Percentile | O30: =QUARTILE(O15:O24,1) -> 7.5556733 | P30: =QUARTILE(P15:P24,1) -> 34.389509 | Q30: =QUARTILE(Q15:Q24,1) -> 55.385689
B31: Low | O31: =MIN(O15:O24) -> 6.0235581 | P31: =MIN(P15:P24) -> 17.767121 | Q31: =MIN(Q15:Q24) -> 14.710974
B33: Hindustan Unilever Comparable Valuation | O33: EV/Revenue | P33: EV/EBITDA | Q33: P/E
B35: Implied Enterprise Value | O35: =O$29*K15 -> 530503.85 | P35: =P$29*L15 -> 614613.94 | Q35: =+Q37+Q36 -> 602433.82
B36: Net Debt | O36: =$G$15 -> -5906 | P36: =$G$15 -> -5906 | Q36: =$G$15 -> -5906 | V36: 2282.9837
B37: Implied Market Value | O37: =O35-O36 -> 536409.85 | P37: =P35-P36 -> 620519.94 | Q37: =Q29*M15 -> 608339.82
B38: Shares Outstanding | O38: =$E$15 -> 234.96 | P38: =$E$15 -> 234.96 | Q38: =$E$15 -> 234.96 | V38: 2640.9599 | Y38: 2589.1208
B40: Implied Value per Share | O40: =O37/O38 -> 2282.9837 | P40: =P37/P38 -> 2640.9599 | Q40: =Q37/Q38 -> 2589.1208
B42: Source: The Valuation School, Screener.in
O43: =IF(O40>$D$15,"Undervalued","Overvalued") -> Overvalued | P43: =IF(P40>$D$15,"Undervalued","Overvalued") -> Undervalued | Q43: =IF(Q40>$D$15,"Undervalued","Overvalued") -> Undervalued

Sheet historical approch
B3: ='dupont analysis'!B3 -> HINDUSTAN UNILEVER LTD
B4: ='dupont analysis'!$B$4 -> (HINDUSTAN UNILEVER LTD | BSE Code :500696)
B5: ='dupont analysis'!$B$5 -> INR 2528.9
B6: ='dupont analysis'!$B$6 -> 52 week (High - INR 3,022.9 & Low - 2,136.0)
A8: # | B8: Date | C8: Close | D8: Returns | E8: Sorted Return | H8: ="Calculation of Value At Risk"&" - "&'Data Sheet'!B1&"(Historical)" -> Calculation of Value At Risk - HINDUSTAN UNILEVER LTD(Historical)
B9: 41394 | C9: 583.8 | D9: =(C9-C10)/C10 -> -0.76121723 | E9: 0.17382125
B10: 43928 | C10: 2444.9 | D10: =(C10-C11)/C11 -> 8.7678785 | E10: 0.13499838 | H10: Mean | L10: =AVERAGE(E10:E5851) -> 0.0034255361
B11: 36672 | C11: 250.3 | D11: =(C11-C12)/C12 -> -0.87800361 | E11: 0.11925949 | H11: Std Deviation | L11: =_xlfn.STDEV.S(E10:E5851) -> 0.015074527
B12: 43910 | C12: 2051.7 | D12: =(C12-C13)/C13 -> 7.9320853 | E12: 0.11608551 | H12: min | L12: =MIN(E10:E5851) -> -0.020893532
B13: 36950 | C13: 229.7 | D13: =(C13-C14)/C14 -> -0.046887967 | E13: 0.11423721 | H13: max | L13: =MAX(E10:E5851) -> 0.13499838
B14: 36650 | C14: 241 | D14: =(C14-C15)/C15 -> -0.64820086 | E14: 0.10247027 | H14: CMP | L14: ='Data Sheet'!B8 -> 2528.9
B15: 41472 | C15: 685.05 | D15: =(C15-C16)/C16 -> 2.7271491 | E15: 0.099422244
B16: 39149 | C16: 183.8 | D16: =(C16-C17)/C17 -> -0.19755512 | E16: 0.098625224 | H16: Percentile | I16: Confidence | J16: VAR % | K16: Stock Price | L16: VAR(INR)
B17: 38898 | C17: 229.05 | D17: =(C17-C18)/C18 -> -0.00304679 | E17: 0.09305655 | H17: 0.05 | I17: =1-H17 -> 0.95 | J17: =_xlfn.PERCENTILE.INC($E$10:$E$5851,H17) -> -0.016373707 | K17: =$L$14*(1-(J17)) -> 2570.3075 | L17: =$L$14-K17 -> -41.407467
B18: 37174 | C18: 229.75 | D18: =(C18-C19)/C19 -> -0.88336083 | E18: 0.088089036 | H18: 0.03 | I18: =1-H18 -> 0.97 | J18: =_xlfn.PERCENTILE.INC($E$10:$E$5851,H18) -> -0.017750072 | K18: =$L$14*(1-(J18)) -> 2573.7882 | L18: =$L$14-K18 -> -44.888156
B19: 43728 | C19: 1969.75 | D19: =(C19-C20)/C20 -> -0.028651034 | E19: 0.086608744 | H19: 0.01 | I19: =1-H19 -> 0.99 | J19: =_xlfn.PERCENTILE.INC($E$10:$E$5851,H19) -> -0.019860293 | K19: =$L$14*(1-(J19)) -> 2579.1247 | L19: =$L$14-K19 -> -50.224696
B20: 43914 | C20: 2027.85 | D20: =(C20-C21)/C21 -> 2.3609845 | E20: 0.084585762 | H20: 0.005 | I20: =1-H20 -> 0.995 | J20: =_xlfn.PERCENTILE.INC($E$10:$E$5851,H20) -> -0.020331789 | K20: =$L$14*(1-(J20)) -> 2580.3171 | L20: =$L$14-K20 -> -51.417062
B21: 41789 | C21: 603.35 | D21: =(C21-C22)/C22 -> 1.9605005 | E21: 0.084284302
B22: 37152 | C22: 203.8 | D22: =(C22-C23)/C23 -> 0.0096606391 | E22: 0.083466241
B23: 38883 | C23: 201.85 | D23: =(C23-C24)/C24 -> -0.31137418 | E23: 0.083176818
B24: 36578 | C24: 293.12 | D24: =(C24-C25)/C25 -> 0.12504798 | E24: 0.080029477
B25: 36619 | C25: 260.54 | D25: =(C25-C26)/C26 -> -0.040014738 | E25: 0.080003316
B26: 36577 | C26: 271.4 | D26: =(C26-C27)/C27 -> -0.058162132 | E26: 0.079984083
B27: 36600 | C27: 288.16 | D27: =(C27-C28)/C28 -> 0.14667728 | E27: 0.079979012
B28: 36574 | C28: 251.3 | D28: =(C28-C29)/C29 -> 0.93904321 | E28: 0.079884835
B29: 38125 | C29: 129.6 | D29: =(C29-C30)/C30 -> -0.46446281 | E29: 0.078202995
B30: 38870 | C30: 242 | D30: =(C30-C31)/C31 -> 0.20909318 | E30: 0.075555556
B31: 39472 | C31: 200.15 | D31: =(C31-C32)/C32 -> -0.57969341 | E31: 0.075208165
B32: 41114 | C32: 476.2 | D32: =(C32-C33)/C33 -> 0.86161063 | E32: 0.075064906
... B6359: 38124 | C6359: 120.2 | D6359: =(C6359-C6360)/C6360 -> -0.4791125 | E6359: -0.1508301
B6360: 36528 | C6360: 230.76

Sheet monte Corle simulation
B5: ='Data Sheet'!B1 -> HINDUSTAN UNILEVER LTD
B6: =CONCATENATE("(",B5," |"," BSE Code :",'Data Sheet'!B4,")") -> (HINDUSTAN UNILEVER LTD | BSE Code :500696)
B7: =CONCATENATE(,"INR ",'Data Sheet'!B8) -> INR 2528.9
B8: 52 week (High - INR 3,022.9 & Low - 2,136.0)
A10: # | B10: Date | C10: Close | D10: Returns | E10: Sorted Return | F10: Replication | G10: Simulation Return | I10: ="Calculation of Value At Risk"&" - "&'Data Sheet'!B1&"(Simulation)" -> Calculation of Value At Risk - HINDUSTAN UNILEVER LTD(Simulation)
B11: 45912 | C11: 2580.5 | D11: =(C11-C12)/C12 -> -0.015827613 | E11: -0.015827613 | F11: 1 | G11: =_xlfn.NORM.INV(RAND(),$M$13,$M$14) -> 0.013415644
B12: 45911 | C12: 2622 | D12: =(C12-C13)/C13 -> -0.0081331568 | E12: -0.0081331568 | F12: 2 | G12: =_xlfn.NORM.INV(RAND(),$M$13,$M$14) -> -0.0080240499 | I12: Historical Approch
B13: 45910 | C13: 2643.5 | D13: =(C13-C14)/C14 -> 0.0005677517 | E13: 0.0005677517 | F13: 3 | G13: =_xlfn.NORM.INV(RAND(),$M$13,$M$14) -> 0.014434273 | I13: Mean | M13: =AVERAGE(E11:E5853) -> -0.0037632899
B14: 45909 | C14: 2642 | D14: =(C14-C15)/C15 -> 0.0068981287 | E14: 0.0068981287 | F14: 4 | G14: =_xlfn.NORM.INV(RAND(),$M$13,$M$14) -> -0.0028980272 | I14: Std Deviation | M14: =_xlfn.STDEV.S(E11:E5853) -> 0.019591759
B15: 45908 | C15: 2623.9 | D15: =(C15-C16)/C16 -> -0.0036075036 | E15: -0.0036075036 | F15: 5 | G15: =_xlfn.NORM.INV(RAND(),$M$13,$M$14) -> 0.0093870392 | I15: min | M15: =MIN(E11:E5853) -> -0.17840284
B16: 45905 | C16: 2633.4 | D16: =(C16-C17)/C17 -> -0.012450311 | E16: -0.012450311 | F16: 6 | G16: =_xlfn.NORM.INV(RAND(),$M$13,$M$14) -> 0.059273545 | I16: max | M16: =MAX(E11:E5853) -> 0.059595059
B17: 45904 | C17: 2666.6 | D17: =(C17-C18)/C18 -> 0.00071302586 | E17: 0.00071302586 | F17: 7 | G17: =_xlfn.NORM.INV(RAND(),$M$13,$M$14) -> -0.0069592472 | I17: CMP | M17: ='Data Sheet'!B8 -> 2528.9
B18: 45903 | C18: 2664.7 | D18: =(C18-C19)/C19 -> -0.0045946956 | E18: -0.0045946956 | F18: 8 | G18: =_xlfn.NORM.INV(RAND(),$M$13,$M$14) -> 0.0050790332
B19: 45902 | C19: 2677 | D19: =(C19-C20)/C20 -> 0.010379317 | E19: 0.010379317 | F19: 9 | G19: =_xlfn.NORM.INV(RAND(),$M$13,$M$14) -> -0.052666373 | I19: Monte Corle Simulation
B20: 45901 | C20: 2649.5 | D20: =(C20-C21)/C21 -> -0.0038724716 | E20: -0.0038724716 | F20: 10 | G20: =_xlfn.NORM.INV(RAND(),$M$13,$M$14) -> -0.021855694 | I20: Mean | M20: =AVERAGE(G11:G5854) -> -0.0041074388
B21: 45898 | C21: 2659.8 | D21: =(C21-C22)/C22 -> 0.002034358 | E21: 0.002034358 | F21: 11 | G21: =_xlfn.NORM.INV(RAND(),$M$13,$M$14) -> 0.032476497 | I21: Std Deviation | M21: =_xlfn.STDEV.S(G11:G5854) -> 0.019652483
B22: 45897 | C22: 2654.4 | D22: =(C22-C23)/C23 -> -0.014187031 | E22: -0.014187031 | F22: 12 | G22: =_xlfn.NORM.INV(RAND(),$M$13,$M$14) -> -0.013697561 | I22: min | M22: =MIN(G11:G5854) -> -0.074817093
B23: 45895 | C23: 2692.6 | D23: =(C23-C24)/C24 -> 0.023179815 | E23: 0.023179815 | F23: 13 | G23: =_xlfn.NORM.INV(RAND(),$M$13,$M$14) -> 0.0086977657 | I23: max | M23: =MAX(G11:G5854) -> 0.071630319
B24: 45894 | C24: 2631.6 | D24: =(C24-C25)/C25 -> 0.00064641241 | E24: 0.00064641241 | F24: 14 | G24: =_xlfn.NORM.INV(RAND(),$M$13,$M$14) -> -0.021787989 | I24: CMP | M24: =M17 -> 2528.9
B25: 45891 | C25: 2629.9 | D25: =(C25-C26)/C26 -> -0.0068353474 | E25: -0.0068353474 | F25: 15 | G25: =_xlfn.NORM.INV(RAND(),$M$13,$M$14) -> -0.00020393738
B26: 45890 | C26: 2648 | D26: =(C26-C27)/C27 -> -0.0081654056 | E26: -0.0081654056 | F26: 16 | G26: =_xlfn.NORM.INV(RAND(),$M$13,$M$14) -> -0.013232445 | I26: Percentile | J26: Confidence | K26: VAR % | L26: Stock Price | M26: VAR(INR)
B27: 45889 | C27: 2669.8 | D27: =(C27-C28)/C28 -> 0.024953931 | E27: 0.024953931 | F27: 17 | G27: =_xlfn.NORM.INV(RAND(),$M$13,$M$14) -> -0.039140553 | I27: 0.05 | J27: =1-I27 -> 0.95 | K27: =_xlfn.PERCENTILE.INC(G11:G5854,I27) -> -0.036757809 | L27: =$M$17*(1-(K27)) -> 2621.8568 | M27: =$M$17-L27 -> -92.956822
B28: 45888 | C28: 2604.8 | D28: =(C28-C29)/C29 -> 0.014290721 | E28: 0.014290721 | F28: 18 | G28: =_xlfn.NORM.INV(RAND(),$M$13,$M$14) -> -0.0075647311 | I28: 0.03 | J28: =1-I28 -> 0.97 | K28: =_xlfn.PERCENTILE.INC(G12:G5855,I28) -> -0.041116747 | L28: =$M$17*(1-(K28)) -> 2632.8801 | M28: =$M$17-L28 -> -103.98014
B29: 45887 | C29: 2568.1 | D29: =(C29-C30)/C30 -> 0.035273724 | E29: 0.035273724 | F29: 19 | G29: =_xlfn.NORM.INV(RAND(),$M$13,$M$14) -> 0.004760991 | I29: 0.01 | J29: =1-I29 -> 0.99 | K29: =_xlfn.PERCENTILE.INC(G13:G5856,I29) -> -0.049117706 | L29: =$M$17*(1-(K29)) -> 2653.1138 | M29: =$M$17-L29 -> -124.21377
B30: 45883 | C30: 2480.6 | D30: =(C30-C31)/C31 -> -0.0058113903 | E30: -0.0058113903 | F30: 20 | G30: =_xlfn.NORM.INV(RAND(),$M$13,$M$14) -> 0.011558841 | I30: 0.005 | J30: =1-I30 -> 0.995 | K30: =_xlfn.PERCENTILE.INC(G14:G5857,I30) -> -0.054479554 | L30: =$M$17*(1-(K30)) -> 2666.6733 | M30: =$M$17-L30 -> -137.77334
B31: 45882 | C31: 2495.1 | D31: =(C31-C32)/C32 -> 0.0045494806 | E31: 0.0045494806 | F31: 21 | G31: =_xlfn.NORM.INV(RAND(),$M$13,$M$14) -> -0.0044041796
B32: 45881 | C32: 2483.8 | D32: =(C32-C33)/C33 -> -0.013738882 | E32: -0.013738882 | F32: 22 | G32: =_xlfn.NORM.INV(RAND(),$M$13,$M$14) -> 0.019779432
B33: 45880 | C33: 2518.4 | D33: =(C33-C34)/C34 -> 0.0079244377 | E33: 0.0079244377 | F33: 23 | G33: =_xlfn.NORM.INV(RAND(),$M$13,$M$14) -> -0.040895247
B34: 45877 | C34: 2498.6 | D34: =(C34-C35)/C35 -> -0.0075074479 | E34: -0.0075074479 | F34: 24 | G34: =_xlfn.NORM.INV(RAND(),$M$13,$M$14) -> -0.023375092
B35: 45876 | C35: 2517.5 | D35: =(C35-C36)/C36 -> -0.0071383499 | E35: -0.0071383499 | F35: 25 | G35: =_xlfn.NORM.INV(RAND(),$M$13,$M$14) -> -0.014353744
B36: 45875 | C36: 2535.6 | D36: =(C36-C37)/C37 -> 0.00035507161 | E36: 0.00035507161 | F36: 26 | G36: =_xlfn.NORM.INV(RAND(),$M$13,$M$14) -> -0.00269054
B37: 45874 | C37: 2534.7 | D37: =(C37-C38)/C38 -> -0.0035381531 | E37: -0.0035381531 | F37: 27 | G37: =_xlfn.NORM.INV(RAND(),$M$13,$M$14) -> -0.018623899
B38: 45873 | C38: 2543.7 | D38: =(C38-C39)/C39 -> -0.0039158868 | E38: -0.0039158868 | F38: 28 | G38: =_xlfn.NORM.INV(RAND(),$M$13,$M$14) -> 0.0096337277
B39: 45870 | C39: 2553.7 | D39: =(C39-C40)/C40 -> 0.012890687 | E39: 0.012890687 | F39: 29 | G39: =_xlfn.NORM.INV(RAND(),$M$13,$M$14) -> -0.0058358876
B40: 45869 | C40: 2521.2 | D40: =(C40-C41)/C41 -> 0.034380898 | E40: 0.034380898 | F40: 30 | G40: =_xlfn.NORM.INV(RAND(),$M$13,$M$14) -> -0.019547398
B41: 45868 | C41: 2437.4 | D41: =(C41-C42)/C42 -> -0.0066025432 | E41: -0.0066025432 | F41: 31 | G41: =_xlfn.NORM.INV(RAND(),$M$13,$M$14) -> 0.032723098
B42: 45867 | C42: 2453.6 | D42: =(C42-C43)/C43 -> 0.00491481 | E42: 0.00491481 | F42: 32 | G42: =_xlfn.NORM.INV(RAND(),$M$13,$M$14) -> -0.031460887
... B1010: 44433 | C1010: 2645 | D1010: =(C1010-C1011)/C1011 -> 0.0045575389 | E1010: -0.029209622 | F1010: 1000 | G1010: =_xlfn.NORM.INV(RAND(),$M$13,$M$14) -> -0.026135222
B1011: 44432 | C1011: 2633 | D1011: =(C1011-C1012)/C1012 -> -0.00043657347 | E1011: -0.029148449 | G1011: =_xlfn.NORM.INV(RAND(),$M$13,$M$14) -> 0.0049148021
B1012: 44431 | C1012: 2634.15 | D1012: =(C1012-C1013)/C1013 -> 0.0056310605 | E1012: -0.029147065 | G1012: =_xlfn.NORM.INV(RAND(),$M$13,$M$14) -> 0.00197644
B1013: 44428 | C1013: 2619.4 | D1013: =(C1013-C1014)/C1014 -> 0.053639307 | E1013: -0.029112754 | G1013: =_xlfn.NORM.INV(RAND(),$M$13,$M$14) -> 0.016328368
B1014: 44426 | C1014: 2486.05 | D1014: =(C1014-C1015)/C1015 -> 0.00090587004 | E1014: -0.029078845 | G1014: =_xlfn.NORM.INV(RAND(),$M$13,$M$14) -> -0.0059242696
B1015: 44425 | C1015: 2483.8 | D1015: =(C1015-C1016)/C1016 -> 0.023656446 | E1015: -0.02892562 | G1015: =_xlfn.NORM.INV(RAND(),$M$13,$M$14) -> -0.044083987
B1016: 44424 | C1016: 2426.4 | D1016: =(C1016-C1017)/C1017 -> 0.0091079226 | E1016: -0.028925064 | G1016: =_xlfn.NORM.INV(RAND(),$M$13,$M$14) -> 0.013192349
B1017: 44421 | C1017: 2404.5 | D1017: =(C1017-C1018)/C1018 -> 0.0050996949 | E1017: -0.028899322 | G1017: =_xlfn.NORM.INV(RAND(),$M$13,$M$14) -> -0.00048452106
B1018: 44420 | C1018: 2392.3 | D1018: =(C1018-C1019)/C1019 -> 0.00077391286 | E1018: -0.028803795 | G1018: =_xlfn.NORM.INV(RAND(),$M$13,$M$14) -> 0.0064230292
B1019: 44419 | C1019: 2390.45 | D1019: =(C1019-C1020)/C1020 -> 0.0036317071 | E1019: -0.02879319 | G1019: =_xlfn.NORM.INV(RAND(),$M$13,$M$14) -> -0.016215301
B1020: 44418 | C1020: 2381.8 | D1020: =(C1020-C1021)/C1021 -> -0.0011323129 | E1020: -0.028756152 | G1020: =_xlfn.NORM.INV(RAND(),$M$13,$M$14) -> -0.0074469839
B1021: 44417 | C1021: 2384.5 | D1021: =(C1021-C1022)/C1022 -> 0.0054817626 | E1021: -0.028732394 | G1021: =_xlfn.NORM.INV(RAND(),$M$13,$M$14) -> -0.0032442405
B1022: 44414 | C1022: 2371.5 | D1022: =(C1022-C1023)/C1023 -> 0.005853162 | E1022: -0.028672346 | G1022: =_xlfn.NORM.INV(RAND(),$M$13,$M$14) -> 0.023129557
... B6362: 36528 | C6362: 230.76 | D6362: =(C6362-C6363)/C6363 -> #DIV/0! | E6362: 0.20011786 | G6362: =_xlfn.NORM.INV(RAND(),$M$13,$M$14) -> 0.017395279

Sheet dupont analysis
B3: ='Data Sheet'!B1 -> HINDUSTAN UNILEVER LTD
B4: =CONCATENATE("(",B3," |"," BSE Code :",'Data Sheet'!B4,")") -> (HINDUSTAN UNILEVER LTD | BSE Code :500696)
B5: =CONCATENATE(,"INR ",'Data Sheet'!B8) -> INR 2528.9
B6: 52 week (High - INR 3,022.9 & Low - 2,136.0)
B8: About The Company
B9: Hindustan Unilever Limited (HUL) is an Indian fast-moving consumer goods company, headquartered in Mumbai. Hindustan Unilever is in the FMCG business comprising primarily of Home Care, Beauty & Personal Care and Foods & Refreshment segments. The Company has manufacturing facilities across the country and sells primarily in India.
B13: Financial Summary
B52: Dupont Analysis - Return On equity & Return on Asset
B54: Return on Equtiy (ROE)
C55: =[3]HistoricalFS!F3 -> 43555 | D55: =[3]HistoricalFS!G3 -> 43921 | E55: =[3]HistoricalFS!H3 -> 44286 | F55: =[3]HistoricalFS!I3 -> 44651 | G55: =[3]HistoricalFS!J3 -> 45016 | H55: =[3]HistoricalFS!K3 -> 45382 | I55: =[3]HistoricalFS!L3 -> 45747
B56: Net Profit | C56: ='Data Sheet'!E30 -> 6054 | D56: ='Data Sheet'!F30 -> 6748 | E56: ='Data Sheet'!G30 -> 7995 | F56: ='Data Sheet'!H30 -> 8879 | G56: ='Data Sheet'!I30 -> 10120 | H56: ='Data Sheet'!J30 -> 10277 | I56: ='Data Sheet'!K30 -> 10649
B57: Average Shareholder Equity | C57: =(('Data Sheet'!E57+'Data Sheet'!E58)+('Data Sheet'!D57+'Data Sheet'!D58))/2 -> 7574 | D57: =(('Data Sheet'!F57+'Data Sheet'!F58)+('Data Sheet'!E57+'Data Sheet'!E58))/2 -> 8048 | E57: =(('Data Sheet'!G57+'Data Sheet'!G58)+('Data Sheet'!F57+'Data Sheet'!F58))/2 -> 27951.5 | F57: =(('Data Sheet'!H57+'Data Sheet'!H58)+('Data Sheet'!G57+'Data Sheet'!G58))/2 -> 48367.5 | G57: =(('Data Sheet'!I57+'Data Sheet'!I58)+('Data Sheet'!H57+'Data Sheet'!H58))/2 -> 49682.5 | H57: =(('Data Sheet'!J57+'Data Sheet'!J58)+('Data Sheet'!I57+'Data Sheet'!I58))/2 -> 50761 | I57: =(('Data Sheet'!K57+'Data Sheet'!K58)+('Data Sheet'!J57+'Data Sheet'!J58))/2 -> 50310
B58: Return on Equtiy (ROE) | C58: =C56/C57 -> 0.79931344 | D58: =D56/D57 -> 0.83846918 | E58: =E56/E57 -> 0.28603116 | F58: =F56/F57 -> 0.18357368 | G58: =G56/G57 -> 0.20369345 | H58: =H56/H57 -> 0.20245858 | I58: =I56/I57 -> 0.21166766
B60: ROE - Dupont Equation
C61: =C55 -> 43555 | D61: =D55 -> 43921 | E61: =E55 -> 44286 | F61: =F55 -> 44651 | G61: =G55 -> 45016 | H61: =H55 -> 45382 | I61: =I55 -> 45747
B62: Net Profit | C62: =C56 -> 6054 | D62: =D56 -> 6748 | E62: =E56 -> 7995 | F62: =F56 -> 8879 | G62: =G56 -> 10120 | H62: =H56 -> 10277 | I62: =I56 -> 10649
B63: Revenue | C63: ='Data Sheet'!E17 -> 39310 | D63: ='Data Sheet'!F17 -> 39783 | E63: ='Data Sheet'!G17 -> 47028 | F63: ='Data Sheet'!H17 -> 52446 | G63: ='Data Sheet'!I17 -> 60580 | H63: ='Data Sheet'!J17 -> 61896 | I63: ='Data Sheet'!K17 -> 63121
B64: Net Profit Margin (A) | C64: =C62/C63 -> 0.15400661 | D64: =D62/D63 -> 0.16962019 | E64: =E62/E63 -> 0.1700051 | F64: =F62/F63 -> 0.16929794 | G64: =G62/G63 -> 0.16705183 | H64: =H62/H63 -> 0.16603658 | I64: =I62/I63 -> 0.16870772
B66: Revenue | C66: =C63 -> 39310 | D66: =D63 -> 39783 | E66: =E63 -> 47028 | F66: =F63 -> 52446 | G66: =G63 -> 60580 | H66: =H63 -> 61896 | I66: =I63 -> 63121
B67: Average Total Asset | C67: =('Data Sheet'!E66+'Data Sheet'!D66)/2 -> 18245.5 | D67: =('Data Sheet'!F66+'Data Sheet'!E66)/2 -> 19391 | E67: =('Data Sheet'!G66+'Data Sheet'!F66)/2 -> 44446.5 | F67: =('Data Sheet'!H66+'Data Sheet'!G66)/2 -> 69623 | G67: =('Data Sheet'!I66+'Data Sheet'!H66)/2 -> 71791.5 | H67: =('Data Sheet'!J66+'Data Sheet'!I66)/2 -> 75783 | I67: =('Data Sheet'!K66+'Data Sheet'!J66)/2 -> 79176
B68: Asset Turnover Ratio(B) | C68: =C66/C67 -> 2.1545039 | D68: =D66/D67 -> 2.0516219 | E68: =E66/E67 -> 1.0580811 | F68: =F66/F67 -> 0.75328555 | G68: =G66/G67 -> 0.84383249 | H68: =H66/H67 -> 0.8167531 | I68: =I66/I67 -> 0.79722391
B70: Average Total Asset | C70: =C67 -> 18245.5 | D70: =D67 -> 19391 | E70: =E67 -> 44446.5 | F70: =F67 -> 69623 | G70: =G67 -> 71791.5 | H70: =H67 -> 75783 | I70: =I67 -> 79176
B71: Average Shareholder Equity | C71: =C57 -> 7574 | D71: =D57 -> 8048 | E71: =E57 -> 27951.5 | F71: =F57 -> 48367.5 | G71: =G57 -> 49682.5 | H71: =H57 -> 50761 | I71: =I57 -> 50310
B72: Equity Multiplier (C) | C72: =C70/C71 -> 2.4089649 | D72: =D70/D71 -> 2.4094185 | E72: =E70/E71 -> 1.5901293 | F72: =F70/F71 -> 1.4394583 | G72: =G70/G71 -> 1.4450058 | H72: =H70/H71 -> 1.4929375 | I72: =I70/I71 -> 1.5737627
B74: Return On Equity (A*B*C) | C74: =C64*C68*C72 -> 0.79931344 | D74: =D64*D68*D72 -> 0.83846918 | E74: =E64*E68*E72 -> 0.28603116 | F74: =F64*F68*F72 -> 0.18357368 | G74: =G64*G68*G72 -> 0.20369345 | H74: =H64*H68*H72 -> 0.20245858 | I74: =I72*I68*I64 -> 0.21166766
B76: Return on Asset (ROA) | P76: 1.5737627
C77: =C55 -> 43555 | D77: =D55 -> 43921 | E77: =E55 -> 44286 | F77: =F55 -> 44651 | G77: =G55 -> 45016 | H77: =H55 -> 45382 | I77: =I55 -> 45747
B78: Net Profit | C78: =C56 -> 6054 | D78: =D56 -> 6748 | E78: =E56 -> 7995 | F78: =F56 -> 8879 | G78: =G56 -> 10120 | H78: =H56 -> 10277 | I78: =I56 -> 10649
B79: Average Total Asset | C79: =C67 -> 18245.5 | D79: =D67 -> 19391 | E79: =E67 -> 44446.5 | F79: =F67 -> 69623 | G79: =G67 -> 71791.5 | H79: =H67 -> 75783 | I79: =I67 -> 79176
B80: Return on Equtiy (ROE) | C80: =C78/C79 -> 0.33180784 | D80: =D78/D79 -> 0.34799649 | E80: =E78/E79 -> 0.17987918 | F80: =F78/F79 -> 0.1275297 | G80: =G78/G79 -> 0.14096376 | H80: =H78/H79 -> 0.13561089 | I80: =I78/I79 -> 0.13449783
B82: ROA - Dupont Equation
C83: =C77 -> 43555 | D83: =D77 -> 43921 | E83: =E77 -> 44286 | F83: =F77 -> 44651 | G83: =G77 -> 45016 | H83: =H77 -> 45382 | I83: =I77 -> 45747
B84: Net Profit | C84: =C78 -> 6054 | D84: =D78 -> 6748 | E84: =E78 -> 7995 | F84: =F78 -> 8879 | G84: =G78 -> 10120 | H84: =H78 -> 10277 | I84: =I78 -> 10649
B85: Revenue | C85: =C63 -> 39310 | D85: =D63 -> 39783 | E85: =E63 -> 47028 | F85: =F63 -> 52446 | G85: =G63 -> 60580 | H85: =H63 -> 61896 | I85: =I63 -> 63121
B86: Net Profit Margin (A) | C86: =C84/C85 -> 0.15400661 | D86: =D84/D85 -> 0.16962019 | E86: =E84/E85 -> 0.1700051 | F86: =F84/F85 -> 0.16929794 | G86: =G84/G85 -> 0.16705183 | H86: =H84/H85 -> 0.16603658 | I86: =I84/I85 -> 0.16870772
P87: 0.16870772
B88: Revenue | C88: =C85 -> 39310 | D88: =D85 -> 39783 | E88: =E85 -> 47028 | F88: =F85 -> 52446 | G88: =G85 -> 60580 | H88: =H85 -> 61896 | I88: =I85 -> 63121
B89: Average Total Asset | C89: =C79 -> 18245.5 | D89: =D79 -> 19391 | E89: =E79 -> 44446.5 | F89: =F79 -> 69623 | G89: =G79 -> 71791.5 | H89: =H79 -> 75783 | I89: =I79 -> 79176
B90: Asset Turnover Ratio(B) | C90: =C88/C89 -> 2.1545039 | D90: =D88/D89 -> 2.0516219 | E90: =E88/E89 -> 1.0580811 | F90: =F88/F89 -> 0.75328555 | G90: =G88/G89 -> 0.84383249 | H90: =H88/H89 -> 0.8167531 | I90: =I88/I89 -> 0.79722391 | P90: 0.79722391
B92: Return On Asset (A*B) | C92: =C90*C86 -> 0.33180784 | D92: =D90*D86 -> 0.34799649 | E92: =E90*E86 -> 0.17987918 | F92: =F90*F86 -> 0.1275297 | G92: =G90*G86 -> 0.14096376 | H92: =H90*H86 -> 0.13561089 | I92: =I90*I86 -> 0.13449783
B106: Disclaimer : This report is made as part of educational assignment and is meant for educational purpose only. The author of the report is not liable for any losses due to actions taken basis this report. It is advisable to consult SEBI registered reasearch analyst before making any investments

Sheet Altman Z Score
B3: ='dupont analysis'!B3 -> HINDUSTAN UNILEVER LTD
B4: ='dupont analysis'!$B$4 -> (HINDUSTAN UNILEVER LTD | BSE Code :500696)
B5: ='dupont analysis'!$B$5 -> INR 2528.9
B6: ='dupont analysis'!$B$6 -> 52 week (High - INR 3,022.9 & Low - 2,136.0)
B8: Altman's Z Score Analysis
B9: Hindustan Unilever Limited (HUL) is an Indian fast-moving consumer goods company, headquartered in Mumbai. Hindustan Unilever is in the FMCG business comprising primarily of Home Care, Beauty & Personal Care and Foods & Refreshment segments. The Company has manufacturing facilities across the country and sells primarily in India.
B13: Financial Summary
B52: Altman's Z Score Calculation
B54: Working Capital / Total Assets
C55: =[3]HistoricalFS!F3 -> 43555 | D55: =[3]HistoricalFS!G3 -> 43921 | E55: =[3]HistoricalFS!H3 -> 44286 | F55: =[3]HistoricalFS!I3 -> 44651 | G55: =[3]HistoricalFS!J3 -> 45016 | H55: =[3]HistoricalFS!K3 -> 45382 | I55: =[3]HistoricalFS!L3 -> 45747
B56: Working Capital | C56: ='Data Sheet'!E65-'Data Sheet'!E60 -> 129 | D56: ='Data Sheet'!F65-'Data Sheet'!F60 -> 898 | E56: ='Data Sheet'!G65-'Data Sheet'!G60 -> -7223 | F56: ='Data Sheet'!H65-'Data Sheet'!H60 -> -6203 | G56: ='Data Sheet'!I65-'Data Sheet'!I60 -> -5169 | H56: ='Data Sheet'!J65-'Data Sheet'!J60 -> -6692 | I56: ='Data Sheet'!K65-'Data Sheet'!K60 -> -8104
B57: Total Assets | C57: ='Data Sheet'!E66 -> 18629 | D57: ='Data Sheet'!F66 -> 20153 | E57: ='Data Sheet'!G66 -> 68740 | F57: ='Data Sheet'!H66 -> 70506 | G57: ='Data Sheet'!I66 -> 73077 | H57: ='Data Sheet'!J66 -> 78489 | I57: ='Data Sheet'!K66 -> 79863
B58: Working Capital / Total Assets | C58: =C56/C57 -> 0.0069246873 | D58: =D56/D57 -> 0.044559123 | E58: =E56/E57 -> -0.1050771 | F58: =F56/F57 -> -0.087978328 | G58: =G56/G57 -> -0.07073361 | H58: =H56/H57 -> -0.085260355 | I58: =I56/I57 -> -0.10147377
B60: Retained Earnings / Total Assests
C61: =C55 -> 43555 | D61: =D55 -> 43921 | E61: =E55 -> 44286 | F61: =F55 -> 44651 | G61: =G55 -> 45016 | H61: =H55 -> 45382 | I61: =I55 -> 45747
B62: Retained Earnings | C62: =HistoricalFS!F47*HistoricalFS!F49*HistoricalFS!F55 -> 986 | D62: =HistoricalFS!G47*HistoricalFS!G49*HistoricalFS!G55 -> 932 | E62: =HistoricalFS!H47*HistoricalFS!H49*HistoricalFS!H55 -> 0 | F62: =HistoricalFS!I47*HistoricalFS!I49*HistoricalFS!I55 -> 683 | G62: =HistoricalFS!J47*HistoricalFS!J49*HistoricalFS!J55 -> 530 | H62: =HistoricalFS!K47*HistoricalFS!K49*HistoricalFS!K55 -> 0 | I62: =HistoricalFS!L47*HistoricalFS!L49*HistoricalFS!L55 -> 0
B63: Total Assets | C63: =C57 -> 18629 | D63: =D57 -> 20153 | E63: =E57 -> 68740 | F63: =F57 -> 70506 | G63: =G57 -> 73077 | H63: =H57 -> 78489 | I63: =I57 -> 79863
B64: Retained Earnings / Total Assests | C64: =C62/C63 -> 0.05292823 | D64: =D62/D63 -> 0.046246216 | E64: =E62/E63 -> 0 | F64: =F62/F63 -> 0.0096871188 | G64: =G62/G63 -> 0.0072526239 | H64: =H62/H63 -> 0 | I64: =I62/I63 -> 0
B66: EBIT / Total Assets
C67: =C55 -> 43555 | D67: =D55 -> 43921 | E67: =E55 -> 44286 | F67: =F55 -> 44651 | G67: =G55 -> 45016 | H67: =H55 -> 45382 | I67: =I55 -> 45747
B68: EBIT | C68: ='Profit & Loss'!E32 -> 8637 | D68: ='Profit & Loss'!F32 -> 9283 | E68: ='Profit & Loss'!G32 -> 10722 | F68: ='Profit & Loss'!H32 -> 11985 | G68: ='Profit & Loss'!I32 -> 13458 | H68: ='Profit & Loss'!J32 -> 14260 | I68: ='Profit & Loss'!K32 -> 14810
B69: Total Assets | C69: =C57 -> 18629 | D69: =D57 -> 20153 | E69: =E57 -> 68740 | F69: =F57 -> 70506 | G69: =G57 -> 73077 | H69: =H57 -> 78489 | I69: =I57 -> 79863
B70: EBIT / Total Assets | C70: =C68/C69 -> 0.46363197 | D70: =D68/D69 -> 0.46062621 | E70: =E68/E69 -> 0.15597905 | F70: =F68/F69 -> 0.16998553 | G70: =G68/G69 -> 0.18416191 | H70: =H68/H69 -> 0.18168151 | I70: =I68/I69 -> 0.18544257
B72: Market Cap / Long Term Liabilities
C73: =C55 -> 43555 | D73: =D55 -> 43921 | E73: =E55 -> 44286 | F73: =F55 -> 44651 | G73: =G55 -> 45016 | H73: =H55 -> 45382 | I73: =I55 -> 45747
B74: Market Cap | C74: =('Data Sheet'!E90*'Data Sheet'!E70)/10000000 -> 369471.75 | D74: =('Data Sheet'!F90*'Data Sheet'!F70)/10000000 -> 497557.31 | E74: =('Data Sheet'!G90*'Data Sheet'!G70)/10000000 -> 571297.42 | F74: =('Data Sheet'!H90*'Data Sheet'!H70)/10000000 -> 481349.01 | G74: =('Data Sheet'!I90*'Data Sheet'!I70)/10000000 -> 601577.6 | H74: =('Data Sheet'!J90*'Data Sheet'!J70)/10000000 -> 532029.7 | I74: =('Data Sheet'!K90*'Data Sheet'!K70)/10000000 -> 530737.42
B75: Long Term Liabilities | C75: ='Data Sheet'!E59 -> 99 | D75: 0 | E75: 0 | F75: ='Data Sheet'!H59 -> 1043 | G75: ='Data Sheet'!I59 -> 1219 | H75: ='Data Sheet'!J59 -> 1484 | I75: ='Data Sheet'!K59 -> 1648
B76: Market Cap / Long Term Liabilities | C76: =C74/C75 -> 3732.0379 | D76: =D74 -> 497557.31 | E76: =E74 -> 571297.42 | F76: =F74/F75 -> 461.50433 | G76: =G74/G75 -> 493.5009 | H76: =H74/H75 -> 358.51058 | I76: =I74/I75 -> 322.04941
B78: Sales / Total Assets
C79: =C55 -> 43555 | D79: =D55 -> 43921 | E79: =E55 -> 44286 | F79: =F55 -> 44651 | G79: =G55 -> 45016 | H79: =H55 -> 45382 | I79: =I55 -> 45747
B80: Sales | C80: ='Data Sheet'!E30 -> 6054 | D80: ='Data Sheet'!F30 -> 6748 | E80: ='Data Sheet'!G30 -> 7995 | F80: ='Data Sheet'!H30 -> 8879 | G80: ='Data Sheet'!I30 -> 10120 | H80: ='Data Sheet'!J30 -> 10277 | I80: ='Data Sheet'!K17 -> 63121
B81: Total Assets | C81: =C57 -> 18629 | D81: =D57 -> 20153 | E81: =E57 -> 68740 | F81: =F57 -> 70506 | G81: =G57 -> 73077 | H81: =H57 -> 78489 | I81: =I57 -> 79863
B82: Sales / Total Assets | C82: =C80/C81 -> 0.32497719 | D82: =D80/D81 -> 0.33483849 | E82: =E80/E81 -> 0.11630783 | F82: =F80/F81 -> 0.12593254 | G82: =G80/G81 -> 0.13848406 | H82: =H80/H81 -> 0.13093555 | I82: =I80/I81 -> 0.790366
B84: Altman's Z score
C85: =C61 -> 43555 | D85: =D61 -> 43921 | E85: =E61 -> 44286 | F85: =F61 -> 44651 | G85: =G61 -> 45016 | H85: =H61 -> 45382 | I85: =I61 -> 45747
B86: Final Score | C86: =(C58*1.2)+(C64*1.4)+(C70*3.3)+(C76*0.6)+(C82*1) -> 2241.1601 | D86: =(D58*1.2)+(D64*1.4)+(D70*3.3)+(D76*0.6)+(D82*1) -> 298536.36 | E86: =(E58*1.2)+(E64*1.4)+(E70*3.3)+(E76*0.6)+(E82*1) -> 342778.95 | F86: =(F58*1.2)+(F64*1.4)+(F70*3.3)+(F76*0.6)+(F82*1) -> 277.49747 | G86: =(G58*1.2)+(G64*1.4)+(G70*3.3)+(G76*0.6)+(G82*1) -> 296.77203 | H86: =(H58*1.2)+(H64*1.4)+(H70*3.3)+(H76*0.6)+(H82*1) -> 215.73452 | I86: =(I58*1.2)+(I64*1.4)+(I70*3.3)+(I76*0.6)+(I82*1) -> 194.5102
B87: Financial Stability | C87: =IF(C86<1.8,"High Risk",IF(C86>3,"Strong","Grey zone")) -> Strong | D87: =IF(D86<1.8,"High Risk",IF(D86>3,"Strong","Grey zone")) -> Strong | E87: =IF(E86<1.8,"High Risk",IF(E86>3,"Strong","Grey zone")) -> Strong | F87: =IF(F86<1.8,"High Risk",IF(F86>3,"Strong","Grey zone")) -> Strong | G87: =IF(G86<1.8,"High Risk",IF(G86>3,"Strong","Grey zone")) -> Strong | H87: =IF(H86<1.8,"High Risk",IF(H86>3,"Strong","Grey zone")) -> Strong | I87: =IF(I86<1.8,"High Risk",IF(I86>3,"Strong","Grey zone")) -> Strong
B90: Disclaimer : This report is made as part of educational assignment and is meant for educational purpose only. The author of the report is not liable for any losses due to actions taken basis this report. It is advisable to consult SEBI registered reasearch analyst before making any investments

Sheet Summary
B3: ='Data Sheet'!B1 -> HINDUSTAN UNILEVER LTD
B4: =CONCATENATE("(",B3," |"," BSE Code :",'Data Sheet'!B4,")") -> (HINDUSTAN UNILEVER LTD | BSE Code :500696)
B5: =CONCATENATE(,"INR ",'Data Sheet'!B8) -> INR 2528.9
B6: 52 week (High - INR 3,022.9 & Low - 2,136.0)
B10: =CONCATENATE("Valuation Summary - ","HINDUSTAN UNILEVER LTD") -> Valuation Summary - HINDUSTAN UNILEVER LTD
B11: The valuation of Hindustan Unilever Ltd. has been conducted using a combination of Discounted Cash Flow (DCF) and Relative Valuation methodologies. The analysis integrates sector-aligned assumptions, regulatory benchmarks, and performance trends observed in the FMCG space.
B15: CorenAssumption:
B17: 1. Terminal Growth Rate:5.8%, aligned with long term econonic growth expectations and FMCG Sector maturity.
B18: 2. Tax Rate: A standard corporate of 30% has been applied to operating metrics and used consistently throughout the valuation calculations, reflecting current Indian Tax Policy.
B20: 3. Cost of Equity: The calculation includes the following key components
B21: • Risk-free Rate: Based on 10- Year government bond yield which is 7.36%
B22: • Levered Beta: 0.75, indicative of Unilever relatively low market volatility compread to broader market.
B23: • Equity Risk Premium: The equity premium has been determined using the market data and reflects the additional return investors expect for taking on equity risk over government bonds which is (Total Market Return - Risk-free Rate) 7.96%
B26: Valuation Outcomes:
B28: 1. DCF Valuation Output
B29: • Enterprise Value: INR 543931.4 Crores
B30: • Equity Value Per Share: INR 2315
... B59: Interpretation: Hindustan UniLever's Z-Score has slightly below compared to last year and it is maintained safe zone across all years.

Sheet  Conclusion
B3: ='Data Sheet'!B1 -> HINDUSTAN UNILEVER LTD
B4: =CONCATENATE("(",P5," |"," BSE Code :",'Data Sheet'!B4,")") -> (HINDUNILVR | BSE Code :500696)
B5: =CONCATENATE(,"INR ",'Data Sheet'!B8) -> INR 2528.9 | P5: HINDUNILVR
B6: 52 week (High - INR 3,022.9 & Low - 2,136.0)
B10: conclusion
B12: The DCF Valuation highlights the underlying strength of Nestlé India's cash flows, driven by its expansive product portfolio, dominant market share in key segments, and strong brand equity. While the base-case scenario reflects conservative intrinsic value, the sensitivity analysis shows how minor changes in growth or cost of capital can significantly impact valuation—a useful insight for risk-aware decision-making
B18: Relative valuation multiples such as EV/EBITDA and P/E indicate that Hindustan Unilever trades at a premium compared to peers—a reflection of its consistent profitability, leadership in the packaged food industry, and defensive qualities in volatile markets. This premium appears justified given the company's brand strength, innovation focus, and dividend consistency
B21: The Altman Z-Score, used to assess financial distress risk, places Hindustan Unilever India well into the 'safe zone', reinforcing its strong capital structure, profitability, and low leverage. This underscores the company's resilience and makes it attractive for long-term, risk-averse investors.
B25: The Value at Risk (VaR) analysis offers a quantitative view of downside potential, helping to contextualize market volatility relative to expected return. For a large-cap FMCG firm like Hindustan Unilever limited VaR impact further supports its status as a relatively stable equity investment
B32: Disclaimer: This report has been prepared as part of an academic exercise and is intended solely for learning and educational purposes. The financial model, valuation analysis, and all associated commentary are based on publicly available data, reasonable assumptions, and standard financial methodologies, and are intended to demonstrate analytical techniques in a learning context
B37: This report does not constitute investment advice, stock recommendations, or any form of financial guidance. Readers and users of this report are advised to conduct their own research and consult with a qualified financial advisor before making any investment decisions. The author of this report is not liable for the accuracy, completeness, or future applicability of the information presented herein. It is advisable to consult a SEBI-registered research analyst before making any investments
B42: Sources
B44: • Screener.in
B45: • The Valuation School
B46: • Yahoo Finance
... B50: • Tikertape

Sheet Sheet7

Sheet Peer
B3: Name | C3: Sub-Sector | D3: ?Market Cap | E3: PE Ratio | F3: Enterprise Value | G3: Beta | H3: Total Equity | I3: Debt to Equity | J3: Total Debt
B4: Hindustan Unilever Ltd | C4: FMCG - Household Products | D4: 621114.45 | E4: 58.33 | F4: 611664.45 | G4: 0.74 | H4: 49609 | I4: 0.03 | J4: 1648
B5: ITC Ltd | C5: FMCG - Tobacco | D5: 517413.81 | E5: 14.89 | F5: 497766.38 | G5: 0.83 | H5: 70397.94 | I5: 0 | J5: 284.54
B6: Nestle India Ltd | C6: FMCG - Foods | D6: 234772.27 | E6: 73.19 | F6: 235843.47 | G6: 0.84 | H6: 4010.21 | I6: 0.29 | J6: 1166.85
B7: Britannia Industries Ltd | C7: FMCG - Foods | D7: 149314.26 | E7: 68.53 | F7: 149162.25 | G7: 0.76 | H7: 4381.32 | I7: 0.28 | J7: 1246.51
B8: Godrej Consumer Products Ltd | C8: FMCG - Personal Products | D8: 128518.6 | E8: 69.38 | F8: 128937.3 | G8: 0.84 | H8: 12003.92 | I8: 0.33 | J8: 4004.49
B9: Dabur India Ltd | C9: FMCG - Personal Products | D9: 97109.54 | E9: 54.94 | F9: 95803.92 | G9: 0.54 | H9: 11210.26 | I9: 0.08 | J9: 950.37
B10: Marico Ltd | C10: FMCG - Personal Products | D10: 95337.54 | E10: 58.53 | F10: 94030.54 | G10: 0.51 | H10: 4266 | I10: 0.13 | J10: 554
B11: Colgate-Palmolive (India) Ltd | C11: FMCG - Personal Products | D11: 65477.82 | E11: 45.57 | F11: 64443.53 | G11: 0.93 | H11: 1664.47 | I11: 0.04 | J11: 60.84
B12: Patanjali Foods Ltd | C12: Packaged Foods & Meats | D12: 65342.22 | E12: 50.24 | F12: 65695.93 | G12: 1.14 | H12: 11370.89 | I12: 0.07 | J12: 787.67
B13: Godfrey Phillips India Ltd | C13: FMCG - Tobacco | D13: 56085.84 | E13: 52.32 | F13: 56060.7 | G13: 0.44 | H13: 5253.99 | I13: 0.03 | J13: 177.48
B14: Procter & Gamble Hygiene and Health Care Ltd | C14: FMCG - Personal Products | D14: 43026.71 | E14: 67.59 | F14: 42548.33 | G14: 0.48 | H14: 736.99 | I14: 0 | J14: 2.32
B15: AWL Agri Business Ltd | C15: FMCG - Foods | D15: 33191.63 | E15: 27.08 | F15: 32553.66 | G15: 0.7 | H15: 9423.92 | I15: 0.21 | J15: 1937.32
... B18: Hatsun Agro Product Ltd | C18: FMCG - Foods | D18: 20233.34 | E18: 72.57 | F18: 22732.78 | G18: 0.75 | H18: 1717.56 | I18: 1.5 | J18: 2570.45
B19: 16
B20: Zydus Wellness Ltd | C20: FMCG - Foods | D20: 15824.68 | E20: 45.62 | F20: 15903.38 | G20: 0.5 | H20: 5671.6 | I20: 0.03 | J20: 188.3
B21: 17
B22: LT Foods Ltd | C22: Packaged Foods & Meats | D22: 15744.45 | E22: 26.01 | F22: 16666.65 | G22: 0.92 | H22: 3426.69 | I22: 0.27 | J22: 917.48
B23: 18
B24: Jyothy Labs Ltd | C24: FMCG - Household Products | D24: 11960.18 | E24: 32.29 | F24: 11422.64 | G24: 0.73 | H24: 2049.51 | I24: 0.03 | J24: 61.28
B25: 19
B26: Avanti Feeds Ltd | C26: Packaged Foods & Meats | D26: 10304.94 | E26: 19.49 | F26: 8755 | G26: 0.41 | H26: 3174.84 | I26: 0 | J26: 15.14
B27: 20
B28: KRBL Ltd | C28: Packaged Foods & Meats | D28: 10075.73 | E28: 21.17 | F28: 9670.18 | G28: 0.56 | H28: 5241.2 | I28: 0.08 | J28: 406.68
B29: 21
B30: Dodla Dairy Ltd | C30: FMCG - Foods | D30: 8660.06 | E30: 33.32 | F30: 7970.14 | G30: 0.78 | H30: 1405.95 | I30: 0.03 | J30: 42.43
B31: 22
B32: Mrs. Bectors Food Specialities Ltd | C32: FMCG - Foods | D32: 8649.77 | E32: 60.39 | F32: 8545.65 | G32: 0.87 | H32: 1165.78 | I32: 0.16 | J32: 184.05
B33: 23
B34: Hindustan Foods Ltd | C34: FMCG - Foods | D34: 6397.05 | E34: 58.35 | F34: 7204.85 | G34: 1.72 | H34: 891.93 | I34: 1 | J34: 891.42
B35: 24
B36: Cupid Ltd | C36: FMCG - Personal Products | D36: 5439.02 | E36: 133.02 | F36: 5302.58 | G36: 0.07 | H36: 342.2 | I36: 0.06 | J36: 18.99
B37: 25
B38: Gokul Agro Resources Ltd | C38: Packaged Foods & Meats | D38: 5014.26 | E38: 20.42 | F38: 5152.37 | G38: 0.76 | H38: 1035.95 | I38: 0.53 | J38: 543.92
B39: 26
B40: VST Industries Ltd | C40: FMCG - Tobacco | D40: 4555.64 | E40: 15.69 | F40: 4205.64 | G40: 0.78 | H40: 1322.69 | I40: 0 | J40: 0
B41: 27
B42: Heritage Foods Ltd | C42: FMCG - Foods | D42: 4490.4 | E42: 23.85 | F42: 4409.21 | G42: 1.13 | H42: 971.97 | I42: 0.18 | J42: 174.7
B43: 28
B44: Vadilal Industries Ltd | C44: FMCG - Foods | D44: 4061.48 | E44: 27.02 | F44: 4222.85 | G44: 0.01 | H44: 695.62 | I44: 0.31 | J44: 218.29
B45: 29
B46: Parag Milk Foods Ltd | C46: FMCG - Foods | D46: 3152.49 | E46: 26.54 | F46: 3769.62 | G46: 1.18 | H46: 912.11 | I46: 0.71 | J46: 644.7
B47: 30
B48: Bajaj Consumer Care Ltd | C48: FMCG - Personal Products | D48: 3042.71 | E48: 24.29 | F48: 2593.95 | G48: 0.84 | H48: 747.9 | I48: 0.01 | J48: 4.17
B49: 31
B50: Sundrop Brands Ltd | C50: Packaged Foods & Meats | D50: 3026.87 | E50: -27.54 | F50: 2992.86 | G50: 0.57 | H50: 1438.38 | I50: 0.01 | J50: 14.31
B51: 32
B52: RPSG Ventures Ltd | C52: Packaged Foods & Meats | D52: 2848.74 | E52: -58.09 | F52: 9913.35 | G52: 1.46 | H52: 4588.05 | I52: 1.34 | J52: 6152
B53: 33
B54: ADF Foods Ltd | C54: Packaged Foods & Meats | D54: 2569.93 | E54: 37.12 | F54: 2502.43 | G54: 0.86 | H54: 492.66 | I54: 0.12 | J54: 59.23
B55: 34
B56: Tasty Bite Eatables Ltd | C56: Packaged Foods & Meats | D56: 2412.55 | E56: 94.13 | F56: 2469.63 | G56: 0.99 | H56: 311.32 | I56: 0.23 | J56: 72.47
B57: 35
B58: Prataap Snacks Ltd | C58: Packaged Foods & Meats | D58: 2398.25 | E58: -69.94 | F58: 2460.59 | G58: 0.39 | H58: 690.25 | I58: 0.11 | J58: 76.42
B59: 36
B60: Venky's (India) Ltd | C60: Packaged Foods & Meats | D60: 2135.92 | E60: 18.31 | F60: 1995.36 | G60: 1.2 | H60: 1475.58 | I60: 0.11 | J60: 169.66
B61: 37
B62: Polo Queen Industrial and Fintech Ltd | C62: FMCG - Household Products | D62: 1740.86 | E62: 656.93 | F62: 1754.82 | G62: -0.53 | H62: 188.47 | I62: 0.08 | J62: 14.65
B63: 38
B64: Lotus Chocolate Company Ltd | C64: FMCG - Foods | D64: 1505.23 | E64: 87.36 | F64: 1501.51 | G64: 1.7 | H64: 36.83 | I64: 0.01 | J64: 0.47
B65: 39
B66: Dcm Shriram Industries Ltd | C66: Packaged Foods & Meats | D66: 1471.39 | E66: 14.5 | F66: 1905.68 | G66: 1.24 | H66: 898.95 | I66: 0.59 | J66: 533.99
B67: 40
B68: Chaman Lal Setia Exports Ltd | C68: Packaged Foods & Meats | D68: 1421.66 | E68: 13.82 | F68: 1487.21 | G68: 0.77 | H68: 733.28 | I68: 0.17 | J68: 123.16

Sheet nifty 50 data
B4: returns on market
B6: year | C6: return
B7: 2000 | C7: -0.1465 | F7: average return | G7: =AVERAGE(C7:C31) -> 0.151836 | I7: Year | J7: Return (%) | K7: Market Sentiment
B8: 2001 | C8: -0.1618 | F8: Dividend yeild | G8: 1.35% 1 | I8: 2000 | J8: -0.14 | K8: Dot-com crash impact | M8: Average return | N8: =AVERAGE(J8:J32) -> 0.15316
B9: 2002 | C9: 0.0325 | F9: Total returns | G9: =SUM(G7:G8) -> 0.151836 | I9: 2001 | J9: -0.174 | K9: Global slowdown, 9/11 aftermath | M9: Dividend Yeild | N9: 1.36% 1
B10: 2003 | C10: 0.719 | I10: 2002 | J10: 0.032 | K10: Mild recovery begins | M10: Total Return | N10: =SUM(N8:N9) -> 0.15316
B11: 2004 | C11: 0.1068 | I11: 2003 | J11: 0.719 | K11: Strong bull run starts
B12: 2005 | C12: 0.3634 | I12: 2004 | J12: 0.106 | K12: Continued growth
B13: 2006 | C13: 0.3983 | I13: 2005 | J13: 0.363 | K13: Economic optimism
B14: 2007 | C14: 0.5477 | I14: 2006 | J14: 0.398 | K14: Robust corporate earnings
B15: 2008 | C15: -0.5179 | I15: 2007 | J15: 0.547 | K15: Peak of pre-crisis rally
B16: 2009 | C16: 0.7576 | I16: 2008 | J16: -0.518 | K16: Global financial crisis
B17: 2010 | C17: 0.1795 | I17: 2009 | J17: 0.757 | K17: Recovery bounce
B18: 2011 | C18: -0.2462 | I18: 2010 | J18: 0.179 | K18: Stabilization phase
B19: 2012 | C19: 0.277 | I19: 2011 | J19: -0.247 | K19: Eurozone crisis
B20: 2013 | C20: 0.0676 | I20: 2012 | J20: 0.276 | K20: Policy reforms boost
B21: 2014 | C21: 0.3139 | I21: 2013 | J21: 0.067 | K21: Volatile but positive
B22: 2015 | C22: -0.0406 | I22: 2014 | J22: 0.313 | K22: Modi-led rally
... B31: 2024 | C31: 0.0497 | I31: 2023 | J31: 0.2 | K31: Resilient earnings
I32: 2024 | J32: 0.092 | K32: Moderation phase
I33: 2025 | J33: -3.4%* | K33: Partial data (YTD)

Sheet List of Stocks
A2: COMPANY_NAME | B2: BSE | C2: NSE | D2: Industry
A3: 20 MICRONS LTD | B3: 533022 | C3: 20MICRONS | D3: Mining
A4: 21ST CENTURY MANAGEMENT SERVICES LTD | B4: 526921 | C4: 21STCENMGM | D4: Other Financial Services
A5: 3I INFOTECH LTD | B5: 532628 | C5: 3IINFOTECH | D5: IT Consulting & Software
A6: 3M (INDIA) LTD | B6: 523395 | C6: 3M(INDIA) | D6: Diversified
A7: 3M INDIA LTD | B7: 523395 | C7: 3MINDIA | D7: Diversified
A8: 3P LAND HOLDINGS LTD | B8: 516092 | C8: 3PLAND | D8: Paper & Paper Products
A9: 5PAISA CAPITAL LTD | B9: 540776 | C9: 5PAISA | D9: Other Financial Services
A10: 63 MOONS TECHNOLOGIES LTD | B10: 526881 | C10: 63MOONS | D10: IT Consulting & Software
A11: 7NR RETAIL LTD | B11: 540615 | C11: Not Listed | D11: Specialty Retail
A12: 7SEAS ENTERTAINMENT LTD | B12: 540874 | C12: Not Listed | D12: Movies & Entertainment
A13: 8K MILES SOFTWARE SERVICES LTD | B13: 512161 | C13: 8KMILES | D13: Internet Software & Services
A14: A & M FEBCON LTD | B14: 540697 | C14: Not Listed | D14: Industrial Machinery
A15: A AND M JUMBO BAGS LTD | B15: Not Listed | C15: AMJUMBO | D15: SME
A16: A INFRASTRUCTURE LTD | B16: 539620 | C16: Not Listed | D16: Cement & Cement Products
A17: A K SPINTEX LTD | B17: 539300 | C17: Not Listed | D17: Textiles
A18: A K CAPITAL SERVICES LTD | B18: 530499 | C18: Not Listed | D18: Finance (including NBFCs)
A19: A.F. Enterprises Ltd | B19: 538351 | C19: AFEL | D19: Investment Companies
A20: A-1 ACID LTD | B20: 542012 | C20: Not Listed | D20: Comm.Trading & Distribution
A21: A2Z INFRA ENGINEERING LTD | B21: 533292 | C21: A2ZINFRA | D21: Utilities:Non-Elec.
A22: AADHAAR VENTURES (INDIA) LTD | B22: 531611 | C22: Not Listed | D22: Finance (including NBFCs)
A23: AADHAAR VENTURES INDIA LTD | B23: 531611 | C23: Not Listed | D23: Finance (including NBFCs)
A24: AAKASH EXPLORATION SERVICES LTD | B24: Not Listed | C24: AAKASH | D24: SME
A25: AANANDA LAKSHMI SPINNING MILLS LTD | B25: 539096 | C25: Not Listed | D25: Textiles
A26: AANCHAL ISPAT LTD | B26: 538812 | C26: Not Listed | D26: Iron & Steel/Interm.Products
A27: AAR COMMERCIAL COMPANY LTD | B27: 539632 | C27: Not Listed | D27: Distributors
A28: Aar Shyam India Investment Company Ltd | B28: 542377 | C28: AARSHYAM | D28: Finance (including NBFCs)
A29: AAREY DRUGS & PHARMACEUTICALS LTD | B29: 524412 | C29: Not Listed | D29: Pharmaceuticals
A30: AARON INDUSTRIES LTD | B30: Not Listed | C30: AARON | D30: SME
A31: Aartech Solonics Ltd | B31: 542580 | C31: AARTECH | D31: Heavy Electrical Equipment
A32: AARTI DRUGS LTD | B32: 524348 | C32: AARTIDRUGS | D32: Pharmaceuticals
A33: AARTI INDUSTRIES LTD | B33: 524208 | C33: AARTIIND | D33: Commodity Chemicals
A34: AARV INFRATEL LTD | B34: 526488 | C34: Not Listed | D34: Textiles
A35: AARVEE DENIMS & EXPORTS LTD | B35: 514274 | C35: AARVEEDEN | D35: Textiles
A36: AARVI ENCON LTD | B36: Not Listed | C36: AARVI | D36: SME
A37: AASHEE INFOTECH LTD | B37: 519319 | C37: Not Listed | D37: Internet Software & Services
A38: AASWA TRADING & EXPORTS LTD | B38: 512038 | C38: Not Listed | D38: Comm.Trading & Distribution
A39: AAVAS FINANCIERS LTD | B39: 541988 | C39: AAVAS | D39: Housing Finance
A40: AAYUSH FOOD AND HERBS LTD | B40: 539528 | C40: Not Listed | D40: Packaged Foods
A41: ABAN OFFSHORE LTD | B41: 523204 | C41: ABAN | D41: Exploration & Production
A42: ABANS ENTERPRISES LTD | B42: 512165 | C42: Not Listed | D42: Comm.Trading & Distribution
A43: ABB INDIA LTD | B43: 500002 | C43: ABB | D43: Heavy Electrical Equipment
A44: ABBOTT (INDIA) LTD | B44: 500488 | C44: ABBOT(INDIA) | D44: Pharmaceuticals
A45: ABBOTT INDIA LTD | B45: 500488 | C45: ABBOTINDIA | D45: Pharmaceuticals
A46: ABC (INDIA) LTD | B46: 520123 | C46: Not Listed | D46: Surface Transportation
A47: ABC GAS INTERNATIONAL LTD | B47: 513119 | C47: Not Listed | D47: Copper
A48: ABC INDIA LTD | B48: 520123 | C48: Not Listed | D48: Surface Transportation
... A56: ABIRAMI FINANCIAL SERVICES INDIA LTD | B56: 511756 | C56: Not Listed | D56: Finance (including NBFCs)
A57: ABM INTERNATIONAL LTD | B57: Not Listed | C57: ABMINTLTD | D57: Others
A58: ABM KNOWLEDGEWARE LTD | B58: 531161 | C58: Not Listed | D58: IT Software Products
A59: ACC LTD | B59: 500410 | C59: ACC | D59: Cement & Cement Products
A60: ACCEL LTD | B60: 517494 | C60: Not Listed | D60: Storage Media & Peripherals
A61: ACCELYA KALE SOLUTIONS LTD | B61: 532268 | C61: ACCELYA | D61: IT Consulting & Software
A62: ACCORD SYNERGY LTD | B62: Not Listed | C62: ACCORD | D62: SME
A63: ACCURACY SHIPPING LTD | B63: Not Listed | C63: ACCURACY | D63: SME
A64: ACE EDUTREND LTD | B64: 530093 | C64: Not Listed | D64: Education
A65: ACE INTEGRATED SOLUTIONS LTD | B65: Not Listed | C65: ACEINTEG | D65: SME
A66: ACE MEN ENGG WORKS LTD | B66: 539661 | C66: Not Listed | D66: Distributors
A67: ACE SOFTWARE EXPORTS LTD | B67: 531525 | C67: Not Listed | D67: IT Software Products
A68: Achal Investments Ltd | B68: 538570 | C68: ACHAL | D68: Other Financial Services
A69: ACI INFOCOM LTD | B69: 517356 | C69: Not Listed | D69: Storage Media & Peripherals
A70: ACKNIT INDUSTRIES LTD | B70: 530043 | C70: Not Listed | D70: Other Apparels & Accessories
A71: ACME RESOURCES LTD | B71: 539391 | C71: Not Listed | D71: Finance (including NBFCs)
A72: ACROW INDIA LTD. | B72: 513149 | C72: ACROW | D72: Iron &amp; Steel Products
A73: ACRYSIL LTD | B73: 524091 | C73: Not Listed | D73: Plastic Products
A74: ACTION CONSTRUCTION EQUIPMENT LTD | B74: 532762 | C74: ACE | D74: Transport Related Services
A75: ACTION FINANCIAL SERVICES (INDIA) LTD | B75: 511706 | C75: Not Listed | D75: Other Financial Services
A76: ACTION FINANCIAL SERVICES INDIA LTD | B76: 511706 | C76: Not Listed | D76: Other Financial Services
A77: ACTIVE CLOTHING CO LTD | B77: 541144 | C77: Not Listed | D77: Other Apparels & Accessories
... A135: AGRI-TECH INDIA LTD | B135: 537292 | C135: AGRITECH | D135: Other Agricultural Products
A136: AGRO PHOS (INDIA) LTD | B136: Not Listed | C136: AGROPHOS | D136: SME
A137: AGRO PHOS INDIA LTD | B137: Not Listed | C137: AGROPHOS | D137: SME
A138: AGRO TECH FOODS LTD | B138: 500215 | C138: ATFL | D138: Other Agricultural Products
A139: AHIMSA INDUSTRIES LTD | B139: Not Listed | C139: AHIMSA | D139: SME
A140: AHLADA ENGINEERS LTD | B140: Not Listed | C140: AHLADA | D140: SME
A141: AHLUWALIA CONTRACTS (INDIA) LTD | B141: 532811 | C141: AHLUCONT | D141: Realty
A142: AHLUWALIA CONTRACTS INDIA LTD | B142: 532811 | C142: AHLUCONT | D142: Realty
A143: AHMEDABAD STEELCRAFT LTD | B143: 522273 | C143: Not Listed | D143: Iron & Steel/Interm.Products
A144: AI CHAMPDANY INDUSTRIES LTD | B144: 532806 | C144: Not Listed | D144: Jute & Jute Products
A145: AIA ENGINEERING LTD | B145: 532683 | C145: AIAENG | D145: Other Industrial Goods
A146: AIMCO PESTICIDES LTD | B146: 524288 | C146: Not Listed | D146: Agrochemicals
A147: AIRAN LTD | B147: Not Listed | C147: AIRAN | D147: SME
A148: AIRO LAM LTD | B148: Not Listed | C148: AIROLAM | D148: SME
A149: AISHWARYA TELECOM LTD | B149: 532975 | C149: Not Listed | D149: Telecom Equipment
A150: AJANTA PHARMA LTD | B150: 532331 | C150: AJANTPHARM | D150: Pharmaceuticals
A151: AJANTA SOYA LTD | B151: 519216 | C151: Not Listed | D151: Edible Oils
A152: AJCON GLOBAL SERVICES LTD | B152: 511692 | C152: Not Listed | D152: Other Financial Services
A153: AJEL LTD | B153: 530713 | C153: Not Listed | D153: IT Consulting & Software
A154: AJMERA REALTY & INFRA (INDIA) LTD | B154: 513349 | C154: AJMERA | D154: Realty
A155: AJMERA REALTY & INFRA INDIA LTD | B155: 513349 | C155: AJMERA | D155: Realty
A156: AJOONI BIOTECH LTD | B156: Not Listed | C156: AJOONI | D156: SME
A157: AJWA FUN WORLD & RESORT LTD | B157: 526628 | C157: Not Listed | D157: Other Leisure Facilities
A158: AKAR AUTO INDUSTRIES LTD | B158: 530621 | C158: Not Listed | D158: Industrial Machinery
A159: AKASH INFRA PROJECTS LTD | B159: Not Listed | C159: AKASH | D159: SME
A160: AKASHDEEP METAL INDUSTRIES LTD | B160: 538778 | C160: Not Listed | D160: Finance (including NBFCs)
A161: AKG EXIM LTD | B161: Not Listed | C161: AKG | D161: SME
A162: AKI (INDIA) LTD | B162: 542020 | C162: Not Listed | D162: Other Apparels & Accessories
A163: AKI INDIA LTD | B163: 542020 | C163: Not Listed | D163: Other Apparels & Accessories
A164: AKM LACE AND EMBROTEX LTD | B164: 540718 | C164: Not Listed | D164: Textiles
A165: AKME STAR HOUSING FINANCE LTD | B165: 539017 | C165: Not Listed | D165: Housing Finance
...

Sheet Raw FS
B2: Particular | C2: ='Data Sheet'!B16 -> 42460 | D2: ='Data Sheet'!C16 -> 42825 | E2: ='Data Sheet'!D16 -> 43190 | F2: ='Data Sheet'!E16 -> 43555 | G2: ='Data Sheet'!F16 -> 43921 | H2: ='Data Sheet'!G16 -> 44286 | I2: ='Data Sheet'!H16 -> 44651 | J2: ='Data Sheet'!I16 -> 45016 | ... L2: ='Data Sheet'!K16 -> 45747
B4: Equity Capital | C4: ='BAlance sheet HUL'!C4 -> 216 | D4: 562 | E4: 562 | F4: 624 | G4: 624 | H4: 624 | I4: 648 | J4: 648 | K4: 648 | L4: 648
B5: Reserves | C5: ='BAlance sheet HUL'!C5 -> 6357 | D5: 638 | E5: 959 | F5: 3218 | G5: 4045 | H5: 4963 | I5: 10432 | J5: 11536 | K5: 13030 | L5: 15430
B6: Borrowings -
B7: Long term Borrowings | C7: ='BAlance sheet HUL'!C7 -> 0 | D7: 0 | E7: 908 | F7: 981 | G7: 246 | H7: 126 | I7: 0 | J7: 0 | K7: 0 | L7: 0
B8: Short term Borrowings | C8: ='BAlance sheet HUL'!C8 -> 177 | D8: 0 | E8: 129 | F8: 139 | G8: 7 | H8: 304 | I8: 4 | J8: 0 | K8: 0 | L8: 0
B9: Lease Liabilities | C9: ='BAlance sheet HUL'!C9 -> 0 | D9: 0 | E9: 0 | F9: 0 | G9: 0 | H9: 0 | I9: 295 | J9: 393 | K9: 647 | L9: 643
B10: Other Borrowings | C10: ='BAlance sheet HUL'!C10 -> 8043 | D10: 904 | E10: 155 | F10: 378 | G10: 186 | H10: 270 | I10: 34 | J10: 0 | K10: 0 | L10: 0
B11: Other Liabilities -
B12: Non controlling int | C12: ='BAlance sheet HUL'!C11 -> 20 | D12: 0 | E12: 0 | F12: 0 | G12: 1 | H12: 1 | I12: 0 | J12: 0 | K12: 0 | L12: 0
B13: Trade Payables | C13: ='BAlance sheet HUL'!C12 -> 5685 | D13: 119 | E13: 194 | F13: 261 | G13: 317 | H13: 463 | I13: 433 | J13: 578 | K13: 589 | L13: 754
B14: ='BAlance sheet HUL'!B13 -> Advance from Customers | C14: ='BAlance sheet HUL'!C13 -> 45
B15: Other liability items | C15: ='BAlance sheet HUL'!C14 -> 2293 | D15: 133 | E15: 194 | F15: 219 | G15: 222 | H15: 254 | I15: 229 | J15: 500 | K15: 557 | L15: 629
B16: Total Liabilities | C16: =SUM(C7:C14) -> 13970 | D16: 2355 | E16: 3102 | F16: 5819 | G16: 5648 | H16: 7006 | I16: 12076 | J16: 13655 | K16: 15471 | L16: 18105
B18: Fixed Assets -
B19: Land | C19: 460 | D19: 602 | E19: 784 | F19: 1044 | G19: 1438 | H19: 2028 | I19: 2740 | J19: 3483 | K19: 4527 | L19: 5519
B20: Building | C20: 717 | D20: 946 | E20: 1162 | F20: 1379 | G20: 1757 | H20: 2173 | I20: 3139 | J20: 3649 | K20: 4938 | L20: 6201
B21: Plant Machinery | C21: 39 | D21: 51 | E21: 59 | F21: 88 | G21: 124 | H21: 191 | I21: 272 | J21: 352 | K21: 491 | L21: 656
B22: Equipments | C22: 9 | D22: 12 | E22: 11 | F22: 16 | G22: 21 | H22: 29 | I22: 39 | J22: 50 | K22: 73 | L22: 85
B23: Computers | C23: 23 | D23: 30 | E23: 21 | F23: 30 | G23: 53 | H23: 76 | I23: 95 | J23: 119 | K23: 153 | L23: 190
B24: Furniture n fittings | C24: 135 | D24: 172 | E24: 143 | F24: 202 | G24: 265 | H24: 357 | I24: 476 | J24: 581 | K24: 772 | L24: 968
B25: Vehicles | C25: 4 | D25: 6 | E25: 6 | F25: 6 | G25: 2 | H25: 3 | I25: 4 | J25: 4 | K25: 3 | L25: 15
B26: Intangible Assets | C26: 0 | D26: 0 | E26: 0 | F26: 0 | G26: 78 | H26: 78 | I26: 78 | J26: 78 | K26: 78 | L26: 78
B27: Other fixed assets | C27: 10 | D27: 12 | E27: 6 | F27: 39 | G27: 61 | H27: 74 | I27: 82 | J27: 81 | K27: 91 | L27: 105
B28: Gross Block | C28: 1397 | D28: 1832 | E28: 2192 | F28: 2805 | G28: 3801 | H28: 5010 | I28: 6927 | J28: 8396 | K28: 11127 | L28: 13816
B29: Accumulated Depreciation | C29: 225 | D29: 304 | E29: 98 | F29: 228 | G29: 401 | H29: 609 | I29: 979 | J29: 1387 | K29: 1867 | L29: 2476
B30: Net Block | C30: =C28-C29 -> 1172 | D30: =D28-D29 -> 1528 | E30: =E28-E29 -> 2094 | F30: =F28-F29 -> 2577 | G30: =G28-G29 -> 3400 | H30: =H28-H29 -> 4401 | I30: =I28-I29 -> 5948 | J30: =J28-J29 -> 7009 | ... L30: =L28-L29 -> 11340
B32: CWIP | C32: 89 | D32: 98 | E32: 82 | F32: 153 | G32: 147 | H32: 377 | I32: 364 | J32: 1020 | K32: 1129 | L32: 829
B33: Investments | C33: 16 | D33: 15 | E33: 29 | F33: 26 | G33: 68 | H33: 17 | I33: 15 | J33: 3 | K33: 6 | L33: 202
B35: Other Assets -
B36: Inventories | C36: 378 | D36: 540 | E36: 672 | F36: 948 | G36: 1163 | H36: 1609 | I36: 1947 | J36: 2248 | K36: 2743 | L36: 3243
B37: Trade receivables | C37: 10 | D37: 7 | E37: 8 | F37: 21 | G37: 34 | H37: 64 | I37: 20 | J37: 44 | K37: 67 | L37: 62
B38: Cash Equivalents | C38: 55 | D38: 38 | E38: 35 | F38: 1884 | G38: 560 | H38: 219 | I38: 108 | J38: 1446 | K38: 299 | L38: 1408
B39: Loans n Advances | C39: 14 | D39: 21 | E39: 32 | F39: 45 | G39: 51 | H39: 98 | I39: 94 | J39: 81 | K39: 109 | L39: 97
B40: Other asset items | C40: 74 | D40: 108 | E40: 150 | F40: 165 | G40: 225 | H40: 221 | I40: 3580 | J40: 1806 | K40: 1859 | L40: 922
B41: Total Assets | C41: 1808 | D41: 2355 | E41: 3102 | F41: 5819 | G41: 5648 | H41: 7006 | I41: 12076 | J41: 13655 | K41: 15471 | L41: 18105

Sheet Balance Sheet
A1: ='Profit & Loss'!A1 -> HINDUSTAN UNILEVER LTD | E1: =UPDATE | J1: SCREENER.IN
A3: Narration | B3: ='Data Sheet'!B56 -> 42460 | C3: ='Data Sheet'!C56 -> 42825 | D3: ='Data Sheet'!D56 -> 43190 | E3: ='Data Sheet'!E56 -> 43555 | F3: ='Data Sheet'!F56 -> 43921 | G3: ='Data Sheet'!G56 -> 44286 | H3: ='Data Sheet'!H56 -> 44651 | I3: ='Data Sheet'!I56 -> 45016 | ... K3: ='Data Sheet'!K56 -> 45747
A4: Equity Share Capital | B4: ='Data Sheet'!B57 -> 216 | C4: ='Data Sheet'!C57 -> 216 | D4: ='Data Sheet'!D57 -> 216 | E4: ='Data Sheet'!E57 -> 216 | F4: ='Data Sheet'!F57 -> 216 | G4: ='Data Sheet'!G57 -> 235 | H4: ='Data Sheet'!H57 -> 235 | I4: ='Data Sheet'!I57 -> 235 | ... K4: ='Data Sheet'!K57 -> 235
A5: Reserves | B5: ='Data Sheet'!B58 -> 6357 | C5: ='Data Sheet'!C58 -> 6528 | D5: ='Data Sheet'!D58 -> 7065 | E5: ='Data Sheet'!E58 -> 7651 | F5: ='Data Sheet'!F58 -> 8013 | G5: ='Data Sheet'!G58 -> 47439 | H5: ='Data Sheet'!H58 -> 48826 | I5: ='Data Sheet'!I58 -> 50069 | ... K5: ='Data Sheet'!K58 -> 49167
A6: Borrowings | B6: ='Data Sheet'!B59 -> 177 | C6: ='Data Sheet'!C59 -> 277 | D6: ='Data Sheet'!D59 -> 0 | E6: ='Data Sheet'!E59 -> 99 | F6: ='Data Sheet'!F59 -> 0 | G6: ='Data Sheet'!G59 -> 0 | H6: ='Data Sheet'!H59 -> 1043 | I6: ='Data Sheet'!I59 -> 1219 | ... K6: ='Data Sheet'!K59 -> 1648
A7: Other Liabilities | B7: ='Data Sheet'!B60 -> 8043 | C7: ='Data Sheet'!C60 -> 8685 | D7: ='Data Sheet'!D60 -> 10581 | E7: ='Data Sheet'!E60 -> 10663 | F7: ='Data Sheet'!F60 -> 11924 | G7: ='Data Sheet'!G60 -> 21066 | H7: ='Data Sheet'!H60 -> 20402 | I7: ='Data Sheet'!I60 -> 21554 | ... K7: ='Data Sheet'!K60 -> 28813
A8: Total | B8: ='Data Sheet'!B61 -> 14793 | C8: ='Data Sheet'!C61 -> 15706 | D8: ='Data Sheet'!D61 -> 17862 | E8: ='Data Sheet'!E61 -> 18629 | F8: ='Data Sheet'!F61 -> 20153 | G8: ='Data Sheet'!G61 -> 68740 | H8: ='Data Sheet'!H61 -> 70506 | I8: ='Data Sheet'!I61 -> 73077 | ... K8: ='Data Sheet'!K61 -> 79863
A10: Net Block | B10: ='Data Sheet'!B62 -> 3258 | C10: ='Data Sheet'!C62 -> 4419 | D10: ='Data Sheet'!D62 -> 4528 | E10: ='Data Sheet'!E62 -> 4715 | F10: ='Data Sheet'!F62 -> 5479 | G10: ='Data Sheet'!G62 -> 51443 | H10: ='Data Sheet'!H62 -> 51473 | I10: ='Data Sheet'!I62 -> 52678 | ... K10: ='Data Sheet'!K62 -> 54335
A11: Capital Work in Progress | B11: ='Data Sheet'!B63 -> 408 | C11: ='Data Sheet'!C63 -> 229 | D11: ='Data Sheet'!D63 -> 461 | E11: ='Data Sheet'!E63 -> 406 | F11: ='Data Sheet'!F63 -> 597 | G11: ='Data Sheet'!G63 -> 745 | H11: ='Data Sheet'!H63 -> 1313 | I11: ='Data Sheet'!I63 -> 1132 | ... K11: ='Data Sheet'!K63 -> 1009
A12: Investments | B12: ='Data Sheet'!B64 -> 2592 | C12: ='Data Sheet'!C64 -> 3794 | D12: ='Data Sheet'!D64 -> 2873 | E12: ='Data Sheet'!E64 -> 2716 | F12: ='Data Sheet'!F64 -> 1255 | G12: ='Data Sheet'!G64 -> 2709 | H12: ='Data Sheet'!H64 -> 3521 | I12: ='Data Sheet'!I64 -> 2882 | ... K12: ='Data Sheet'!K64 -> 3810
A13: Other Assets | B13: ='Data Sheet'!B65 -> 8535 | C13: ='Data Sheet'!C65 -> 7264 | D13: ='Data Sheet'!D65 -> 10000 | E13: ='Data Sheet'!E65 -> 10792 | F13: ='Data Sheet'!F65 -> 12822 | G13: ='Data Sheet'!G65 -> 13843 | H13: ='Data Sheet'!H65 -> 14199 | I13: ='Data Sheet'!I65 -> 16385 | ... K13: ='Data Sheet'!K65 -> 20709
A14: Total | B14: ='Data Sheet'!B66 -> 14793 | C14: ='Data Sheet'!C66 -> 15706 | D14: ='Data Sheet'!D66 -> 17862 | E14: ='Data Sheet'!E66 -> 18629 | F14: ='Data Sheet'!F66 -> 20153 | G14: ='Data Sheet'!G66 -> 68740 | H14: ='Data Sheet'!H66 -> 70506 | I14: ='Data Sheet'!I66 -> 73077 | ... K14: ='Data Sheet'!K66 -> 79863
A16: Working Capital | B16: =B13-B7 -> 492 | C16: =C13-C7 -> -1421 | D16: =D13-D7 -> -581 | E16: =E13-E7 -> 129 | F16: =F13-F7 -> 898 | G16: =G13-G7 -> -7223 | H16: =H13-H7 -> -6203 | I16: =I13-I7 -> -5169 | ... K16: =K13-K7 -> -8104
A17: Debtors | B17: ='Data Sheet'!B67 -> 1264 | C17: ='Data Sheet'!C67 -> 1085 | D17: ='Data Sheet'!D67 -> 1310 | E17: ='Data Sheet'!E67 -> 1816 | F17: ='Data Sheet'!F67 -> 1149 | G17: ='Data Sheet'!G67 -> 1758 | H17: ='Data Sheet'!H67 -> 2236 | I17: ='Data Sheet'!I67 -> 3079 | ... K17: ='Data Sheet'!K67 -> 3819
A18: Inventory | B18: ='Data Sheet'!B68 -> 2726 | C18: ='Data Sheet'!C68 -> 2541 | D18: ='Data Sheet'!D68 -> 2513 | E18: ='Data Sheet'!E68 -> 2574 | F18: ='Data Sheet'!F68 -> 2767 | G18: ='Data Sheet'!G68 -> 3579 | H18: ='Data Sheet'!H68 -> 4096 | I18: ='Data Sheet'!I68 -> 4251 | ... K18: ='Data Sheet'!K68 -> 4415
A20: Debtor Days | B20: =IF('Profit & Loss'!B4>0,'Balance Sheet'!B17/('Profit & Loss'!B4/365),0) -> 14.334183 | C20: =IF('Profit & Loss'!C4>0,'Balance Sheet'!C17/('Profit & Loss'!C4/365),0) -> 11.942133 | D20: =IF('Profit & Loss'!D4>0,'Balance Sheet'!D17/('Profit & Loss'!D4/365),0) -> 13.451962 | E20: =IF('Profit & Loss'!E4>0,'Balance Sheet'!E17/('Profit & Loss'!E4/365),0) -> 16.861867 | F20: =IF('Profit & Loss'!F4>0,'Balance Sheet'!F17/('Profit & Loss'!F4/365),0) -> 10.541814 | G20: =IF('Profit & Loss'!G4>0,'Balance Sheet'!G17/('Profit & Loss'!G4/365),0) -> 13.644425 | H20: =IF('Profit & Loss'!H4>0,'Balance Sheet'!H17/('Profit & Loss'!H4/365),0) -> 15.56153 | I20: =IF('Profit & Loss'!I4>0,'Balance Sheet'!I17/('Profit & Loss'!I4/365),0) -> 18.551255 | ... K20: =IF('Profit & Loss'!K4>0,'Balance Sheet'!K17/('Profit & Loss'!K4/365),0) -> 22.083538
A21: Inventory Turnover | B21: =IF('Balance Sheet'!B18>0,'Profit & Loss'!B4/'Balance Sheet'!B18,0) -> 11.807043 | C21: =IF('Balance Sheet'!C18>0,'Profit & Loss'!C4/'Balance Sheet'!C18,0) -> 13.050767 | D21: =IF('Balance Sheet'!D18>0,'Profit & Loss'!D4/'Balance Sheet'!D18,0) -> 14.144449 | E21: =IF('Balance Sheet'!E18>0,'Profit & Loss'!E4/'Balance Sheet'!E18,0) -> 15.27195 | F21: =IF('Balance Sheet'!F18>0,'Profit & Loss'!F4/'Balance Sheet'!F18,0) -> 14.377665 | G21: =IF('Balance Sheet'!G18>0,'Profit & Loss'!G4/'Balance Sheet'!G18,0) -> 13.139983 | H21: =IF('Balance Sheet'!H18>0,'Profit & Loss'!H4/'Balance Sheet'!H18,0) -> 12.804199 | I21: =IF('Balance Sheet'!I18>0,'Profit & Loss'!I4/'Balance Sheet'!I18,0) -> 14.250765 | ... K21: =IF('Balance Sheet'!K18>0,'Profit & Loss'!K4/'Balance Sheet'!K18,0) -> 14.296942
A23: Return on Equity | B23: =IF(SUM('Balance Sheet'!B4:B5)>0,'Profit & Loss'!B12/SUM('Balance Sheet'!B4:B5),"") -> 0.6315229 | C23: =IF(SUM('Balance Sheet'!C4:C5)>0,'Profit & Loss'!C12/SUM('Balance Sheet'!C4:C5),"") -> 0.66370107 | D23: =IF(SUM('Balance Sheet'!D4:D5)>0,'Profit & Loss'!D12/SUM('Balance Sheet'!D4:D5),"") -> 0.71611042 | E23: =IF(SUM('Balance Sheet'!E4:E5)>0,'Profit & Loss'!E12/SUM('Balance Sheet'!E4:E5),"") -> 0.76954366 | F23: =IF(SUM('Balance Sheet'!F4:F5)>0,'Profit & Loss'!F12/SUM('Balance Sheet'!F4:F5),"") -> 0.82002673 | G23: =IF(SUM('Balance Sheet'!G4:G5)>0,'Profit & Loss'!G12/SUM('Balance Sheet'!G4:G5),"") -> 0.16770147 | H23: =IF(SUM('Balance Sheet'!H4:H5)>0,'Profit & Loss'!H12/SUM('Balance Sheet'!H4:H5),"") -> 0.18097878 | I23: =IF(SUM('Balance Sheet'!I4:I5)>0,'Profit & Loss'!I12/SUM('Balance Sheet'!I4:I5),"") -> 0.20117684 | ... K23: =IF(SUM('Balance Sheet'!K4:K5)>0,'Profit & Loss'!K12/SUM('Balance Sheet'!K4:K5),"") -> 0.21555807
A24: Return on Capital Emp | C24: =IF((B4+B5+B6+C4+C5+C6)>0,('Profit & Loss'!C10+'Profit & Loss'!C9)*2/(B4+B5+B6+C4+C5+C6),"") -> 0.94430325 | D24: =IF((C4+C5+C6+D4+D5+D6)>0,('Profit & Loss'!D10+'Profit & Loss'!D9)*2/(C4+C5+C6+D4+D5+D6),"") -> 1.0253111 | E24: =IF((D4+D5+D6+E4+E5+E6)>0,('Profit & Loss'!E10+'Profit & Loss'!E9)*2/(D4+D5+D6+E4+E5+E6),"") -> 1.1329442 | F24: =IF((E4+E5+E6+F4+F5+F6)>0,('Profit & Loss'!F10+'Profit & Loss'!F9)*2/(E4+E5+E6+F4+F5+F6),"") -> 1.1464032 | G24: =IF((F4+F5+F6+G4+G5+G6)>0,('Profit & Loss'!G10+'Profit & Loss'!G9)*2/(F4+F5+F6+G4+G5+G6),"") -> 0.38359301 | H24: =IF((G4+G5+G6+H4+H5+H6)>0,('Profit & Loss'!H10+'Profit & Loss'!H9)*2/(G4+G5+G6+H4+H5+H6),"") -> 0.24514717 | I24: =IF((H4+H5+H6+I4+I5+I6)>0,('Profit & Loss'!I10+'Profit & Loss'!I9)*2/(H4+H5+H6+I4+I5+I6),"") -> 0.26485088 | J24: =IF((I4+I5+I6+J4+J5+J6)>0,('Profit & Loss'!J10+'Profit & Loss'!J9)*2/(I4+I5+I6+J4+J5+J6),"") -> 0.27363876 | K24: =IF((J4+J5+J6+K4+K5+K6)>0,('Profit & Loss'!K10+'Profit & Loss'!K9)*2/(J4+J5+J6+K4+K5+K6),"") -> 0.28548847
C27: ='Profit & Loss'!B12/('Balance Sheet'!B4+B5) -> 0.6315229 | D27: ='Profit & Loss'!C12/('Balance Sheet'!C4+'Balance Sheet'!C5) -> 0.66370107
D28: ='Profit & Loss'!B32/SUM('Balance Sheet'!B4:B6) -> 0.89525926 | E28: ='Profit & Loss'!C32/SUM('Balance Sheet'!C4:C6) -> 0.92607891
E29: ='Profit & Loss'!C32*2/SUM('Balance Sheet'!B4,'Balance Sheet'!B5,'Balance Sheet'!B6,'Balance Sheet'!C4,'Balance Sheet'!C5,'Balance Sheet'!C6) -> 0.94430325
E30: =('Profit & Loss'!C32)*2/SUM('Balance Sheet'!C4,'Balance Sheet'!C5,'Balance Sheet'!C6,'Balance Sheet'!D4,'Balance Sheet'!D5,'Balance Sheet'!D6) -> 0.90924346

Sheet Sheet1
B2: Date | C2: Close
B3: 36528 | C3: 230.76
B4: 36529 | C4: 228.11
B5: 36530 | C5: 219.99
B6: 36531 | C6: 228.82
B7: 36532 | C7: 241.3
B8: 36535 | C8: 243.13
B9: 36536 | C9: 248.58
B10: 36537 | C10: 264.78
B11: 36538 | C11: 278.67
B12: 36539 | C12: 270.21
B13: 36542 | C13: 259.83
B14: 36543 | C14: 256.15
... B6354: 45912 | C6354: 2580.5

Sheet Quarters
A1: ='Profit & Loss'!A1 -> HINDUSTAN UNILEVER LTD | E1: =UPDATE | J1: SCREENER.IN
A3: Narration | B3: ='Data Sheet'!B41 -> 45016 | C3: ='Data Sheet'!C41 -> 45107 | D3: ='Data Sheet'!D41 -> 45199 | E3: ='Data Sheet'!E41 -> 45291 | F3: ='Data Sheet'!F41 -> 45382 | G3: ='Data Sheet'!G41 -> 45473 | H3: ='Data Sheet'!H41 -> 45565 | I3: ='Data Sheet'!I41 -> 45657 | ... K3: ='Data Sheet'!K41 -> 45838
A4: Sales | B4: ='Data Sheet'!B42 -> 15215 | C4: ='Data Sheet'!C42 -> 15496 | D4: ='Data Sheet'!D42 -> 15623 | E4: ='Data Sheet'!E42 -> 15567 | F4: ='Data Sheet'!F42 -> 15210 | G4: ='Data Sheet'!G42 -> 15707 | H4: ='Data Sheet'!H42 -> 15926 | I4: ='Data Sheet'!I42 -> 15818 | ... K4: ='Data Sheet'!K42 -> 16514
A5: Expenses | B5: ='Data Sheet'!B43 -> 11643 | C5: ='Data Sheet'!C43 -> 11832 | D5: ='Data Sheet'!D43 -> 11828 | E5: ='Data Sheet'!E43 -> 11902 | F5: ='Data Sheet'!F43 -> 11675 | G5: ='Data Sheet'!G43 -> 11965 | H5: ='Data Sheet'!H43 -> 12139 | I5: ='Data Sheet'!I43 -> 12123 | ... K5: ='Data Sheet'!K43 -> 12797
A6: Operating Profit | B6: ='Data Sheet'!B50 -> 3572 | C6: ='Data Sheet'!C50 -> 3664 | D6: ='Data Sheet'!D50 -> 3795 | E6: ='Data Sheet'!E50 -> 3665 | F6: ='Data Sheet'!F50 -> 3535 | G6: ='Data Sheet'!G50 -> 3742 | H6: ='Data Sheet'!H50 -> 3787 | I6: ='Data Sheet'!I50 -> 3695 | ... K6: ='Data Sheet'!K50 -> 3717
A7: Other Income | B7: ='Data Sheet'!B44 -> 240 | C7: ='Data Sheet'!C44 -> 146 | D7: ='Data Sheet'!D44 -> 178 | E7: ='Data Sheet'!E44 -> 184 | F7: ='Data Sheet'!F44 -> 309 | G7: ='Data Sheet'!G44 -> 209 | H7: ='Data Sheet'!H44 -> 203 | I7: ='Data Sheet'!I44 -> 740 | ... K7: ='Data Sheet'!K44 -> 74
A8: Depreciation | B8: ='Data Sheet'!B45 -> 291 | C8: ='Data Sheet'!C45 -> 286 | D8: ='Data Sheet'!D45 -> 297 | E8: ='Data Sheet'!E45 -> 313 | F8: ='Data Sheet'!F45 -> 320 | G8: ='Data Sheet'!G45 -> 329 | H8: ='Data Sheet'!H45 -> 338 | I8: ='Data Sheet'!I45 -> 341 | ... K8: ='Data Sheet'!K45 -> 361
A9: Interest | B9: ='Data Sheet'!B46 -> 29 | C9: ='Data Sheet'!C46 -> 50 | D9: ='Data Sheet'!D46 -> 88 | E9: ='Data Sheet'!E46 -> 91 | F9: ='Data Sheet'!F46 -> 105 | G9: ='Data Sheet'!G46 -> 93 | H9: ='Data Sheet'!H46 -> 110 | I9: ='Data Sheet'!I46 -> 112 | ... K9: ='Data Sheet'!K46 -> 127
A10: Profit before tax | B10: ='Data Sheet'!B47 -> 3492 | C10: ='Data Sheet'!C47 -> 3474 | D10: ='Data Sheet'!D47 -> 3588 | E10: ='Data Sheet'!E47 -> 3445 | F10: ='Data Sheet'!F47 -> 3419 | G10: ='Data Sheet'!G47 -> 3529 | H10: ='Data Sheet'!H47 -> 3542 | I10: ='Data Sheet'!I47 -> 3982 | ... K10: ='Data Sheet'!K47 -> 3303
A11: Tax | B11: ='Data Sheet'!B48 -> 891 | C11: ='Data Sheet'!C48 -> 918 | D11: ='Data Sheet'!D48 -> 931 | E11: ='Data Sheet'!E48 -> 937 | F11: ='Data Sheet'!F48 -> 858 | G11: ='Data Sheet'!G48 -> 917 | H11: ='Data Sheet'!H48 -> 947 | I11: ='Data Sheet'!I48 -> 993 | ... K11: ='Data Sheet'!K48 -> 535
A12: Net profit | B12: ='Data Sheet'!B49 -> 2600 | C12: ='Data Sheet'!C49 -> 2554 | D12: ='Data Sheet'!D49 -> 2656 | E12: ='Data Sheet'!E49 -> 2509 | F12: ='Data Sheet'!F49 -> 2558 | G12: ='Data Sheet'!G49 -> 2610 | H12: ='Data Sheet'!H49 -> 2591 | I12: ='Data Sheet'!I49 -> 2984 | ... K12: ='Data Sheet'!K49 -> 2756
A14: OPM | B14: =IF(B4>0,B6/B4,"") -> 0.23476832 | C14: =IF(C4>0,C6/C4,"") -> 0.23644812 | D14: =IF(D4>0,D6/D4,"") -> 0.24291109 | E14: =IF(E4>0,E6/E4,"") -> 0.23543393 | F14: =IF(F4>0,F6/F4,"") -> 0.23241289 | G14: =IF(G4>0,G6/G4,"") -> 0.23823773 | H14: =IF(H4>0,H6/H4,"") -> 0.23778727 | I14: =IF(I4>0,I6/I4,"") -> 0.23359464 | ... K14: =IF(K4>0,K6/K4,"") -> 0.22508175

Sheet Sheet2
B4: S.No. | C4: Name | D4: CMP Rs. | E4: Debt Rs.Cr. | F4: EV Rs.Cr. | G4: No. Eq. Shares Cr. | H4: Cash End Rs.Cr. | I4: Sales Rs.Cr. | J4: EBIT 12M Rs.Cr. | K4: Dep 12M Rs.Cr. | L4: NP 12M Rs.Cr. | M4: EPS 12M Rs. | N4: Mar Cap Rs.Cr. | O4: Net debt | P4: EBITDA
B5: 1 | C5: Hind. Unilever | D5: 2584 | E5: 1648 | F5: 601344.18 | G5: 234.96 | H5: 7554 | I5: 63928 | J5: 14392 | K5: 1387 | L5: 10827 | M5: 45.94 | N5: 607250.18 | O5: =E5-H5 -> -5906 | P5: =J5+K5 -> 15779
B6: 2 | C6: ITC | D6: 413.6 | E6: 284.54 | F6: 514437.38 | G6: 1252.67 | H6: 4012.36 | I6: 79040.32 | J6: 27288.31 | K6: 1666.15 | L6: 35218.9 | M6: 27.89 | N6: 518165.2 | O6: =E6-H6 -> -3727.82 | P6: =J6+K6 -> 28954.46
B7: 3 | C7: Nestle India | D7: 1217.45 | E7: 1166.85 | F7: 235930.01 | G7: 192.83 | H7: 95.65 | I7: 20483.77 | J7: 4199.27 | K7: 584.15 | L7: 3227.13 | M7: 16.74 | N7: 234858.81 | O7: =E7-H7 -> 1071.2 | P7: =J7+K7 -> 4783.42
B8: 4 | C8: Varun Beverages | D8: 469.9 | E8: 2138.25 | F8: 158924.38 | G8: 338.2 | H8: 2450.05 | I8: 21077.78 | J8: 4069.35 | K8: 1096.05 | L8: 2881.31 | M8: 8.5 | N8: 158935.1 | O8: =E8-H8 -> -311.8 | P8: =J8+K8 -> 5165.4
B9: 5 | C9: Britannia Inds. | D9: 6251 | E9: 1246.51 | F9: 151486.47 | G9: 24.09 | H9: 312.48 | I9: 18314.59 | J9: 3082.63 | K9: 321.45 | L9: 2193.11 | M9: 91.08 | N9: 150552.44 | O9: =E9-H9 -> 934.03 | P9: =J9+K9 -> 3404.08
B10: 6 | C10: Godrej Consumer | D10: 1253.8 | E10: 4009.19 | F10: 131531.36 | G10: 102.31 | H10: 483.06 | I10: 14694.57 | J10: 3052.74 | K10: 243.89 | L10: 1853.97 | M10: 18.12 | N10: 128005.23 | O10: =E10-H10 -> 3526.13 | P10: =J10+K10 -> 3296.63
B11: 7 | C11: Tata Consumer | D11: 1102.5 | E11: 2392.68 | F11: 108695.95 | G11: 98.95 | H11: 2817.86 | I11: 18045.14 | J11: 2012.49 | K11: 601.67 | L11: 1329.6 | M11: 13.36 | N11: 109121.13 | O11: =E11-H11 -> -425.18 | P11: =J11+K11 -> 2614.16
B12: 8 | C12: Dabur India | D12: 538.8 | E12: 950.37 | F12: 95938.78 | G12: 177.37 | H12: 578.01 | I12: 12618.56 | J12: 2443.53 | K12: 450.62 | L12: 1754.36 | M12: 10.05 | N12: 95566.42 | O12: =E12-H12 -> 372.36 | P12: =J12+K12 -> 2894.15
B13: 9 | C13: Marico | D13: 736.1 | E13: 554 | F13: 95302.71 | G13: 129.79 | H13: 777 | I13: 11447 | J13: 2213 | K13: 182 | L13: 1697 | M13: 12.88 | N13: 95525.71 | O13: =E13-H13 -> -223 | P13: =J13+K13 -> 2395
B14: 10 | C14: United Spirits | D14: 1308 | E14: 480 | F14: 93555.04 | G14: 72.74 | H14: 2030 | I14: 12329 | J14: 2248 | K14: 287 | L14: 1514 | M14: 20.82 | N14: 95105.04 | O14: =E14-H14 -> -1550 | P14: =J14+K14 -> 2535
B15: 11 | C15: Patanjali Foods | D15: 592.9 | E15: 787.67 | F15: 64982.79 | G15: 108.78 | H15: 275.3 | I15: 35866.38 | J15: 1704.89 | K15: 273.26 | L15: 1218.83 | M15: 11.22 | N15: 64470.42 | O15: =E15-H15 -> 512.37 | P15: =J15+K15 -> 1978.15
B16: 12 | C16: Colgate-Palmoliv | D16: 2353.35 | E16: 60.84 | F16: 62996.37 | G16: 27.2 | H16: 1095.13 | I16: 5977.52 | J16: 1876.9 | K16: 158.77 | L16: 1393.45 | M16: 51.23 | N16: 64030.66 | O16: =E16-H16 -> -1034.29 | P16: =J16+K16 -> 2035.67
... B19: 15 | C19: P & G Hygiene | D19: 13201 | E19: 2.32 | F19: 42375.29 | G19: 3.25 | H19: 480.7 | I19: 4311.45 | J19: 1141.23 | K19: 41.03 | L19: 828.65 | M19: 255.28 | N19: 42853.67 | O19: =E19-H19 -> -478.38 | P19: =J19+K19 -> 1182.26

Sheet Cash Flow
A1: ='Balance Sheet'!A1 -> HINDUSTAN UNILEVER LTD | E1: =UPDATE | J1: SCREENER.IN
A3: Narration | B3: ='Data Sheet'!B81 -> 42460 | C3: ='Data Sheet'!C81 -> 42825 | D3: ='Data Sheet'!D81 -> 43190 | E3: ='Data Sheet'!E81 -> 43555 | F3: ='Data Sheet'!F81 -> 43921 | G3: ='Data Sheet'!G81 -> 44286 | H3: ='Data Sheet'!H81 -> 44651 | I3: ='Data Sheet'!I81 -> 45016 | ... K3: ='Data Sheet'!K81 -> 45747
A4: Cash from Operating Activity | B4: ='Data Sheet'!B82 -> 4171 | C4: ='Data Sheet'!C82 -> 5185 | D4: ='Data Sheet'!D82 -> 6059 | E4: ='Data Sheet'!E82 -> 5800 | F4: ='Data Sheet'!F82 -> 7623 | G4: ='Data Sheet'!G82 -> 9163 | H4: ='Data Sheet'!H82 -> 9048 | I4: ='Data Sheet'!I82 -> 9991 | ... K4: ='Data Sheet'!K82 -> 11886
A5: Cash from Investing Activity | B5: ='Data Sheet'!B83 -> -282 | C5: ='Data Sheet'!C83 -> -1173 | D5: ='Data Sheet'!D83 -> -1063 | E5: ='Data Sheet'!E83 -> -438 | F5: ='Data Sheet'!F83 -> 1791 | G5: ='Data Sheet'!G83 -> -1228 | H5: ='Data Sheet'!H83 -> -1728 | I5: ='Data Sheet'!I83 -> -1484 | ... K5: ='Data Sheet'!K83 -> 6473
A6: Cash from Financing Activity | B6: ='Data Sheet'!B84 -> -3864 | C6: ='Data Sheet'!C84 -> -4214 | D6: ='Data Sheet'!D84 -> -4975 | E6: ='Data Sheet'!E84 -> -5390 | F6: ='Data Sheet'!F84 -> -6819 | G6: ='Data Sheet'!G84 -> -9309 | H6: ='Data Sheet'!H84 -> -8015 | I6: ='Data Sheet'!I84 -> -8953 | ... K6: ='Data Sheet'!K84 -> -13101
A7: Net Cash Flow | B7: ='Data Sheet'!B85 -> 25 | C7: ='Data Sheet'!C85 -> -202 | D7: ='Data Sheet'!D85 -> 21 | E7: ='Data Sheet'!E85 -> -28 | F7: ='Data Sheet'!F85 -> 2595 | G7: ='Data Sheet'!G85 -> -1374 | H7: ='Data Sheet'!H85 -> -695 | I7: ='Data Sheet'!I85 -> -446 | ... K7: ='Data Sheet'!K85 -> 5258

Sheet Customization
A1: How to use it?
A3: You can customize this workbook as you want.
B4: You can add custom formating, add conditional formating, add your own formulas… do ANYTHING.
B5: Please don't edit the "Data Sheet" only.
A7: After customization, you can upload this back on Screener.
B8: Upload on: | C8: https://www.screener.in/excel/
A10: Download your customized workbooks now onwards.
B11: Now whenever you will "Export to excel" from Screener, it will export your customized file.
A14: TESTING:
B15: This is a testing feature currently.
B16: You can report any formula errors on the worksheet at: support@screener.in

Sheet itc share price
C5: Date | D5: Close | E5: Volume
C6: 45912 | D6: 2580.5 | E6: 1.36838
C7: 45911 | D7: 2622 | E7: 1.212707
C8: 45910 | D8: 2643.5 | E8: 1.031486
C9: 45909 | D9: 2642 | E9: 1.610956
C10: 45908 | D10: 2623.9 | E10: 0.90341
C11: 45905 | D11: 2633.4 | E11: 0.944879
C12: 45904 | D12: 2666.6 | E12: 2.494678
C13: 45903 | D13: 2664.7 | E13: 1.010692
C14: 45902 | D14: 2677 | E14: 1.525106
C15: 45901 | D15: 2649.5 | E15: 1.096729 | F15: 1000000
C16: 45898 | D16: 2659.8 | E16: 1.972773
C17: 45897 | D17: 2654.4 | E17: 3.198743
C18: 45895 | D18: 2692.6 | E18: 4.348648
C19: 45894 | D19: 2631.6 | E19: 0.667598
C20: 45891 | D20: 2629.9 | E20: 1.223445
C21: 45890 | D21: 2648 | E21: 2.235686
C22: 45889 | D22: 2669.8 | E22: 3.156954
C23: 45888 | D23: 2604.8 | E23: 1.400717
C24: 45887 | D24: 2568.1 | E24: 3.089136
C25: 45883 | D25: 2480.6 | E25: 1.104362
C26: 45882 | D26: 2495.1 | E26: 0.969803
C27: 45881 | D27: 2483.8 | E27: 1.406211
... C41: 45861 | D41: 2450.4 | E41: 1.320795
C42: 45860 | D42: 2479.7 | E42: 0.861632 | K42: 10000000
C43: 45859 | D43: 2464.9 | E43: 1.16996 | L43: 100
C44: 45856 | D44: 2489.6 | E44: 0.771112
C45: 45855 | D45: 2509.8 | E45: 0.807474
C46: 45854 | D46: 2517.6 | E46: 1.284379 | I46: Shareholder's name | J46: No Of Shares | K46: % Holding | L46: Market value (In Crs)
C47: 45853 | D47: 2526.9 | E47: 1.700294 | I47: Tobacco Manufacturers (India) Limited | J47: 222.84959 | K47: 0.1781 | L47: ='Data Sheet'!$B$8*J47 -> 563564.32
C48: 45852 | D48: 2516.6 | E48: 2.427712 | I48: Life Insurance Corporation of India | J48: 197.70109 | K48: 0.158 | L48: ='Data Sheet'!$B$8*J48 -> 499966.28
C49: 45849 | D49: 2519.6 | E49: 7.242235 | I49: Specified Undertaking of the Unit Trust of India | J49: 97.453143 | K49: 0.0779 | L49: ='Data Sheet'!$B$8*J49 -> 246449.25
C50: 45848 | D50: 2408.4 | E50: 1.053695 | I50: Myddleton Investment Company Limited | J50: 48.631194 | K50: 0.0389 | L50: ='Data Sheet'!$B$8*J50 -> 122983.43
C51: 45847 | D51: 2423.4 | E51: 1.74169 | I51: SBI Mutual Funds | J51: 43.517441 | K51: 0.0348 | L51: ='Data Sheet'!$B$8*J51 -> 110051.26
C52: 45846 | D52: 2392.7 | E52: 1.471046 | I52: ICICI Prudential Mutual Funds | J52: 27.619721 | K52: 0.0221 | L52: ='Data Sheet'!$B$8*J52 -> 69847.513
C53: 45845 | D53: 2410.4 | E53: 2.701583 | I53: GQG Partners Emerging Markets Equity Fund | J53: 26.390174 | K53: 0.0211 | L53: ='Data Sheet'!$B$8*J53 -> 66738.111
C54: 45842 | D54: 2339.3 | E54: 1.242346 | I54: General Insurance Corporation of India | J54: 21.708551 | K54: 0.0173 | L54: ='Data Sheet'!$B$8*J54 -> 54898.754
C55: 45841 | D55: 2313.4 | E55: 1.060039 | I55: Goldman Sachs GQG Partners International Opportunities Fund | J55: 20.70918 | K55: 0.0165 | L55: ='Data Sheet'!$B$8*J55 -> 52371.444
C56: 45840 | D56: 2307.1 | E56: 1.128034 | I56: NPS Trust (various Pension Funds) | J56: 19.633872 | K56: 0.0157 | L56: ='Data Sheet'!$B$8*J56 -> 49652.099
C57: 45839 | D57: 2295.5 | E57: 0.759914
C58: 45838 | D58: 2294.6 | E58: 1.403754
C59: 45835 | D59: 2306.9 | E59: 1.050745
C60: 45834 | D60: 2280.8 | E60: 1.874722
C61: 45833 | D61: 2278.7 | E61: 1.04727
C62: 45832 | D62: 2263.1 | E62: 2.440747
C63: 45831 | D63: 2275.1 | E63: 0.842856
C64: 45828 | D64: 2306.2 | E64: 2.685864
C65: 45827 | D65: 2294.2 | E65: 1.214549
C66: 45826 | D66: 2297.3 | E66: 2.056563
C67: 45825 | D67: 2328.6 | E67: 1.119284
C68: 45824 | D68: 2327.4 | E68: 1.105297
... C1248: 44075 | D1248: 2161.65 | E1248: 1.738013

Sheet input sheet
I1: Hindustan Unilever Limited (HUL) is an Indian fast-moving consumer goods company, headquartered in Mumbai.[3] It is a subsidiary of the Anglo-Dutch company Unilever. Its products include foods, beverages, cleaning agents, personal care products and other consumer staples. However, the integration of GSK's 3,800 employees remained uncertain as HUL stated there was no clause for retention of employees in the deal.
C4: ITC Limited is an Indian conglomerate, headquartered in Kolkata.It has a presence across six business segments, namely FMCG, agribusiness, information technology, paper products, and packaging. It generates a plurality of its revenue from tobacco products.ITC is the second-largest FMCG company in India and the third-largest tobacco company in the world. It employs 36,500 people at more than 60 locations across India.
G7: 45809
F8: FIIs | G8: =O27 -> 0.1018
F9: DIIs | G9: =O28 -> 0.1599
F10: Public & Government | G10: =SUM(O29:O30) -> 0.1193
F11: =C26 -> Promoters | G11: =O26 -> 0.619
G13: =SUM(G8:G11) -> 1
D25: 44805 | E25: 44896 | F25: 44986 | G25: 45078 | H25: 45170 | I25: 45261 | J25: 45352 | K25: 45444 | L25: 45536 | M25: 45627 | N25: 45717 | O25: 45809
C26: Promoters | D26: 0.619 | E26: 0.619 | F26: 0.619 | G26: 0.619 | H26: 0.619 | I26: 0.619 | J26: 0.619 | K26: 0.619 | L26: 0.619 | M26: 0.619 | N26: 0.619 | O26: 0.619
C27: FIIs | D27: 0.1405 | E27: 0.1432 | F27: 0.1436 | G27: 0.1448 | H27: 0.139 | I27: 0.1365 | J27: 0.1267 | K27: 0.1187 | L27: 0.1217 | M27: 0.1143 | N27: 0.1062 | O27: 0.1018
C28: DIIs | D28: 0.1172 | E28: 0.115 | F28: 0.1151 | G28: 0.1147 | H28: 0.119 | I28: 0.1231 | J28: 0.1321 | K28: 0.1409 | L28: 0.1413 | M28: 0.1467 | N28: 0.1548 | O28: 0.1599
C29: Government | D29: 0.0004 | E29: 0.0004 | F29: 0.0004 | G29: 0.0004 | H29: 0.0004 | I29: 0.0004 | J29: 0.0004 | K29: 0.0005 | L29: 0.0005 | M29: 0.0006 | N29: 0.0007 | O29: 0.0007
C30: Public | D30: 0.1232 | E30: 0.1223 | F30: 0.1217 | G30: 0.1209 | H30: 0.1226 | I30: 0.1211 | J30: 0.1219 | K30: 0.1211 | L30: 0.1175 | M30: 0.1194 | N30: 0.1193 | O30: 0.1186
C34: Shareholder's name | D34: Total Shares Held | E34: Shareholding (%) | F34: Quarter Ending | G34: market value | I34: 10000000
C35: UNILEVER PLC | D35: 111.43701 | E35: 0.4743 | F35: 45809 | G35: ='Data Sheet'!$B$8*'input sheet'!D35 -> 281813.07 | H35: =100 -> 100
C36: LICI INDEX PLUS FLEXI SMART GROWTH FUND | D36: 15.131235 | E36: 0.0644 | F36: 45809 | G36: ='Data Sheet'!$B$8*'input sheet'!D36 -> 38265.381 | L36: Nitin Paranjpe@ Rohit Jawa Ritesh Tiwari BP Biddappa* Dev Bajpai# Leo Puri Ashu Suyash Ranjay Gulati Neelam Dhawan Tarun Bajaj O.P. Bhatt Sanjiv Misra Designation Chairman Chief Executive Officer and Managing Director Executive Director, Finance, IT and CFO Executive Director and Chief People, Transformation and Sustainability Officer Executive Director, Legal and Corporate Affairs and Company Secretary Independent Director Independent Director Independent Director Independent Director Independent Director Independent Director Independent Director Ratio of remuneration of each Director to median remuneration of Employees N.A. 146.47 59.18 66.32 83.65 3.58 3.51 2.71 3.66 3.55 1.49 1.35 Percentage increase in Remuneration N.A. 3.75 9.70 Not comparable** Not comparable** 142.70^ 122.66^ 109^ Not comparable** Not comparable** Not comparable** Not comparable** Kalpana Morparia Independent Director Radhika Shah Company Secretary & Compliance Officer 2.41 Not comparable**
C37: UNILEVER GROUP LIMITED | D37: 10.673946 | E37: 0.0454 | F37: 45809 | G37: ='Data Sheet'!$B$8*'input sheet'!D37 -> 26993.342
C38: UNILEVER OVERSEAS HOLDINGS AG | D38: 6.878432 | E38: 0.0293 | F38: 45809 | G38: ='Data Sheet'!$B$8*'input sheet'!D38 -> 17394.867
C39: UNILEVER UK&CN HOLDINGS LIMITED | D39: 6.008625 | E39: 0.0256 | F39: 45809 | G39: ='Data Sheet'!$B$8*'input sheet'!D39 -> 15195.212
C40: UNILEVER SOUTH INDIA ESTATES LIMITED | D40: 5.27472 | E40: 0.0224 | F40: 45809 | G40: ='Data Sheet'!$B$8*'input sheet'!D40 -> 13339.239
C41: SBI NIFTY 200 QUALITY 30 ETF | D41: 3.9300417 | E41: 0.0167 | F41: 45809 | G41: ='Data Sheet'!$B$8*'input sheet'!D41 -> 9938.6825
C42: ICICI PRUDENTIAL MUTUAL FUND | D42: 3.4360582 | E42: 0.0146 | F42: 45809 | G42: ='Data Sheet'!$B$8*'input sheet'!D42 -> 8689.4476
C43: UNILEVER ASSAM ESTATES LIMITED | D43: 3.282048 | E43: 0.014 | F43: 45809 | G43: ='Data Sheet'!$B$8*'input sheet'!D43 -> 8299.9712
C44: UNILEVER OVERSEAS HOLDINGS B V | D44: 1.8865 | E44: 0.008 | F44: 45809 | G44: ='Data Sheet'!$B$8*'input sheet'!D44 -> 4770.7699
C50: S Puri Chairman & Managing Director 377 : 1 0 | F50: S Puri Chairman & Managing Director 377 : 1 0
C51: S Dutta Executive Director & Chief Financial Officer 132 : 1 21 | F51: S Dutta Executive Director & Chief Financial Officer 132 : 1 21
C52: H Malik Executive Director 99 : 1 148 * | F52: H Malik Executive Director 99 : 1 148 *
C53: B Sumant Executive Director 174 : 1 (3) | F53: B Sumant Executive Director 174 : 1 (3)
C54: H Bhargava Independent Director 14 : 1 (7) | F54: H Bhargava Independent Director 14 : 1 (7)
C55: A M Bharucha Independent Director 9 : 1 2572 * | F55: A M Bharucha Independent Director 9 : 1 2572 *
C56: C K Mishra 1 Independent Director 9 : 1 | F56: C K Mishra 1 Independent Director 9 : 1
C57: S Mohanty 2 Non-Executive Director 0 : 1 | F57: S Mohanty 2 Non-Executive Director 0 : 1
C58: S Mukherjee Independent Director 13 : 1 (8) | F58: S Mukherjee Independent Director 13 : 1 (8)
C59: A Nayak Independent Director 13 : 1 (10) | F59: A Nayak Independent Director 13 : 1 (10)
C60: A Pande 3 Non-Executive Director 1 : 1 | F60: A Pande 3 Non-Executive Director 1 : 1
C61: S Panray Non-Executive Director 13 : 1 (9) | F61: S Panray Non-Executive Director 13 : 1 (9)
... C71: R K Singhi Executive Vice President & Company Secretary 47 : 1 4 | F71: R K Singhi Executive Vice President & Company Secretary 47 : 1 4

Sheet Sheet3

Sheet Profit & Loss
A1: ='Data Sheet'!B1 -> HINDUSTAN UNILEVER LTD | H1: =UPDATE | M1: SCREENER.IN
A3: Narration | B3: ='Data Sheet'!B16 -> 42460 | C3: ='Data Sheet'!C16 -> 42825 | D3: ='Data Sheet'!D16 -> 43190 | E3: ='Data Sheet'!E16 -> 43555 | F3: ='Data Sheet'!F16 -> 43921 | G3: ='Data Sheet'!G16 -> 44286 | H3: ='Data Sheet'!H16 -> 44651 | I3: ='Data Sheet'!I16 -> 45016 | ... K3: ='Data Sheet'!K16 -> 45747 | L3: Trailing | M3: Best Case | N3: Worst Case
A4: Sales | B4: ='Data Sheet'!B17 -> 32186 | C4: ='Data Sheet'!C17 -> 33162 | D4: ='Data Sheet'!D17 -> 35545 | E4: ='Data Sheet'!E17 -> 39310 | F4: ='Data Sheet'!F17 -> 39783 | G4: ='Data Sheet'!G17 -> 47028 | H4: ='Data Sheet'!H17 -> 52446 | I4: ='Data Sheet'!I17 -> 60580 | ... K4: ='Data Sheet'!K17 -> 63121 | L4: =SUM(Quarters!H4:K4) -> 63928 | M4: =$K4+M23*K4 -> 67142.015 | N4: =$K4+N23*L4 -> 64386.216
A5: Expenses | B5: =SUM('Data Sheet'!B18,'Data Sheet'!B20:B24, -1*'Data Sheet'!B19) -> 26276 | C5: =SUM('Data Sheet'!C18,'Data Sheet'!C20:C24, -1*'Data Sheet'!C19) -> 26834 | D5: =SUM('Data Sheet'!D18,'Data Sheet'!D20:D24, -1*'Data Sheet'!D19) -> 28046 | E5: =SUM('Data Sheet'!E18,'Data Sheet'!E20:E24, -1*'Data Sheet'!E19) -> 30430 | F5: =SUM('Data Sheet'!F18,'Data Sheet'!F20:F24, -1*'Data Sheet'!F19) -> 29922 | G5: =SUM('Data Sheet'!G18,'Data Sheet'!G20:G24, -1*'Data Sheet'!G19) -> 35402 | H5: =SUM('Data Sheet'!H18,'Data Sheet'!H20:H24, -1*'Data Sheet'!H19) -> 39589 | I5: =SUM('Data Sheet'!I18,'Data Sheet'!I20:I24, -1*'Data Sheet'!I19) -> 46433 | ... K5: =SUM('Data Sheet'!K18,'Data Sheet'!K20:K24, -1*'Data Sheet'!K19) -> 48278 | L5: =SUM(Quarters!H5:K5) -> 49111 | M5: =M4-M6 -> 51351.448 | N5: =N4-N6 -> 49626.274
A6: Operating Profit | B6: =B4-B5 -> 5910 | C6: =C4-C5 -> 6328 | D6: =D4-D5 -> 7499 | E6: =E4-E5 -> 8880 | F6: =F4-F5 -> 9861 | G6: =G4-G5 -> 11626 | H6: =H4-H5 -> 12857 | I6: =I4-I5 -> 14147 | ... K6: =K4-K5 -> 14843 | L6: =SUM(Quarters!H6:K6) -> 14817 | M6: =M4*M24 -> 15790.567 | N6: =N4*N24 -> 14759.942
A7: Other Income | B7: ='Data Sheet'!B25 -> 486 | C7: ='Data Sheet'!C25 -> 606 | D7: ='Data Sheet'!D25 -> 353 | E7: ='Data Sheet'!E25 -> 322 | F7: ='Data Sheet'!F25 -> 424 | G7: ='Data Sheet'!G25 -> 170 | H7: ='Data Sheet'!H25 -> 219 | I7: ='Data Sheet'!I25 -> 448 | ... K7: ='Data Sheet'!K25 -> 1322 | L7: =SUM(Quarters!H7:K7) -> 1188 | M7: 0 | N7: 0
A8: Depreciation | B8: ='Data Sheet'!B26 -> 353 | C8: ='Data Sheet'!C26 -> 432 | D8: ='Data Sheet'!D26 -> 520 | E8: ='Data Sheet'!E26 -> 565 | F8: ='Data Sheet'!F26 -> 1002 | G8: ='Data Sheet'!G26 -> 1074 | H8: ='Data Sheet'!H26 -> 1091 | I8: ='Data Sheet'!I26 -> 1137 | ... K8: ='Data Sheet'!K26 -> 1355 | L8: =SUM(Quarters!H8:K8) -> 1387 | M8: =+$L8 -> 1387 | N8: =+$L8 -> 1387
A9: Interest | B9: ='Data Sheet'!B27 -> 17 | C9: ='Data Sheet'!C27 -> 35 | D9: ='Data Sheet'!D27 -> 26 | E9: ='Data Sheet'!E27 -> 33 | F9: ='Data Sheet'!F27 -> 118 | G9: ='Data Sheet'!G27 -> 117 | H9: ='Data Sheet'!H27 -> 106 | I9: ='Data Sheet'!I27 -> 114 | ... K9: ='Data Sheet'!K27 -> 395 | L9: =SUM(Quarters!H9:K9) -> 429 | M9: =+$L9 -> 429 | N9: =+$L9 -> 429
A10: Profit before tax | B10: ='Data Sheet'!B28 -> 6026 | C10: ='Data Sheet'!C28 -> 6467 | D10: ='Data Sheet'!D28 -> 7306 | E10: ='Data Sheet'!E28 -> 8604 | F10: ='Data Sheet'!F28 -> 9165 | G10: ='Data Sheet'!G28 -> 10605 | H10: ='Data Sheet'!H28 -> 11879 | I10: ='Data Sheet'!I28 -> 13344 | ... K10: ='Data Sheet'!K28 -> 14415 | L10: =SUM(Quarters!H10:K10) -> 14189 | M10: =M6+M7-SUM(M8:M9) -> 13974.567 | N10: =N6+N7-SUM(N8:N9) -> 12943.942
A11: Tax | B11: ='Data Sheet'!B29 -> 1875 | C11: ='Data Sheet'!C29 -> 1977 | D11: ='Data Sheet'!D29 -> 2079 | E11: ='Data Sheet'!E29 -> 2544 | F11: ='Data Sheet'!F29 -> 2409 | G11: ='Data Sheet'!G29 -> 2606 | H11: ='Data Sheet'!H29 -> 2987 | I11: ='Data Sheet'!I29 -> 3201 | ... K11: ='Data Sheet'!K29 -> 3744 | L11: =SUM(Quarters!H11:K11) -> 3362 | M11: =IF($L10>0,$L11/$L10,0) -> 0.23694411 | N11: =IF($L10>0,$L11/$L10,0) -> 0.23694411
A12: Net profit | B12: ='Data Sheet'!B30 -> 4151 | C12: ='Data Sheet'!C30 -> 4476 | D12: ='Data Sheet'!D30 -> 5214 | E12: ='Data Sheet'!E30 -> 6054 | F12: ='Data Sheet'!F30 -> 6748 | G12: ='Data Sheet'!G30 -> 7995 | H12: ='Data Sheet'!H30 -> 8879 | I12: ='Data Sheet'!I30 -> 10120 | ... K12: ='Data Sheet'!K30 -> 10649 | L12: =SUM(Quarters!H12:K12) -> 10795 | M12: =M10-M11*M10 -> 10663.375 | N12: =N10-N11*N10 -> 9876.9514
A13: EPS | B13: =IF('Data Sheet'!B93>0,B12/'Data Sheet'!B93,0) -> 19.182957 | C13: =IF('Data Sheet'!C93>0,C12/'Data Sheet'!C93,0) -> 20.681052 | D13: =IF('Data Sheet'!D93>0,D12/'Data Sheet'!D93,0) -> 24.088704 | E13: =IF('Data Sheet'!E93>0,E12/'Data Sheet'!E93,0) -> 27.966924 | F13: =IF('Data Sheet'!F93>0,F12/'Data Sheet'!F93,0) -> 31.171471 | G13: =IF('Data Sheet'!G93>0,G12/'Data Sheet'!G93,0) -> 34.027068 | H13: =IF('Data Sheet'!H93>0,H12/'Data Sheet'!H93,0) -> 37.789411 | I13: =IF('Data Sheet'!I93>0,I12/'Data Sheet'!I93,0) -> 43.071161 | ... K13: =IF('Data Sheet'!K93>0,K12/'Data Sheet'!K93,0) -> 45.322608 | L13: =IF('Data Sheet'!$B6>0,'Profit & Loss'!L12/'Data Sheet'!$B6,0) -> 44.107583 | M13: =IF('Data Sheet'!$B6>0,'Profit & Loss'!M12/'Data Sheet'!$B6,0) -> 43.569775 | N13: =IF('Data Sheet'!$B6>0,'Profit & Loss'!N12/'Data Sheet'!$B6,0) -> 40.356503
A14: Price to earning | B14: =IF(B15>0,B15/B13,"") -> 45.326694 | C14: =IF(C15>0,C15/C13,"") -> 44.086249 | D14: =IF(D15>0,D15/D13,"") -> 55.35167 | E14: =IF(E15>0,E15/E13,"") -> 61.029236 | F14: =IF(F15>0,F15/F13,"") -> 73.737297 | G14: =IF(G15>0,G15/G13,"") -> 71.457816 | H14: =IF(H15>0,H15/H13,"") -> 54.212277 | I14: =IF(I15>0,I15/I13,"") -> 59.444648 | ... K14: =IF(K15>0,K15/K13,"") -> 49.839365 | L14: =IF(L13>0,L15/L13,0) -> 57.334812 | M14: =M25 -> 57.334812 | N14: =N25 -> 54.596997
A15: Price | B15: ='Data Sheet'!B90 -> 869.5 | C15: ='Data Sheet'!C90 -> 911.75 | D15: ='Data Sheet'!D90 -> 1333.35 | E15: ='Data Sheet'!E90 -> 1706.8 | F15: ='Data Sheet'!F90 -> 2298.5 | G15: ='Data Sheet'!G90 -> 2431.5 | H15: ='Data Sheet'!H90 -> 2048.65 | I15: ='Data Sheet'!I90 -> 2560.35 | ... K15: ='Data Sheet'!K90 -> 2258.85 | L15: ='Data Sheet'!B8 -> 2528.9 | M15: =M13*M14 -> 2498.0649 | N15: =N13*N14 -> 2203.3439
A17: RATIOS:
A18: Dividend Payout | B18: =IF('Data Sheet'!B30>0, 'Data Sheet'!B31/'Data Sheet'!B30, 0) -> 0.83257046 | C18: =IF('Data Sheet'!C30>0, 'Data Sheet'!C31/'Data Sheet'!C30, 0) -> 0.82037534 | D18: =IF('Data Sheet'!D30>0, 'Data Sheet'!D31/'Data Sheet'!D30, 0) -> 0.82853855 | E18: =IF('Data Sheet'!E30>0, 'Data Sheet'!E31/'Data Sheet'!E30, 0) -> 0.78493558 | F18: =IF('Data Sheet'!F30>0, 'Data Sheet'!F31/'Data Sheet'!F30, 0) -> 0.80023711 | G18: =IF('Data Sheet'!G30>0, 'Data Sheet'!G31/'Data Sheet'!G30, 0) -> 1.1904315 | H18: =IF('Data Sheet'!H30>0, 'Data Sheet'!H31/'Data Sheet'!H30, 0) -> 0.89987611 | I18: =IF('Data Sheet'!I30>0, 'Data Sheet'!I31/'Data Sheet'!I30, 0) -> 0.90563241 | ... K18: =IF('Data Sheet'!K30>0, 'Data Sheet'!K31/'Data Sheet'!K30, 0) -> 1.1695934
A19: OPM | B19: =IF(B6>0,B6/B4,0) -> 0.18362021 | C19: =IF(C6>0,C6/C4,0) -> 0.19082082 | D19: =IF(D6>0,D6/D4,0) -> 0.21097201 | E19: =IF(E6>0,E6/E4,0) -> 0.22589672 | F19: =IF(F6>0,F6/F4,0) -> 0.24786969 | G19: =IF(G6>0,G6/G4,0) -> 0.24721443 | H19: =IF(H6>0,H6/H4,0) -> 0.24514739 | I19: =IF(I6>0,I6/I4,0) -> 0.23352592 | ... L19: =IF(L6>0,L6/L4,0) -> 0.23177637
G22: TRENDS: | H22: 10 YEARS | I22: 7 YEARS | J22: 5 YEARS | K22: 3 YEARS | L22: RECENT | M22: BEST | N22: WORST
G23: Sales Growth | H23: =IF(B4=0,"",POWER($K4/B4,1/9)-1) -> 0.077707146 | I23: =IF(D4=0,"",POWER($K4/D4,1/7)-1) -> 0.0854952 | J23: =IF(F4=0,"",POWER($K4/F4,1/5)-1) -> 0.096718749 | K23: =IF(H4=0,"",POWER($K4/H4, 1/3)-1) -> 0.063703284 | L23: =IF(ISERROR(MAX(IF(J4=0,"",(K4-J4)/J4),IF(K4=0,"",(L4-K4)/K4))),"",MAX(IF(J4=0,"",(K4-J4)/J4),IF(K4=0,"",(L4-K4)/K4))) -> 0.019791263 | M23: =MAX(K23:L23) -> 0.063703284 | N23: =MIN(H23:L23) -> 0.019791263
G24: OPM | H24: =IF(SUM(B4:$K$4)=0,"",SUMPRODUCT(B19:$K$19,B4:$K$4)/SUM(B4:$K$4)) -> 0.22924072 | I24: =IF(SUM(E4:$K$4)=0,"",SUMPRODUCT(E19:$K$19,E4:$K$4)/SUM(E4:$K$4)) -> 0.23855461 | J24: =IF(SUM(G4:$K$4)=0,"",SUMPRODUCT(G19:$K$19,G4:$K$4)/SUM(G4:$K$4)) -> 0.23900011 | K24: =IF(SUM(I4:$K$4)=0, "", SUMPRODUCT(I19:$K$19,I4:$K$4)/SUM(I4:$K$4)) -> 0.2351816 | L24: =L19 -> 0.23177637 | M24: =MAX(K24:L24) -> 0.2351816 | N24: =MIN(H24:L24) -> 0.22924072
G25: Price to Earning | H25: =IF(ISERROR(AVERAGEIF(B14:$L14,">0")),"",AVERAGEIF(B14:$L14,">0")) -> 56.68993 | I25: =IF(ISERROR(AVERAGEIF(E14:$L14,">0")),"",AVERAGEIF(E14:$L14,">0")) -> 59.853077 | J25: =IF(ISERROR(AVERAGEIF(G14:$L14,">0")),"",AVERAGEIF(G14:$L14,">0")) -> 57.343013 | K25: =IF(ISERROR(AVERAGEIF(I14:$L14,">0")),"",AVERAGEIF(I14:$L14,">0")) -> 54.596997 | L25: =L14 -> 57.334812 | M25: =MAX(K25:L25) -> 57.334812 | N25: =MIN(H25:L25) -> 54.596997
B26: =B10+B9 -> 6043 | C26: =B6-B8 -> 5557
A28: Sales groeth yoy | C28: =C4/B4-1 -> 0.030323743 | D28: =D4/C4-1 -> 0.071859357 | E28: =E4/D4-1 -> 0.10592207 | F28: =F4/E4-1 -> 0.012032562 | G28: =G4/F4-1 -> 0.18211296 | H28: =H4/G4-1 -> 0.11520796 | I28: =I4/H4-1 -> 0.15509286 | J28: =J4/I4-1 -> 0.021723341 | K28: =K4/J4-1 -> 0.019791263
A29: Gross profit | B29: ='Data Sheet'!B17-'Data Sheet'!B18-'Data Sheet'!B19-'Data Sheet'!B20-'Data Sheet'!B21 -> 15810 | C29: ='Data Sheet'!C17-'Data Sheet'!C18-'Data Sheet'!C19-'Data Sheet'!C20-'Data Sheet'!C21 -> 16518 | D29: ='Data Sheet'!D17-'Data Sheet'!D18-'Data Sheet'!D19-'Data Sheet'!D20-'Data Sheet'!D21 -> 17947 | E29: ='Data Sheet'!E17-'Data Sheet'!E18-'Data Sheet'!E19-'Data Sheet'!E20-'Data Sheet'!E21 -> 20128 | F29: ='Data Sheet'!F17-'Data Sheet'!F18-'Data Sheet'!F19-'Data Sheet'!F20-'Data Sheet'!F21 -> 20773 | G29: ='Data Sheet'!G17-'Data Sheet'!G18-'Data Sheet'!G19-'Data Sheet'!G20-'Data Sheet'!G21 -> 23275 | H29: ='Data Sheet'!H17-'Data Sheet'!H18-'Data Sheet'!H19-'Data Sheet'!H20-'Data Sheet'!H21 -> 25881 | I29: ='Data Sheet'!I17-'Data Sheet'!I18-'Data Sheet'!I19-'Data Sheet'!I20-'Data Sheet'!I21 -> 27903 | ... K29: ='Data Sheet'!K17-'Data Sheet'!K18-'Data Sheet'!K19-'Data Sheet'!K20-'Data Sheet'!K21 -> 31363
A30: grosa profit margin | B30: =B29/B4 -> 0.49120736 | C30: =C29/C4 -> 0.49810024 | D30: =D29/D4 -> 0.50490927 | E30: =E29/E4 -> 0.51203256 | F30: =F29/F4 -> 0.52215771 | G30: =G29/G4 -> 0.49491792 | H30: =H29/H4 -> 0.49347901 | I30: =I29/I4 -> 0.46059756 | ... K30: =K29/K4 -> 0.49687109
A31: EBITDA Margin | B31: =B6/B4 -> 0.18362021 | C31: =C6/C4 -> 0.19082082 | D31: =D6/D4 -> 0.21097201 | E31: =E6/E4 -> 0.22589672 | F31: =F6/F4 -> 0.24786969 | G31: =G6/G4 -> 0.24721443 | H31: =H6/H4 -> 0.24514739 | I31: =I6/I4 -> 0.23352592 | ... K31: =K6/K4 -> 0.23515153
A32: EBIT | B32: =B6-B8+B7 -> 6043 | C32: =C6-C8+C7 -> 6502 | D32: =D6-D8+D7 -> 7332 | E32: =E6-E8+E7 -> 8637 | F32: =F6-F8+F7 -> 9283 | G32: =G6-G8+G7 -> 10722 | H32: =H6-H8+H7 -> 11985 | I32: =I6-I8+I7 -> 13458 | ... K32: =K6-K8+K7 -> 14810
A33: EBIT MARGIN | B33: =B32/B4 -> 0.18775244 | C33: =C32/C4 -> 0.19606779 | D33: =D32/D4 -> 0.20627374 | E33: =E32/E4 -> 0.21971509 | F33: =F32/F4 -> 0.23334087 | G33: =G32/G4 -> 0.22799183 | H33: =H32/H4 -> 0.22852076 | I33: =I32/I4 -> 0.22215253 | ... K33: =K32/K4 -> 0.23462873
A35: Net Profit Margin | B35: =B12/B4 -> 0.12896912 | C35: =C12/C4 -> 0.13497377 | D35: =D12/D4 -> 0.1466873 | E35: =E12/E4 -> 0.15400661 | F35: =F12/F4 -> 0.16962019 | G35: =G12/G4 -> 0.1700051 | H35: =H12/H4 -> 0.16929794 | I35: =I12/I4 -> 0.16705183 | ... K35: =K12/K4 -> 0.16870772
A37: Eps Yoy | C37: =C13/B13-1 -> 0.078095099 | D37: =D13/C13-1 -> 0.16477172 | E37: =E13/D13-1 -> 0.16099744 | F37: =F13/E13-1 -> 0.11458346 | G37: =G13/F13-1 -> 0.091609332 | H37: =H13/G13-1 -> 0.11056911 | I37: =I13/H13-1 -> 0.13976799 | J37: =J13/I13-1 -> 0.015513834 | K37: =K13/J13-1 -> 0.036197334
A39: Dividend | B39: =B18*B13 -> 15.971163 | C39: =C18*C13 -> 16.966225 | D39: =D18*D13 -> 19.95842 | E39: =E18*E13 -> 21.952234 | F39: =F18*F13 -> 24.944568 | G39: =G18*G13 -> 40.506895 | H39: =H18*H13 -> 34.005788 | I39: =I18*I13 -> 39.006639 | ... K39: =K18*K13 -> 53.009023
A40: DPS YOY | C40: =C39/B39-1 -> 0.062303632 | D40: =D39/C39-1 -> 0.17636188 | E40: =E39/D39-1 -> 0.099898369 | F40: =F39/E39-1 -> 0.13631114 | G40: =G39/F39-1 -> 0.6238764 | H40: =H39/G39-1 -> -0.16049383 | I40: =I39/H39-1 -> 0.14705882 | J40: =J39/I39-1 -> 0.076923077 | K40: =K39/J39-1 -> 0.26190476
A42: Market Cap | B42: ='Data Sheet'!B93*'Data Sheet'!B90 -> 188151.1 | C42: ='Data Sheet'!C93*'Data Sheet'!C90 -> 197330.05 | D42: ='Data Sheet'!D93*'Data Sheet'!D90 -> 288603.61 | E42: ='Data Sheet'!E93*'Data Sheet'!E90 -> 369471 | F42: ='Data Sheet'!F93*'Data Sheet'!F90 -> 497579.28 | G42: ='Data Sheet'!G93*'Data Sheet'!G90 -> 571305.24 | H42: ='Data Sheet'!H93*'Data Sheet'!H90 -> 481350.8 | I42: ='Data Sheet'!I93*'Data Sheet'!I90 -> 601579.84 | ... K42: ='Data Sheet'!K93*'Data Sheet'!K90 -> 530739.4
A43: debt | B43: ='Data Sheet'!B59 -> 177 | C43: ='Data Sheet'!C59 -> 277 | D43: ='Data Sheet'!D59 -> 0 | E43: ='Data Sheet'!E59 -> 99 | F43: ='Data Sheet'!F59 -> 0 | G43: ='Data Sheet'!G59 -> 0 | H43: ='Data Sheet'!H59 -> 1043 | I43: ='Data Sheet'!I59 -> 1219 | ... K43: ='Data Sheet'!K59 -> 1648
A44: cash | B44: ='Data Sheet'!B69 -> 3009 | C44: ='Data Sheet'!C69 -> 1828 | D44: ='Data Sheet'!D69 -> 3485 | E44: ='Data Sheet'!E69 -> 3757 | F44: ='Data Sheet'!F69 -> 5113 | G44: ='Data Sheet'!G69 -> 4471 | H44: ='Data Sheet'!H69 -> 3846 | I44: ='Data Sheet'!I69 -> 4678 | ... K44: ='Data Sheet'!K69 -> 7554
